Workbook
Name at: 'C1'!#REF!

Sheet Sheet3
A1: SUPERVISOR | B1: IGL | F1: SUPERVISOR | G1: IGL
A3: Count of WO NO | B3: Column Labels | G3: Column Labels
A4: Row Labels | B4: CHALLENGER | C4: Grand Total | G4: CHALLENGER | I4: Total TOTAL ESTIMATED COST (SERVICE ITEMS) | J4: Total BILLED/PARTIALLY BILLED COST
A5: AUDITED | B5: 8 | C5: 8 | F5: Row Labels | G5: TOTAL ESTIMATED COST (SERVICE ITEMS) | H5: BILLED/PARTIALLY BILLED COST
A6: FOR AUDIT | B6: 42 | C6: 42 | F6: AUDITED | G6: 309761.23 | H6: 79479.1 | I6: 309761.23 | J6: 79479.1
A7: NO COC | B7: 18 | C7: 18 | F7: FOR AUDIT | G7: 4834813.4 | H7: 368944.03 | I7: 4834813.4 | J7: 368944.03
A8: PAID | B8: 1 | C8: 1 | F8: NO COC | G8: 1976088.5 | I8: 1976088.5
A9: Transferred to DCB (point person for OLDT) | B9: 5 | C9: 5 | F9: PAID | G9: 80751.9 | H9: 84452.5 | I9: 80751.9 | J9: 84452.5
A10: SCHED/ INPRG | B10: 39 | C10: 39 | F10: Transferred to DCB (point person for OLDT) | G10: 169350.32 | I10: 169350.32
A11: Grand Total | B11: 113 | C11: 113 | F11: SCHED/ INPRG | G11: 3937935.2 | I11: 3937935.2
F12: Grand Total | G12: 11308700 | H12: 532875.63 | I12: 11308700 | J12: 532875.63
F14: Row Labels | G14: Sum of TOTAL ESTIMATED COST (SERVICES) | H14: Sum of BILLED / PARTIALLY BILLED COST | I14: Sum of TOTAL ESTIMATED COST (SERVICES) | J14: Sum of BILLED / PARTIALLY BILLED COST
F15: AUDITED | G15: 309761.23 | H15: 79479.1 | K15: 309761.23 | L15: 79479.1
F16: FOR AUDIT | G16: 4366131.1 | H16: 368944.03 | K16: 4366131.1 | L16: 368944.03
F17: NO COC | G17: 1784857.6 | K17: 1784857.6
F18: ON GOING MATERIAL RETURN | G18: 80751.9 | H18: 35552.91 | K18: 80751.9 | L18: 35552.91
F19: SCHED/ INPRG | G19: 4597848.4 | I19: 44676.99 | K19: 4642525.4
F20: Grand Total | G20: 11139350 | H20: 483976.04 | I20: 44676.99 | K20: 11184027 | L20: 483976.04

Sheet SUPV
A1: ME185130 | B1: JEMUEL PERALTA
A2: ME168168 | B2: CRIS EMMANUEL GUEVARRA | CV2: EXT
A3: ME168443 | B3: DEAN CARL BORJAL
A4: ME194579 | B4: IAN PATRICK PEREZ
A5: ME188111 | B5: JUSTINE RAMOS
A6: ME166067 | B6: ISAN CARLO LAZARO | CV6: P2006000921',
A7: ME173899 | B7: JUNILO MICHAEL FLORES
A8: ME189046 | B8: REYZON MATIENZO
A9: ME177199 | B9: MARC JOSEPH FERRER
A10: ME155242 | B10: RONILO JR GANGE
A11: =VLOOKUP(#REF!,'[1]List of Work Orders'!$A:$I,9,FALSE) -> #REF!

Sheet Justifications
A1: Applicant facility not ready
A2: Applicant holds execution
A3: Conjuct work order not released / completed
A4: ECQ (Site inaccessible)
A5: Energized on site but insufficient contract amount / No PO (System error)
A6: Energized on site but with back job
A7: Group quarantine (Manpower)
A8: MEP (Meralco Electrification Project)
A9: Materials unavailability
A10: No pole stake
A11: Road access problem
A12: Special LGU permits
... A21: With system error issue but completed at site
A23: Value | B23: Scope | C23: Start and End Dates | D23: Required Attachment (inclusive of Start and End dates) | E23: Required Remarks (inclusive of Start and End dates
A24: Applicant holds execution | B24: customer-related | C24: Start Date: WMTRL Date | D24: Communication with CRS/Customer | E24: Notes on customer-related concern/s
C25: End Date: Date of resolution with CRS/Customer | E25: Reason/s of applicant holding execution
A26: Third party concern (Applicant-related compliance) | B26: delay caused by parties other than the applicant (eg. LGU, HOA - halts execution due to lack of applicant compliance) | C26: Start Date: Date from CRS/Design/PROW coordination | D26: Communication with CRS/Design/PROW | E26: Notes on third party-related concern/s
C27: End Date: Date of concern resolution | E27: Reason/s of delay casued by third party
A28: Third party concern (Other than the applicant) | B28: delay caused by parties other than the applicant (eg. Neighbor, LGU, HOA - halts execution or requests transfer of pole location/guying, etc.) | C28: Start Date: Date from CRS/Design/PROW coordination | D28: Communication with CRS/Design/PROW | E28: Notes on third party-related concern/s
C29: End Date: Date of concern resolution | E29: Reason/s of delay casued by third party
A30: With ROW problem | B30: expired or unavailable ROW/permit | C30: Start Date: Date from CRS/Design/PROW coordination | D30: Communication with CRS/Design/PROW | E30: Notes on ROW-related concern/s
C31: End Date: Date of concern resolution | E31: Reason/s of ROW problem
A32: Special LGU permits | B32: Permits not common to other LGUs - Contractor’s Tax (Antipolo LGU), Baliwag LGU, ASEANA, BESC Permit Acquisition (BGC) | C32: Start Date: Start date of permit acquisition processing | D32: Communication with concerned party | E32: Notes on permit-related concern/s
C33: End Date: Permit acquisition | E33: Reason/s of permit/s problem
A34: No pole stake | B34: applicable only to subdivision developments; not applicable if proof of pole stake is available in EAM | C34: Start Date: WMTRL Date | D34: Communication with concerned party | E34: Notes on pole stake-related concern/s
C35: End Date: Date of concern resolution
A36: Conjuct work order not released/completed | B36: conjuct work order number not released or not yet completed | C36: Start Date: Date of coordination with CRS/Design | D36: Communication with CRS/Design | E36: Notes on conjuct WO details
C37: End Date: Date of concern resolution | E37: Reason/s of conjuct WO delay in completion
A38: With minor design modifications | B38: Minor design modifications (no change in design scheme / no additional station/task) | C38: Start Date: Date of coordination with Design | D38: Communication with Design | E38: Notes on design modification details
C39: End Date: Date of concern resolution | E39: Reason/s of design modification
A40: With major design modifications | B40: Major design modifications (with changes in design scheme / with additional station/task) | C40: Start Date: Date of coordination with Design | D40: Communication with Design | E40: Notes on design modification details
C41: End Date: Date released to construction after WO reversion | E41: Reason/s of design modification
A42: With pole / drainage /digging / manhole / pole attachment issue | B42: Location problem not related to ROW problem and/or Thrird party concern | C42: Start Date: Date from Design/PROW coordination | D42: Communication with Design/PROW | E42: Notes on issues with pole / drainage / digging / manhole / pole attachment
C43: End Date: Date of concern resolution
A44: Energized on site but with back job | B44: actual energization date must be indicated in the WO specs | C44: Start Date: Date energized | D44: Communication with vendor | E44: Notes on back job details
C45: End Date: Date of completion of back job/WO FCOMP/Date of concern resolution | D45: WO details/milestones | E45: Reason/s of back job
A46: Energized on site but insufficient contract amount / No PO (System error) | B46: actual energization date must be indicated in the WO specs | C46: Start Date: Date energized | D46: Communication with PCT/NCOM | E46: Notes on contract insufficiency
C47: End Date: Date of completion of budget amendment/WO FCOMP/Date of concern resolution | D47: WO details/milestones
A48: Materials unavailability | B48: item code and desciption must be indicated in justification | C48: Start Date: Date material unavailability | D48: Communication with Stores/MMO | E48: Notes on materials unavailability
C49: End Date: Date of stock availability | E49: List of unavailable items
A50: With scheduled PAI | B50: work request number must be indicated in justification | C50: Start Date: Date from PAI request | D50: PAI details | E50: Notes on PAI details
C51: End Date: Date of PAI execution

Sheet UG-SLEM
D1: PROJECTS | E1: F | K1: F | L1: 45293 | X1: PERFORMANCE | AC1: RED(Above 50Days) | AH1: NEW KPI (Starting October 2021) | AL1: COMPUTATION: FOR FCOMP | AQ1: FOR COMP | AT1: (-5) | AU1: 0.75 aspiration | BB1: 0.75 aspiration | BC1: REMARKS | BE1: CERTIFICATE OF COMPLETION | BI1: FIELD AUDIT | BK1: RE-WORK | BO1: MATERIAL BALANCING | BQ1: TRANSMITTAL TO METER | BS1: FOR OLDT DETAILS
A2: Date Received Jacket from P&S | B2: Date Received Awarding of Wo | C2: VIP | D2: WO INITIATOR | E2: WO NO | F2: DESCRIPTION | G2: LOCATION | H2: MUNICIPALITY | I2: AREA OF RESPONSIBILITY | J2: VENDOR REMARKS (free text) | K2: C1 REMARKS (with or without issue) | L2: ASSIGNED | M2: STATUS | N2: SUPERVISOR | O2: C1 CONTRACTOR MANHOUR | P2: TOTAL MANHOURS | Q2: APPLIED LOAD | R2: TYPE | S2: TOTAL PLANNED PROJECT COST | T2: TOTAL ESTIMATED COST (SERVICES) | U2: BILLED / PARTIALLY BILLED COST | V2: % BILLED | W2: DATE WMTRL | X2: DATE SCHED | Y2: DATE RECEIVED BY VC | Z2: ACTUAL DATE COMPLETED ON SITE | AA2: DATE FCOMP | AB2: DATE COMP | AC2: # of days WMTRL TO FCOMP APT Without Exclusion (SPT) | AD2: # of days SCHED TO FCOMP | AE2: # of days COMP | AF2: (0.75) DATE NEEDED FOR WMTRL TO FCOMP | AG2: (0.95) DATE NEEDED FOR FCOMP | AH2: (50 DAYS) DATE NEEDED FOR WMTRL TO FCOMP | AI2: COMPUTED INDEX (WMTRL TO FCOMP) CCTI Without Exclusion | AJ2: COMPUTED INDEX (COMP) | AK2: SPT(M) | AL2: SPT(L) | AM2: 0.75 DURATION (DAYS) | AN2: 0.95 DURATION (DAYS) | AO2: TARGET DAYS | AP2: SPT(M) for comp | AQ2: DURATION (DAYS)COMP | AR2: TARGET DAYS (COMP) | AS2: DATE NEEDED TO COMP | AT2: TARGET DATE TO COMP | AU2: REASON (FOR EXCLUSION) | AV2: FOR CCTI EXCLUSION (Y/N) | AW2: ENCODED IN EAM (Y/N) | AX2: VALIDATED BY DCSAM (Y/N) | AY2: For APT Exclusion (Y/N) | AZ2: START DATE | BA2: DURATION FOR EXCLUSION | BB2: END DATE (FOR EXCLUSION) | BC2: REMARKS / FOLLOW UP BY | BD2: REMARKS 2 | BE2: DATE NEEDED TO SUBMIT COC | BF2: AGEING SUBMISSION OF COC | BG2: DATE COMPLETED (FROM COC) | BH2: ACTUAL RECEIVED COC | BI2: DATE AUDIT | BJ2: BY: | BK2: W/ BACK JOB | BL2: BACKJOB TAGGED IN EAM? RE-WORK | BM2: DATE RECEIVED BY CONTRACTOR | BN2: DATE CORRECTED | BO2: DATE MATERIAL BALANCING | BP2: BY | BQ2: Y/N | BR2: EMAILED TO METER | BS2: DT CORRECTION METHOD | BT2: TLN | BU2: WITH POLE REPL? | BV2: ACTUAL FIELD STATUS | BW2: REMARKS3 | BX2: ABF PRINTED BY (FOR AUDIT) | BY2: DATE PRINTED OF POLE TAG FABRICATION FORM | BZ2: POLE / TLN TAGS | CA2: Days for Exclusion based on emails to concerned office/PCTs (Due to customer only - APT) | CB2: APT with Exclusion | CC2: Days for Exclusion based on emails to concerned office/PCTs (All reason - CCTI) | CD2: Duration for CCTI with exclusion | CE2: CCTI With Exclusion | CF2: Meralco/Customer Reason | CG2: Issue Remarks | CH2: CURRENT CCTI
A3: 45238 | B3: 45236 | D3: CBG | E3: X23083339380 | F3: TANG KUNQUAN | G3: QUIRINO, TAMBO, PARANAQUE | H3: PARAÑAQUE CITY | I3: PARAÑAQUE | J3: UG WO; with issue on pole location | K3: UG | L3: ECOM | M3: COMP | N3: UG | O3: 139.3524 | P3: 659.83 | Q3: 1062 | R3: NEW | S3: 4081533.1 | T3: 132841.45 | U3: 94987.61 | V3: =U3/T3 -> 0.71504497 | W3: 45233.619 | X3: 45233.619 | Y3: 45236.366 | AA3: 45328.546 | AB3: 45581.419 | AC3: =AA3-W3 -> 94.926389 | AD3: =AA3-X3 -> 94.926389 | AE3: =AB3-AA3 -> 252.87361 | AF3: =W3+AO3 -> 45248.267 | AG3: =W3+AN3 -> 45255.972 | AH3: =W3+50 -> 45283.619 | AI3: =(0.3)*(AC3/AK3)+(0.7)*(AC3/AL3) -> 4.0343715 | AJ3: =AE3/AP3 -> 4.597702 | AK3: =IF(P3<51,20,(IF(P3<101,23,(IF(P3<201,26,IF(P3<301,28,IF(P3<401,30,(IF(P3<501,32,(IF(P3<1001,40,50))))))))))) -> 40 | AL3: =IF(Q3<51,36,(IF(Q3<101,34,(IF(Q3<201,32,IF(Q3<301,30,IF(Q3<401,28,(IF(Q3<501,26,(IF(Q3<1001,23,20))))))))))) -> 20 | AM3: =(0.75)/((0.3/AK3)+(0.7/AL3)) -> 17.647059 | AN3: =(0.95)/((0.3/AK3)+(0.7/AL3)) -> 22.352941 | AO3: =AM3-3 -> 14.647059 | AP3: =IF(P3<51,40,(IF(P3<101,42,(IF(P3<201,44,IF(P3<301,46,IF(P3<401,48,(IF(P3<501,50,(IF(P3<1001,55,60))))))))))) -> 55 | AQ3: =0.8*AP3 -> 44 | AR3: =AQ3-5 -> 39 | AS3: =AA3+AQ3 -> 45372.546 | AT3: =AS3-5 -> 45367.546 | BC3: PAID | BF3: 3 | BG3: 45327 | BH3: 45372 | BI3: 45548 | BJ3: ECI | BK3: N | BQ3: Y | BX3: PDZC | BY3: 45238 | BZ3: C5-0512, 116398, C5-8057, 518496, C5-8058 | CB3: =AC3-CA3 -> 94.926389 | CD3: =AC3-CC3 -> 94.926389 | CE3: =(0.3)*(CD3/AK3)+(0.7)*(CD3/AL3) -> 4.0343715 | CH3: =(0.3)*((NOW()-W3)/AK3)+(0.7)*((NOW()-W3)/AL3) -> 28.122134 | CI3: =IF(AB3="","PENDING COMP",(AB3-AA3)/AP3) -> 4.597702 | CK3: =IF(R3="NEW","REV","NON-REV") -> REV
A4: 45310 | D4: CBG | E4: X23083306750 | F4: VITACARE UNIMED HOSPITAL AND MEDICAL CENTER CORP. | G4: DAANG-HARI RD., MOLINO IV, BACOOR | H4: BACOOR CITY | I4: DASMA | K4: UG | L4: POWERHOUSE | M4: TECO | N4: UG | O4: 72.5251 | P4: 585.55 | Q4: 1700 | R4: NEW | S4: 3336508.3 | T4: 36496.41 | V4: =U4/T4 -> 0 | W4: 45295.606 | X4: 45295.606 | Y4: 45296.903 | AA4: 45314.547 | AB4: 45723.674 | AC4: =AA4-W4 -> 18.941667 | AD4: =AA4-X4 -> 18.941667 | AE4: =AB4-AA4 -> 409.12639 | AF4: =W4+AO4 -> 45310.253 | AG4: =W4+AN4 -> 45317.958 | AH4: =W4+50 -> 45345.606 | AI4: =(0.3)*(AC4/AK4)+(0.7)*(AC4/AL4) -> 0.80502083 | AJ4: =AE4/AP4 -> 7.4386616 | AK4: =IF(P4<51,20,(IF(P4<101,23,(IF(P4<201,26,IF(P4<301,28,IF(P4<401,30,(IF(P4<501,32,(IF(P4<1001,40,50))))))))))) -> 40 | AL4: =IF(Q4<51,36,(IF(Q4<101,34,(IF(Q4<201,32,IF(Q4<301,30,IF(Q4<401,28,(IF(Q4<501,26,(IF(Q4<1001,23,20))))))))))) -> 20 | AM4: =(0.75)/((0.3/AK4)+(0.7/AL4)) -> 17.647059 | AN4: =(0.95)/((0.3/AK4)+(0.7/AL4)) -> 22.352941 | AO4: =AM4-3 -> 14.647059 | AP4: =IF(P4<51,40,(IF(P4<101,42,(IF(P4<201,44,IF(P4<301,46,IF(P4<401,48,(IF(P4<501,50,(IF(P4<1001,55,60))))))))))) -> 55 | AQ4: =0.8*AP4 -> 44 | AR4: =AQ4-5 -> 39 | AS4: =AA4+AQ4 -> 45358.547 | AT4: =AS4-5 -> 45353.547 | BC4: NO COC | BF4: 3 | BQ4: Y | BY4: 45315 | BZ4: CR8-5430, CR8-8016, CR8-8016, 182943 | CB4: =AC4-CA4 -> 18.941667 | CD4: =AC4-CC4 -> 18.941667 | CE4: =(0.3)*(CD4/AK4)+(0.7)*(CD4/AL4) -> 0.80502083 | CH4: =(0.3)*((NOW()-W4)/AK4)+(0.7)*((NOW()-W4)/AL4) -> 25.487724 | CI4: =IF(AB4="","PENDING COMP",(AB4-AA4)/AP4) -> 7.4386616 | CK4: =IF(R4="NEW","REV","NON-REV") -> REV
A5: 45350 | B5: 45356 | D5: CBG | E5: X23062134423 | F5: SM DEVELOPMENT CORPORATION, | G5: TOWER C, BLOOM RESIDENCES, PARANAQUE | H5: PARAÑAQUE CITY | I5: PARANAQUE | J5: Conjunct with UG, target itayo poste March 6 | L5: AVECO | M5: COMP | N5: UG | O5: 115.33 | P5: 507.57 | Q5: 1563.3 | R5: NEW | S5: 3001400.5 | T5: 89877.04 | V5: =U5/T5 -> 0 | W5: 45310.658 | X5: 45314.61 | Y5: 45351 | AA5: 45401.602 | AB5: 45694 | AC5: =AA5-W5 -> 90.944444 | AD5: =AA5-X5 -> 86.991667 | AE5: =AB5-AA5 -> 292.39792 | AF5: =W5+AO5 -> 45325.526 | AG5: =W5+AN5 -> 45333.291 | AH5: =W5+50 -> 45360.658 | AI5: =(0.3)*(AC5/AK5)+(0.7)*(AC5/AL5) -> 3.8172334 | AJ5: =AE5/AP5 -> 6.6454072 | AK5: =IF(O5<51,20,(IF(O5<101,23,(IF(O5<201,26,IF(O5<301,28,IF(O5<401,30,(IF(O5<501,32,(IF(O5<1001,40,50))))))))))) -> 26 | AL5: =IF(P5<51,36,(IF(P5<101,34,(IF(P5<201,32,IF(P5<301,30,IF(P5<401,28,(IF(P5<501,26,(IF(P5<1001,23,20))))))))))) -> 23 | AM5: =(0.75)/((0.3/AK5)+(0.7/AL5)) -> 17.868526 | AN5: =(0.95)/((0.3/AK5)+(0.7/AL5)) -> 22.633466 | AO5: =AM5-3 -> 14.868526 | AP5: =IF(O5<51,40,(IF(O5<101,42,(IF(O5<201,44,IF(O5<301,46,IF(O5<401,48,(IF(O5<501,50,(IF(O5<1001,55,60))))))))))) -> 44 | AQ5: =0.8*AP5 -> 35.2 | AR5: =AQ5-5 -> 30.2 | AS5: =AA5+AQ5 -> 45436.802 | AT5: =AS5-5 -> 45431.802 | BC5: ON GOING MAT RETURN | BD5: FULLY BILLED | BE5: =AA5+3 -> 45404.602 | BF5: =IF(ISBLANK(AA5),0,IF(ISBLANK(BH5),($L$1-BE5),(BH5-BE5))) -> 198.39792 | BG5: 45394 | BH5: 45603 | BI5: 45638 | BJ5: ECI | BK5: N | BQ5: Y | CB5: =AC5-CA5 -> 90.944444 | CD5: =AC5-CC5 -> 90.944444 | CE5: =(0.3)*(CD5/AK5)+(0.7)*(CD5/AL5) -> 3.8172334 | CH5: =(0.3)*((NOW()-W5)/AK5)+(0.7)*((NOW()-W5)/AL5) -> 24.540038 | CI5: =IF(AB5="","PENDING COMP",(AB5-AA5)/AP5) -> 6.6454072 | CK5: =IF(R5="NEW","REV","NON-REV") -> REV
A6: 45383 | B6: 45376 | D6: CBG | E6: X24010270067 | F6: PHINMA PROPERTY HOLDINGS CORPORATION | G6: CHROMIUM, METROTOWNE, LAS PINAS CITY | H6: LAS PIÑAS CITY | I6: PARAÑAQUE | J6: UG supervisor | K6: W/O ISSUE | L6: POWERHOUSE | M6: FCOMP | N6: UG | O6: 45.3098 | P6: 375.5 | Q6: 1965.8 | R6: NEW | S6: 3158370.5 | T6: 46889.1 | V6: =U6/T6 -> 0 | W6: 45370.465 | X6: 45383.364 | Y6: 45373 | AA6: 45398.693 | AC6: =AA6-W6 -> 28.228472 | AD6: =AA6-X6 -> 15.329167 | AE6: =AB6-AA6 -> -45398.693 | AF6: =W6+AO6 -> 45386.215 | AG6: =W6+AN6 -> 45394.215 | AH6: =W6+50 -> 45420.465 | AI6: =(0.3)*(AC6/AK6)+(0.7)*(AC6/AL6) -> 1.1291389 | AJ6: =AE6/AP6 -> -1134.9673 | AK6: =IF(O6<51,20,(IF(O6<101,23,(IF(O6<201,26,IF(O6<301,28,IF(O6<401,30,(IF(O6<501,32,(IF(O6<1001,40,50))))))))))) -> 20 | AL6: =IF(P6<51,36,(IF(P6<101,34,(IF(P6<201,32,IF(P6<301,30,IF(P6<401,28,(IF(P6<501,26,(IF(P6<1001,23,20))))))))))) -> 28 | AM6: =(0.75)/((0.3/AK6)+(0.7/AL6)) -> 18.75 | AN6: =(0.95)/((0.3/AK6)+(0.7/AL6)) -> 23.75 | AO6: =AM6-3 -> 15.75 | AP6: =IF(O6<51,40,(IF(O6<101,42,(IF(O6<201,44,IF(O6<301,46,IF(O6<401,48,(IF(O6<501,50,(IF(O6<1001,55,60))))))))))) -> 40 | AQ6: =0.8*AP6 -> 32 | AR6: =AQ6-5 -> 27 | AS6: =AA6+AQ6 -> 45430.693 | AT6: =AS6-5 -> 45425.693 | BC6: NO COC | BE6: =AA6+3 -> 45401.693 | BF6: =IF(ISBLANK(AA6),0,IF(ISBLANK(BH6),($L$1-BE6),(BH6-BE6))) -> -108.69306 | BQ6: Y | BY6: 45384 | BZ6: CU8-1255, 520351, CU8-8053 | CB6: =AC6-CA6 -> 28.228472 | CD6: =AC6-CC6 -> 28.228472 | CE6: =(0.3)*(CD6/AK6)+(0.7)*(CD6/AL6) -> 1.1291389 | CH6: =(0.3)*((NOW()-W6)/AK6)+(0.7)*((NOW()-W6)/AL6) -> 20.994085 | CI6: =IF(AB6="","PENDING COMP",(AB6-AA6)/AP6) -> PENDING COMP | CK6: =IF(R6="NEW","REV","NON-REV") -> REV
E7: X24041165129 | F7: LIGHT RAIL MANILA CORPORATION | G7: NINOY AQUINO, STO. NINO, PARANAQUE | H7: PARANAQUE CITY | I7: PARAÑAQUE | L7: SLEM | M7: FCOMP | N7: SLEM | P7: 136.13 | R7: NEW | V7: =U7/T7 -> #DIV/0! | W7: 45408 | AA7: 45800 | AE7: =AB7-AA7 -> -45800 | AF7: =W7+AO7 -> 45429.207 | AG7: =W7+AN7 -> 45438.662 | AH7: =W7+50 -> 45458 | AI7: =(0.3)*(AC7/AK7)+(0.7)*(AC7/AL7) -> 0 | AJ7: =AE7/AP7 -> -1040.9091 | AK7: =IF(P7<51,20,(IF(P7<101,23,(IF(P7<201,26,IF(P7<301,28,IF(P7<401,30,(IF(P7<501,32,(IF(P7<1001,40,50))))))))))) -> 26 | AL7: =IF(Q7<51,36,(IF(Q7<101,34,(IF(Q7<201,32,IF(Q7<301,30,IF(Q7<401,28,(IF(Q7<501,26,(IF(Q7<1001,23,20))))))))))) -> 36 | AM7: =(0.75)/((0.3/AK7)+(0.7/AL7)) -> 24.206897 | AN7: =(0.95)/((0.3/AK7)+(0.7/AL7)) -> 30.662069 | AO7: =AM7-3 -> 21.206897 | AP7: =IF(P7<51,40,(IF(P7<101,42,(IF(P7<201,44,IF(P7<301,46,IF(P7<401,48,(IF(P7<501,50,(IF(P7<1001,55,60))))))))))) -> 44 | AQ7: =0.8*AP7 -> 35.2 | AR7: =AQ7-5 -> 30.2 | AS7: =AA7+AQ7 -> 45835.2 | AT7: =AS7-5 -> 45830.2 | BF7: =IF(ISBLANK(AA7),0,IF(ISBLANK(BH7),($L$1-BE7),(BH7-BE7))) -> 45293 | CB7: =AC7-CA7 -> 0 | CD7: =AC7-CC7 -> 0 | CE7: =(0.3)*(CD7/AK7)+(0.7)*(CD7/AL7) -> 0 | CH7: =(0.3)*((NOW()-W7)/AK7)+(0.7)*((NOW()-W7)/AL7) -> 15.098488 | CI7: =IF(AB7="","PENDING COMP",(AB7-AA7)/AP7) -> PENDING COMP | CK7: =IF(R7="NEW","REV","NON-REV") -> REV
E8: X24041165310 | F8: LIGHT RAIL MANILA CORPORATION | G8: NINOY AQUINO, STO. NINO, PARANAQUE | H8: PARANAQUE CITY | I8: PARAÑAQUE | L8: SLEM | M8: FCOMP | N8: SLEM | P8: 136.13 | R8: NEW | V8: =U8/T8 -> #DIV/0! | W8: 45408 | AA8: 45811 | AE8: =AB8-AA8 -> -45811 | AF8: =W8+AO8 -> 45429.207 | AG8: =W8+AN8 -> 45438.662 | AH8: =W8+50 -> 45458 | AI8: =(0.3)*(AC8/AK8)+(0.7)*(AC8/AL8) -> 0 | AJ8: =AE8/AP8 -> -1041.1591 | AK8: =IF(P8<51,20,(IF(P8<101,23,(IF(P8<201,26,IF(P8<301,28,IF(P8<401,30,(IF(P8<501,32,(IF(P8<1001,40,50))))))))))) -> 26 | AL8: =IF(Q8<51,36,(IF(Q8<101,34,(IF(Q8<201,32,IF(Q8<301,30,IF(Q8<401,28,(IF(Q8<501,26,(IF(Q8<1001,23,20))))))))))) -> 36 | AM8: =(0.75)/((0.3/AK8)+(0.7/AL8)) -> 24.206897 | AN8: =(0.95)/((0.3/AK8)+(0.7/AL8)) -> 30.662069 | AO8: =AM8-3 -> 21.206897 | AP8: =IF(P8<51,40,(IF(P8<101,42,(IF(P8<201,44,IF(P8<301,46,IF(P8<401,48,(IF(P8<501,50,(IF(P8<1001,55,60))))))))))) -> 44 | AQ8: =0.8*AP8 -> 35.2 | AR8: =AQ8-5 -> 30.2 | AS8: =AA8+AQ8 -> 45846.2 | AT8: =AS8-5 -> 45841.2 | BF8: =IF(ISBLANK(AA8),0,IF(ISBLANK(BH8),($L$1-BE8),(BH8-BE8))) -> 45293 | CB8: =AC8-CA8 -> 0 | CD8: =AC8-CC8 -> 0 | CE8: =(0.3)*(CD8/AK8)+(0.7)*(CD8/AL8) -> 0 | CH8: =(0.3)*((NOW()-W8)/AK8)+(0.7)*((NOW()-W8)/AL8) -> 15.098488 | CI8: =IF(AB8="","PENDING COMP",(AB8-AA8)/AP8) -> PENDING COMP | CK8: =IF(R8="NEW","REV","NON-REV") -> REV
E9: X24041432658 | F9: LIGHT RAIL MANILA CORPORATION | G9: NINOY AQUINO, STO. NINO, PARANAQUE | H9: PARANAQUE CITY | I9: PARAÑAQUE | L9: SLEM | M9: FCOMP | N9: SLEM | P9: 136.13 | R9: NEW | V9: =U9/T9 -> #DIV/0! | W9: 45420 | AA9: 45716 | AC9: =AA9-W9 -> 296 | AD9: =AA9-X9 -> 45716 | AE9: =AB9-AA9 -> -45716 | AF9: =W9+AO9 -> 45441.207 | AG9: =W9+AN9 -> 45450.662 | AH9: =W9+50 -> 45470 | AI9: =(0.3)*(AC9/AK9)+(0.7)*(AC9/AL9) -> 9.1709402 | AJ9: =AE9/AP9 -> -1039 | AK9: =IF(P9<51,20,(IF(P9<101,23,(IF(P9<201,26,IF(P9<301,28,IF(P9<401,30,(IF(P9<501,32,(IF(P9<1001,40,50))))))))))) -> 26 | AL9: =IF(Q9<51,36,(IF(Q9<101,34,(IF(Q9<201,32,IF(Q9<301,30,IF(Q9<401,28,(IF(Q9<501,26,(IF(Q9<1001,23,20))))))))))) -> 36 | AM9: =(0.75)/((0.3/AK9)+(0.7/AL9)) -> 24.206897 | AN9: =(0.95)/((0.3/AK9)+(0.7/AL9)) -> 30.662069 | AO9: =AM9-3 -> 21.206897 | AP9: =IF(P9<51,40,(IF(P9<101,42,(IF(P9<201,44,IF(P9<301,46,IF(P9<401,48,(IF(P9<501,50,(IF(P9<1001,55,60))))))))))) -> 44 | AQ9: =0.8*AP9 -> 35.2 | AR9: =AQ9-5 -> 30.2 | AS9: =AA9+AQ9 -> 45751.2 | AT9: =AS9-5 -> 45746.2 | BF9: =IF(ISBLANK(AA9),0,IF(ISBLANK(BH9),($L$1-BE9),(BH9-BE9))) -> 45293 | CB9: =AC9-CA9 -> 296 | CD9: =AC9-CC9 -> 296 | CE9: =(0.3)*(CD9/AK9)+(0.7)*(CD9/AL9) -> 9.1709402 | CH9: =(0.3)*((NOW()-W9)/AK9)+(0.7)*((NOW()-W9)/AL9) -> 14.726693 | CI9: =IF(AB9="","PENDING COMP",(AB9-AA9)/AP9) -> PENDING COMP | CK9: =IF(R9="NEW","REV","NON-REV") -> REV
A10: 45427 | B10: 45427 | D10: CBG | E10: X24020489831 | F10: SM DEVELOPMENT CORPORATION, | G10: DR. A SANTOS, SAN DIONISIO, PARANAQUE | H10: PARAÑAQUE CITY | I10: PARAÑAQUE | L10: ECOM | M10: FCOMP | N10: UG | O10: 108.1986 | P10: 443.47 | Q10: 1021 | R10: NEW | S10: 3240513.1 | T10: 55638.73 | V10: =U10/T10 -> 0 | W10: 45422.635 | X10: 45425.781 | Y10: 45427 | AA10: 45483.344 | AC10: =AA10-W10 -> 60.709028 | AD10: =AA10-X10 -> 57.563889 | AE10: =AB10-AA10 -> -45483.344 | AF10: =W10+AO10 -> 45436.537 | AG10: =W10+AN10 -> 45444.044 | AH10: =W10+50 -> 45472.635 | AI10: =(0.3)*(AC10/AK10)+(0.7)*(AC10/AL10) -> 2.6939631 | AJ10: =AE10/AP10 -> -909.66689 | AK10: =IF(P10<51,20,(IF(P10<101,23,(IF(P10<201,26,IF(P10<301,28,IF(P10<401,30,(IF(P10<501,32,(IF(P10<1001,40,50))))))))))) -> 32 | AL10: =IF(Q10<51,36,(IF(Q10<101,34,(IF(Q10<201,32,IF(Q10<301,30,IF(Q10<401,28,(IF(Q10<501,26,(IF(Q10<1001,23,20))))))))))) -> 20 | AM10: =(0.75)/((0.3/AK10)+(0.7/AL10)) -> 16.901408 | AN10: =(0.95)/((0.3/AK10)+(0.7/AL10)) -> 21.408451 | AO10: =AM10-3 -> 13.901408 | AP10: =IF(P10<51,40,(IF(P10<101,42,(IF(P10<201,44,IF(P10<301,46,IF(P10<401,48,(IF(P10<501,50,(IF(P10<1001,55,60))))))))))) -> 50 | AQ10: =0.8*AP10 -> 40 | AR10: =AQ10-5 -> 35 | AS10: =AA10+AQ10 -> 45523.344 | AT10: =AS10-5 -> 45518.344 | BC10: ON GOING MAT RETURN | BE10: =AA10+3 -> 45486.344 | BF10: =IF(ISBLANK(AA10),0,IF(ISBLANK(BH10),($L$1-BE10),(BH10-BE10))) -> 6.6555556 | BG10: 45476 | BH10: 45493 | BI10: 45572 | BJ10: ECI | BK10: N | BQ10: Y | BY10: 45428 | BZ10: CZ8-8066, 520527 | CB10: =AC10-CA10 -> 60.709028 | CD10: =AC10-CC10 -> 60.709028 | CE10: =(0.3)*(CD10/AK10)+(0.7)*(CD10/AL10) -> 2.6939631 | CH10: =(0.3)*((NOW()-W10)/AK10)+(0.7)*((NOW()-W10)/AL10) -> 20.975232 | CI10: =IF(AB10="","PENDING COMP",(AB10-AA10)/AP10) -> PENDING COMP | CK10: =IF(R10="NEW","REV","NON-REV") -> REV
A11: 45440 | B11: 45441 | D11: BIZ | E11: X24030698480 | F11: BRILLO DEL ESTE DEVELOPMENT CORP. | G11: ADMIN-COMMERCIAL, EASTGLORY CENTER, PARANAQUE | H11: PARAÑAQUE CITY | I11: PARAÑAQUE | K11: W/O ISSUE | L11: VJC | M11: FCOMP | N11: UG | O11: 37.49 | P11: 600.42 | Q11: 6237 | R11: NEW | S11: 4328746.1 | T11: 30189.83 | U11: 14379.55 | V11: =U11/T11 -> 0.47630444 | W11: 45425.682 | X11: 45427.739 | Y11: 45440 | AA11: 45488.594 | AC11: =AA11-W11 -> 62.911806 | AD11: =AA11-X11 -> 60.854861 | AE11: =AB11-AA11 -> -45488.594 | AF11: =W11+AO11 -> 45440.329 | AG11: =W11+AN11 -> 45448.035 | AH11: =W11+50 -> 45475.682 | AI11: =(0.3)*(AC11/AK11)+(0.7)*(AC11/AL11) -> 2.6737517 | AJ11: =AE11/AP11 -> -827.06534 | AK11: =IF(P11<51,20,(IF(P11<101,23,(IF(P11<201,26,IF(P11<301,28,IF(P11<401,30,(IF(P11<501,32,(IF(P11<1001,40,50))))))))))) -> 40 | AL11: =IF(Q11<51,36,(IF(Q11<101,34,(IF(Q11<201,32,IF(Q11<301,30,IF(Q11<401,28,(IF(Q11<501,26,(IF(Q11<1001,23,20))))))))))) -> 20 | AM11: =(0.75)/((0.3/AK11)+(0.7/AL11)) -> 17.647059 | AN11: =(0.95)/((0.3/AK11)+(0.7/AL11)) -> 22.352941 | AO11: =AM11-3 -> 14.647059 | AP11: =IF(P11<51,40,(IF(P11<101,42,(IF(P11<201,44,IF(P11<301,46,IF(P11<401,48,(IF(P11<501,50,(IF(P11<1001,55,60))))))))))) -> 55 | AQ11: =0.8*AP11 -> 44 | AR11: =AQ11-5 -> 39 | AS11: =AA11+AQ11 -> 45532.594 | AT11: =AS11-5 -> 45527.594 | BC11: NO COC | BD11: PARTIALLY BILLED - 7/25/24 JSB | BE11: =AA11+3 -> 45491.594 | BF11: =IF(ISBLANK(AA11),0,IF(ISBLANK(BH11),($L$1-BE11),(BH11-BE11))) -> -198.59375 | BQ11: Y | BY11: 45440 | BZ11: C5-0154, C5-8080, 520856 | CB11: =AC11-CA11 -> 62.911806 | CD11: =AC11-CC11 -> 62.911806 | CE11: =(0.3)*(CD11/AK11)+(0.7)*(CD11/AL11) -> 2.6737517 | CH11: =(0.3)*((NOW()-W11)/AK11)+(0.7)*((NOW()-W11)/AL11) -> 19.959477 | CI11: =IF(AB11="","PENDING COMP",(AB11-AA11)/AP11) -> PENDING COMP | CK11: =IF(R11="NEW","REV","NON-REV") -> REV
A12: 45457 | B12: 45461 | D12: CBG | E12: X24010113590 | F12: LAS PINAS GENERAL HOSPITAL AND SATELLITE TRAUMA CE | G12: QUIRINO, PULANGLUPA I, LAS PINAS CITY | H12: LAS PIÑAS CITY | I12: PARAÑAQUE | K12: W/O ISSUE | L12: AVECO | M12: FCOMP | N12: UG | O12: 76.7333 | P12: 563.4 | Q12: 1434 | R12: NEW | S12: 3729821 | T12: 61791.45 | V12: =U12/T12 -> 0 | W12: 45443.547 | X12: 45457.689 | Y12: 45454 | AA12: 45481.297 | AC12: =AA12-W12 -> 37.75 | AD12: =AA12-X12 -> 23.607639 | AE12: =AB12-AA12 -> -45481.297 | AF12: =W12+AO12 -> 45458.194 | AG12: =W12+AN12 -> 45465.899 | AH12: =W12+50 -> 45493.547 | AI12: =(0.3)*(AC12/AK12)+(0.7)*(AC12/AL12) -> 1.604375 | AJ12: =AE12/AP12 -> -826.93266 | AK12: =IF(P12<51,20,(IF(P12<101,23,(IF(P12<201,26,IF(P12<301,28,IF(P12<401,30,(IF(P12<501,32,(IF(P12<1001,40,50))))))))))) -> 40 | AL12: =IF(Q12<51,36,(IF(Q12<101,34,(IF(Q12<201,32,IF(Q12<301,30,IF(Q12<401,28,(IF(Q12<501,26,(IF(Q12<1001,23,20))))))))))) -> 20 | AM12: =(0.75)/((0.3/AK12)+(0.7/AL12)) -> 17.647059 | AN12: =(0.95)/((0.3/AK12)+(0.7/AL12)) -> 22.352941 | AO12: =AM12-3 -> 14.647059 | AP12: =IF(P12<51,40,(IF(P12<101,42,(IF(P12<201,44,IF(P12<301,46,IF(P12<401,48,(IF(P12<501,50,(IF(P12<1001,55,60))))))))))) -> 55 | AQ12: =0.8*AP12 -> 44 | AR12: =AQ12-5 -> 39 | AS12: =AA12+AQ12 -> 45525.297 | AT12: =AS12-5 -> 45520.297 | BC12: NO COC | BE12: =AA12+3 -> 45484.297 | BF12: =IF(ISBLANK(AA12),0,IF(ISBLANK(BH12),($L$1-BE12),(BH12-BE12))) -> -191.29653 | BQ12: Y | BY12: 45460 | BZ12: CY7-8072, CY7-8073, 519311, CY7-8073 | CB12: =AC12-CA12 -> 37.75 | CD12: =AC12-CC12 -> 37.75 | CE12: =(0.3)*(CD12/AK12)+(0.7)*(CD12/AL12) -> 1.604375 | CH12: =(0.3)*((NOW()-W12)/AK12)+(0.7)*((NOW()-W12)/AL12) -> 19.200233 | CI12: =IF(AB12="","PENDING COMP",(AB12-AA12)/AP12) -> PENDING COMP | CK12: =IF(R12="NEW","REV","NON-REV") -> REV
A13: 45517 | B13: 45512 | D13: BIZ | E13: X23114429217 | F13: GOLDSERVE HOLDING COMPANY INC. | G13: MIA, TAMBO, PARANAQUE | H13: PARAÑAQUE CITY | I13: PARAÑAQUE | J13: pole location issue | K13: W/ ISSUE | L13: VJC | M13: FCOMP | N13: UG | O13: 62.1094 | P13: 224.02 | Q13: 44 | R13: NEW | S13: 636513.87 | T13: 49637.68 | U13: 41296.18 | V13: =U13/T13 -> 0.83195226 | W13: 45512.711 | X13: 45517.305 | Y13: 45520 | AA13: 45723 | AC13: =AA13-W13 -> 210.28889 | AD13: =AA13-X13 -> 205.69514 | AE13: =AB13-AA13 -> -45723 | AF13: =W13+AO13 -> 45534.58 | AG13: =W13+AN13 -> 45544.211 | AH13: =W13+50 -> 45562.711 | AI13: =(0.3)*(AC13/AK13)+(0.7)*(AC13/AL13) -> 6.3420459 | AJ13: =AE13/AP13 -> -993.97826 | AK13: =IF(P13<51,20,(IF(P13<101,23,(IF(P13<201,26,IF(P13<301,28,IF(P13<401,30,(IF(P13<501,32,(IF(P13<1001,40,50))))))))))) -> 28 | AL13: =IF(Q13<51,36,(IF(Q13<101,34,(IF(Q13<201,32,IF(Q13<301,30,IF(Q13<401,28,(IF(Q13<501,26,(IF(Q13<1001,23,20))))))))))) -> 36 | AM13: =(0.75)/((0.3/AK13)+(0.7/AL13)) -> 24.868421 | AN13: =(0.95)/((0.3/AK13)+(0.7/AL13)) -> 31.5 | AO13: =AM13-3 -> 21.868421 | AP13: =IF(P13<51,40,(IF(P13<101,42,(IF(P13<201,44,IF(P13<301,46,IF(P13<401,48,(IF(P13<501,50,(IF(P13<1001,55,60))))))))))) -> 46 | AQ13: =0.8*AP13 -> 36.8 | AR13: =AQ13-5 -> 31.8 | AS13: =AA13+AQ13 -> 45759.8 | AT13: =AS13-5 -> 45754.8 | BC13: FOR AUDIT | BD13: PARTIALLY BILLED - 7/25/24 JSB, PARTIAL 5/21/2025 | BE13: =AA13+15 -> 45738 | BF13: =IF(ISBLANK(AA13),0,IF(ISBLANK(BH13),($L$1-BE13),(BH13-BE13))) -> 30 | BG13: 45723 | BH13: 45768 | BQ13: Y | BY13: 45518 | BZ13: B5-8037, B5-0084, B5-8038, B5-5094, B5-00971 | CB13: =AC13-CA13 -> 210.28889 | CD13: =AC13-CC13 -> 210.28889 | CE13: =(0.3)*(CD13/AK13)+(0.7)*(CD13/AL13) -> 6.3420459 | CH13: =(0.3)*((NOW()-W13)/AK13)+(0.7)*((NOW()-W13)/AL13) -> 11.538899 | CI13: =IF(AB13="","PENDING COMP",(AB13-AA13)/AP13) -> PENDING COMP | CK13: =IF(R13="NEW","REV","NON-REV") -> REV
D14: CBG | E14: X24062079073 | F14: THE LANDMARK MANILA BAY CORPORATION | G14: ASEANA, ASEANA BUSINESS PARK, PARANAQUE | H14: PARAÑAQUE CITY | I14: PARAÑAQUE | L14: VJC | M14: FCOMP | N14: UG | O14: 147.944 | P14: 563.37 | Q14: 5950 | R14: NEW | S14: 5216314.4 | T14: 140962.37 | V14: =U14/T14 -> 0 | W14: 45569.434 | X14: 45569.555 | AA14: 45581.676 | AE14: =AB14-AA14 -> -45581.676 | AF14: =W14+AO14 -> 45584.081 | AG14: =W14+AN14 -> 45591.787 | AH14: =W14+50 -> 45619.434 | AI14: =(0.3)*(AC14/AK14)+(0.7)*(AC14/AL14) -> 0 | AJ14: =AE14/AP14 -> -828.75775 | AK14: =IF(P14<51,20,(IF(P14<101,23,(IF(P14<201,26,IF(P14<301,28,IF(P14<401,30,(IF(P14<501,32,(IF(P14<1001,40,50))))))))))) -> 40 | AL14: =IF(Q14<51,36,(IF(Q14<101,34,(IF(Q14<201,32,IF(Q14<301,30,IF(Q14<401,28,(IF(Q14<501,26,(IF(Q14<1001,23,20))))))))))) -> 20 | AM14: =(0.75)/((0.3/AK14)+(0.7/AL14)) -> 17.647059 | AN14: =(0.95)/((0.3/AK14)+(0.7/AL14)) -> 22.352941 | AO14: =AM14-3 -> 14.647059 | AP14: =IF(P14<51,40,(IF(P14<101,42,(IF(P14<201,44,IF(P14<301,46,IF(P14<401,48,(IF(P14<501,50,(IF(P14<1001,55,60))))))))))) -> 55 | AQ14: =0.8*AP14 -> 44 | AR14: =AQ14-5 -> 39 | AS14: =AA14+AQ14 -> 45625.676 | AT14: =AS14-5 -> 45620.676 | BC14: NO COC | CB14: =AC14-CA14 -> 0 | CD14: =AC14-CC14 -> 0 | CE14: =(0.3)*(CD14/AK14)+(0.7)*(CD14/AL14) -> 0 | CH14: =(0.3)*((NOW()-W14)/AK14)+(0.7)*((NOW()-W14)/AL14) -> 13.850014 | CI14: =IF(AB14="","PENDING COMP",(AB14-AA14)/AP14) -> PENDING COMP | CK14: =IF(R14="NEW","REV","NON-REV") -> REV
A15: 45694 | D15: BIZ | E15: X24051566102 | F15: ONE PREMIER AND TWO PREMIER CONDOMINIUM CORP. | G15: TWO PREMIER, ALABANG PREMIER, LAS PINAS CITY | H15: LAS PIÑAS CITY | I15: PARAÑAQUE | L15: UG | M15: TECO | N15: UG | P15: 299 | Q15: 3791 | R15: NEW | S15: 3214681.5 | V15: =U15/T15 -> #DIV/0! | W15: 45618 | X15: 45623 | AA15: 45672 | AB15: 45817.263 | AC15: =AA15-W15 -> 54 | AD15: =AA15-X15 -> 49 | AE15: =AB15-AA15 -> 145.26319 | AF15: =W15+AO15 -> 45631.406 | AG15: =W15+AN15 -> 45638.781 | AH15: =W15+50 -> 45668 | AI15: =(0.3)*(AC15/AK15)+(0.7)*(AC15/AL15) -> 2.4685714 | AJ15: =AE15/AP15 -> 3.1578955 | AK15: =IF(P15<51,20,(IF(P15<101,23,(IF(P15<201,26,IF(P15<301,28,IF(P15<401,30,(IF(P15<501,32,(IF(P15<1001,40,50))))))))))) -> 28 | AL15: =IF(Q15<51,36,(IF(Q15<101,34,(IF(Q15<201,32,IF(Q15<301,30,IF(Q15<401,28,(IF(Q15<501,26,(IF(Q15<1001,23,20))))))))))) -> 20 | AM15: =(0.75)/((0.3/AK15)+(0.7/AL15)) -> 16.40625 | AN15: =(0.95)/((0.3/AK15)+(0.7/AL15)) -> 20.78125 | AO15: =AM15-3 -> 13.40625 | AP15: =IF(P15<51,40,(IF(P15<101,42,(IF(P15<201,44,IF(P15<301,46,IF(P15<401,48,(IF(P15<501,50,(IF(P15<1001,55,60))))))))))) -> 46 | AQ15: =0.8*AP15 -> 36.8 | AR15: =AQ15-5 -> 31.8 | AS15: =AA15+AQ15 -> 45708.8 | AT15: =AS15-5 -> 45703.8 | BC15: PAID | BY15: N/A | CB15: =AC15-CA15 -> 54 | CD15: =AC15-CC15 -> 54 | CE15: =(0.3)*(CD15/AK15)+(0.7)*(CD15/AL15) -> 2.4685714 | CH15: =(0.3)*((NOW()-W15)/AK15)+(0.7)*((NOW()-W15)/AL15) -> 12.677335 | CI15: =IF(AB15="","PENDING COMP",(AB15-AA15)/AP15) -> 3.1578955 | CK15: =IF(R15="NEW","REV","NON-REV") -> REV
B16: 45679 | C16: Y | D16: CBG | E16: X24114365991 | F16: IFACE INC. | G16: STA. ANA, SUN VALLEY SUBD, PARANAQUE | H16: PARANAQUE CITY | I16: STA. ROSA | L16: AVECO | M16: FCOMP | N16: RRG | O16: 31.96 | P16: 366.82 | Q16: 994 | R16: NEW | S16: 3141766.4 | T16: 32632.89 | V16: =U16/T16 -> 0 | W16: 45673.69 | X16: 45677.626 | Y16: 45678 | Z16: 45751 | AA16: 45751 | AE16: =AB16-AA16 -> -45751 | AF16: =W16+AO16 -> 45689.239 | AG16: =W16+AN16 -> 45697.185 | AH16: =W16+50 -> 45723.69 | AI16: =(0.3)*(AC16/AK16)+(0.7)*(AC16/AL16) -> 0 | AJ16: =AE16/AP16 -> -953.14583 | AK16: =IF(P16<51,20,(IF(P16<101,23,(IF(P16<201,26,IF(P16<301,28,IF(P16<401,30,(IF(P16<501,32,(IF(P16<1001,40,50))))))))))) -> 30 | AL16: =IF(Q16<51,36,(IF(Q16<101,34,(IF(Q16<201,32,IF(Q16<301,30,IF(Q16<401,28,(IF(Q16<501,26,(IF(Q16<1001,23,20))))))))))) -> 23 | AM16: =(0.75)/((0.3/AK16)+(0.7/AL16)) -> 18.548387 | AN16: =(0.95)/((0.3/AK16)+(0.7/AL16)) -> 23.494624 | AO16: =AM16-3 -> 15.548387 | AP16: =IF(P16<51,40,(IF(P16<101,42,(IF(P16<201,44,IF(P16<301,46,IF(P16<401,48,(IF(P16<501,50,(IF(P16<1001,55,60))))))))))) -> 48 | AQ16: =0.8*AP16 -> 38.4 | AR16: =AQ16-5 -> 33.4 | AS16: =AA16+AQ16 -> 45789.4 | AT16: =AS16-5 -> 45784.4 | BC16: FOR AUDIT | BF16: =IF(ISBLANK(AA16),0,IF(ISBLANK(BH16),($L$1-BE16),(BH16-BE16))) -> 45861 | BG16: 45751 | BH16: 45861 | BY16: 45861 | BZ16: DZ1-8046 | CB16: =AC16-CA16 -> 0 | CD16: =AC16-CC16 -> 0 | CE16: =(0.3)*(CD16/AK16)+(0.7)*(CD16/AL16) -> 0 | CH16: =(0.3)*((NOW()-W16)/AK16)+(0.7)*((NOW()-W16)/AL16) -> 8.9614165 | CI16: =IF(AB16="","PENDING COMP",(AB16-AA16)/AP16) -> PENDING COMP | CK16: =IF(R16="NEW","REV","NON-REV") -> REV
A17: 45691 | D17: BIZ | E17: X25010064382 | F17: ACACIA REALTY CORP. | G17: FINANCE AVE, MADRIGAL BUSINESS PARK, MUNTINLUPA | H17: MUNTINLUPA CITY | I17: PARAÑAQUE | L17: UG | M17: FCOMP | N17: UG | P17: 32.2 | R17: TERMINATION | S17: 102570.5 | V17: =U17/T17 -> #DIV/0! | W17: 45682.541 | X17: 45688.604 | AA17: 45827 | AE17: =AB17-AA17 -> -45827 | AF17: =W17+AO17 -> 45701.315 | AG17: =W17+AN17 -> 45710.122 | AH17: =W17+50 -> 45732.541 | AI17: =(0.3)*(AC17/AK17)+(0.7)*(AC17/AL17) -> 0 | AJ17: =AE17/AP17 -> -1145.675 | AK17: =IF(P17<51,20,(IF(P17<101,23,(IF(P17<201,26,IF(P17<301,28,IF(P17<401,30,(IF(P17<501,32,(IF(P17<1001,40,50))))))))))) -> 20 | AL17: =IF(Q17<51,36,(IF(Q17<101,34,(IF(Q17<201,32,IF(Q17<301,30,IF(Q17<401,28,(IF(Q17<501,26,(IF(Q17<1001,23,20))))))))))) -> 36 | AM17: =(0.75)/((0.3/AK17)+(0.7/AL17)) -> 21.774194 | AN17: =(0.95)/((0.3/AK17)+(0.7/AL17)) -> 27.580645 | AO17: =AM17-3 -> 18.774194 | AP17: =IF(P17<51,40,(IF(P17<101,42,(IF(P17<201,44,IF(P17<301,46,IF(P17<401,48,(IF(P17<501,50,(IF(P17<1001,55,60))))))))))) -> 40 | AQ17: =0.8*AP17 -> 32 | AR17: =AQ17-5 -> 27 | AS17: =AA17+AQ17 -> 45859 | AT17: =AS17-5 -> 45854 | BF17: =IF(ISBLANK(AA17),0,IF(ISBLANK(BH17),($L$1-BE17),(BH17-BE17))) -> 45293 | BY17: N/A | CB17: =AC17-CA17 -> 0 | CD17: =AC17-CC17 -> 0 | CE17: =(0.3)*(CD17/AK17)+(0.7)*(CD17/AL17) -> 0 | CH17: =(0.3)*((NOW()-W17)/AK17)+(0.7)*((NOW()-W17)/AL17) -> 7.328942 | CI17: =IF(AB17="","PENDING COMP",(AB17-AA17)/AP17) -> PENDING COMP | CK17: =IF(R17="NEW","REV","NON-REV") -> NON-REV
A18: 45691 | D18: HMB | E18: X24124836711 | F18: C-E CONSTRUCTION CORPORATION | G18: PARKWAY, FILINVEST CORPORATE CITY, MUNTINLUPA | H18: MUNTINLUPA CITY | I18: PARAÑAQUE | L18: UG | M18: FCOMP | N18: UG | P18: 556.32 | Q18: 535 | R18: NEW | S18: 3359185 | V18: =U18/T18 -> #DIV/0! | W18: 45685.717 | X18: 45691.546 | AA18: 45730 | AC18: =AA18-W18 -> 44.282639 | AD18: =AA18-X18 -> 38.454167 | AE18: =AB18-AA18 -> -45730 | AF18: =W18+AO18 -> 45702.488 | AG18: =W18+AN18 -> 45710.76 | AH18: =W18+50 -> 45735.717 | AI18: =(0.3)*(AC18/AK18)+(0.7)*(AC18/AL18) -> 1.6798523 | AJ18: =AE18/AP18 -> -831.45455 | AK18: =IF(P18<51,20,(IF(P18<101,23,(IF(P18<201,26,IF(P18<301,28,IF(P18<401,30,(IF(P18<501,32,(IF(P18<1001,40,50))))))))))) -> 40 | AL18: =IF(Q18<51,36,(IF(Q18<101,34,(IF(Q18<201,32,IF(Q18<301,30,IF(Q18<401,28,(IF(Q18<501,26,(IF(Q18<1001,23,20))))))))))) -> 23 | AM18: =(0.75)/((0.3/AK18)+(0.7/AL18)) -> 19.770774 | AN18: =(0.95)/((0.3/AK18)+(0.7/AL18)) -> 25.04298 | AO18: =AM18-3 -> 16.770774 | AP18: =IF(P18<51,40,(IF(P18<101,42,(IF(P18<201,44,IF(P18<301,46,IF(P18<401,48,(IF(P18<501,50,(IF(P18<1001,55,60))))))))))) -> 55 | AQ18: =0.8*AP18 -> 44 | AR18: =AQ18-5 -> 39 | AS18: =AA18+AQ18 -> 45774 | AT18: =AS18-5 -> 45769 | BC18: NO COC | BY18: N/A | CB18: =AC18-CA18 -> 44.282639 | CD18: =AC18-CC18 -> 44.282639 | CE18: =(0.3)*(CD18/AK18)+(0.7)*(CD18/AL18) -> 1.6798523 | CH18: =(0.3)*((NOW()-W18)/AK18)+(0.7)*((NOW()-W18)/AL18) -> 7.9511056 | CI18: =IF(AB18="","PENDING COMP",(AB18-AA18)/AP18) -> PENDING COMP | CK18: =IF(R18="NEW","REV","NON-REV") -> REV
A19: 45721 | D19: CBG | E19: R23935710 | F19: CAVITEX INFRASTRUCTURE CORP., CBG | G19: C5 EXTENSION, MOONWALK, PARANAQUE | H19: PARANAQUE CITY | I19: PARAÑAQUE | L19: UG | M19: FCOMP | N19: UG | P19: 182.95 | R19: RELOC | S19: 462215.14 | V19: =U19/T19 -> #DIV/0! | W19: 45707.365 | X19: 45713.533 | Y19: 45709 | AA19: 45758 | AE19: =AB19-AA19 -> -45758 | AF19: =W19+AO19 -> 45728.572 | AG19: =W19+AN19 -> 45738.027 | AH19: =W19+50 -> 45757.365 | AI19: =(0.3)*(AC19/AK19)+(0.7)*(AC19/AL19) -> 0 | AJ19: =AE19/AP19 -> -1039.9545 | AK19: =IF(P19<51,20,(IF(P19<101,23,(IF(P19<201,26,IF(P19<301,28,IF(P19<401,30,(IF(P19<501,32,(IF(P19<1001,40,50))))))))))) -> 26 | AL19: =IF(Q19<51,36,(IF(Q19<101,34,(IF(Q19<201,32,IF(Q19<301,30,IF(Q19<401,28,(IF(Q19<501,26,(IF(Q19<1001,23,20))))))))))) -> 36 | AM19: =(0.75)/((0.3/AK19)+(0.7/AL19)) -> 24.206897 | AN19: =(0.95)/((0.3/AK19)+(0.7/AL19)) -> 30.662069 | AO19: =AM19-3 -> 21.206897 | AP19: =IF(P19<51,40,(IF(P19<101,42,(IF(P19<201,44,IF(P19<301,46,IF(P19<401,48,(IF(P19<501,50,(IF(P19<1001,55,60))))))))))) -> 44 | AQ19: =0.8*AP19 -> 35.2 | AR19: =AQ19-5 -> 30.2 | AS19: =AA19+AQ19 -> 45793.2 | AT19: =AS19-5 -> 45788.2 | BF19: =IF(ISBLANK(AA19),0,IF(ISBLANK(BH19),($L$1-BE19),(BH19-BE19))) -> 45293 | BY19: N/A | CB19: =AC19-CA19 -> 0 | CD19: =AC19-CC19 -> 0 | CE19: =(0.3)*(CD19/AK19)+(0.7)*(CD19/AL19) -> 0 | CH19: =(0.3)*((NOW()-W19)/AK19)+(0.7)*((NOW()-W19)/AL19) -> 5.8232815 | CI19: =IF(AB19="","PENDING COMP",(AB19-AA19)/AP19) -> PENDING COMP | CK19: =IF(R19="NEW","REV","NON-REV") -> NON-REV | CL19: =IF(CJ19="","",IF(CJ19<91,"0-3 MONTHS",(IF(CJ19<181,"4-6 MONTHS",(IF(CJ19<271,"7-9 MONTHS",IF(CJ19>270,"10 MONTHS AND ABOVE",)))))))
E20: R21138022 | F20: CAVITEX INFRASTRUCTURE CORP. | G20: STREET, MULTINATIONAL VILL, MULTINATIONAL VILL, PARANAQUE | H20: PARAÑAQUE CITY | I20: PARAÑAQUE | L20: UG | M20: SCHED | N20: UG | P20: 178.48 | R20: RELOC | V20: =U20/T20 -> #DIV/0! | W20: 44811 | X20: 44813 | AC20: =AA20-W20 -> -44811 | AD20: =AA20-X20 -> -44813 | AE20: =AB20-AA20 -> 0 | AF20: =W20+AO20 -> 44832.207 | AG20: =W20+AN20 -> 44841.662 | AH20: =W20+50 -> 44861 | AI20: =(0.3)*(AC20/AK20)+(0.7)*(AC20/AL20) -> -1388.375 | AJ20: =AE20/AP20 -> 0 | AK20: =IF(P20<51,20,(IF(P20<101,23,(IF(P20<201,26,IF(P20<301,28,IF(P20<401,30,(IF(P20<501,32,(IF(P20<1001,40,50))))))))))) -> 26 | AL20: =IF(Q20<51,36,(IF(Q20<101,34,(IF(Q20<201,32,IF(Q20<301,30,IF(Q20<401,28,(IF(Q20<501,26,(IF(Q20<1001,23,20))))))))))) -> 36 | AM20: =(0.75)/((0.3/AK20)+(0.7/AL20)) -> 24.206897 | AN20: =(0.95)/((0.3/AK20)+(0.7/AL20)) -> 30.662069 | AO20: =AM20-3 -> 21.206897 | AP20: =IF(P20<51,40,(IF(P20<101,42,(IF(P20<201,44,IF(P20<301,46,IF(P20<401,48,(IF(P20<501,50,(IF(P20<1001,55,60))))))))))) -> 44 | AQ20: =0.8*AP20 -> 35.2 | AR20: =AQ20-5 -> 30.2 | AS20: =AA20+AQ20 -> 35.2 | AT20: =AS20-5 -> 30.2 | BF20: =IF(ISBLANK(AA20),0,IF(ISBLANK(BH20),($L$1-BE20),(BH20-BE20))) -> 0 | CB20: =AC20-CA20 -> -44811 | CD20: =AC20-CC20 -> -44811 | CE20: =(0.3)*(CD20/AK20)+(0.7)*(CD20/AL20) -> -1388.375 | CH20: =(0.3)*((NOW()-W20)/AK20)+(0.7)*((NOW()-W20)/AL20) -> 33.595283 | CI20: =IF(AB20="","PENDING COMP",(AB20-AA20)/AP20) -> PENDING COMP | CK20: =IF(R20="NEW","REV","NON-REV") -> NON-REV
E21: R22006061 | F21: PCA RELOC, Overhead Facilities, N, Y, N, DEPARTMENT OF TRANSPORTATION,, CBG | G21: STREET, EAST SERVICE, SN MARTIN DE PORRES, PARANAQUE | H21: PARANAQUE CITY | I21: PARAÑAQUE | L21: SLEM | M21: SCHED | N21: SLEM | P21: 120.75 | R21: RELOC | V21: =U21/T21 -> #DIV/0! | W21: 45057 | X21: 45065 | AC21: =AA21-W21 -> -45057 | AD21: =AA21-X21 -> -45065 | AE21: =AB21-AA21 -> 0 | AF21: =W21+AO21 -> 45078.207 | AG21: =W21+AN21 -> 45087.662 | AH21: =W21+50 -> 45107 | AI21: =(0.3)*(AC21/AK21)+(0.7)*(AC21/AL21) -> -1395.9968 | AJ21: =AE21/AP21 -> 0 | AK21: =IF(P21<51,20,(IF(P21<101,23,(IF(P21<201,26,IF(P21<301,28,IF(P21<401,30,(IF(P21<501,32,(IF(P21<1001,40,50))))))))))) -> 26 | AL21: =IF(Q21<51,36,(IF(Q21<101,34,(IF(Q21<201,32,IF(Q21<301,30,IF(Q21<401,28,(IF(Q21<501,26,(IF(Q21<1001,23,20))))))))))) -> 36 | AM21: =(0.75)/((0.3/AK21)+(0.7/AL21)) -> 24.206897 | AN21: =(0.95)/((0.3/AK21)+(0.7/AL21)) -> 30.662069 | AO21: =AM21-3 -> 21.206897 | AP21: =IF(P21<51,40,(IF(P21<101,42,(IF(P21<201,44,IF(P21<301,46,IF(P21<401,48,(IF(P21<501,50,(IF(P21<1001,55,60))))))))))) -> 44 | AQ21: =0.8*AP21 -> 35.2 | AR21: =AQ21-5 -> 30.2 | AS21: =AA21+AQ21 -> 35.2 | AT21: =AS21-5 -> 30.2 | CB21: =AC21-CA21 -> -45057 | CD21: =AC21-CC21 -> -45057 | CE21: =(0.3)*(CD21/AK21)+(0.7)*(CD21/AL21) -> -1395.9968 | CH21: =(0.3)*((NOW()-W21)/AK21)+(0.7)*((NOW()-W21)/AL21) -> 25.973488 | CI21: =IF(AB21="","PENDING COMP",(AB21-AA21)/AP21) -> PENDING COMP | CK21: =IF(R21="NEW","REV","NON-REV") -> NON-REV
A22: N/A | B22: N/A | D22: CBG | E22: X24041158243 | F22: PHINMA PROPERTY HOLDINGS CORPORATION | G22: ALUMINUM, METROTOWNE, LAS PINAS CITY | H22: LAS PIÑAS CITY | I22: PARAÑAQUE | L22: UG | M22: SCHED | N22: Jayson Ramores | O22: 174.81 | P22: 174.81 | Q22: 1965 | R22: NEW | S22: 2772246.8 | V22: =U22/T22 -> #DIV/0! | W22: 45828.432 | X22: 45834.644 | Y22: N/A | AC22: =AA22-W22 -> -45828.432 | AD22: =AA22-X22 -> -45834.644 | AE22: =AB22-AA22 -> 0 | AF22: =W22+AO22 -> 45841.548 | AG22: =W22+AN22 -> 45848.846 | AH22: =W22+50 -> 45878.432 | AI22: =(0.3)*(AC22/AK22)+(0.7)*(AC22/AL22) -> -2132.7847 | AJ22: =AE22/AP22 -> 0 | AK22: =IF(P22<51,20,(IF(P22<101,23,(IF(P22<201,26,IF(P22<301,28,IF(P22<401,30,(IF(P22<501,32,(IF(P22<1001,40,50))))))))))) -> 26 | AL22: =IF(Q22<51,36,(IF(Q22<101,34,(IF(Q22<201,32,IF(Q22<301,30,IF(Q22<401,28,(IF(Q22<501,26,(IF(Q22<1001,23,20))))))))))) -> 20 | AM22: =(0.75)/((0.3/AK22)+(0.7/AL22)) -> 16.115702 | AN22: =(0.95)/((0.3/AK22)+(0.7/AL22)) -> 20.413223 | AO22: =AM22-3 -> 13.115702 | AP22: 60 | AQ22: =0.95*AP22 -> 57 | AR22: =AQ22-5 -> 52 | AS22: =AA22+AP22 -> 60 | AT22: =IFERROR(TODAY()-AA22,"") -> 45895 | BE22: =AA22+15 -> 15 | BF22: =IF(ISBLANK(AA22),0,IF(ISBLANK(BH22),(BE22-'C1'!$L$1),(BH22-BE22))) -> 0 | CA22: =IF(AY22="Y",BA22,"0") -> 0 | CB22: =AC22-CA22 -> -45828.432 | CC22: =BA22 -> 0 | CD22: =AC22-BA22 -> -45828.432 | CE22: =(0.3)*(CD22/AK22)+(0.7)*(CD22/AL22) -> -2132.7847 | CH22: =(0.3)*(('C1'!$CF$1-W22)/AK22)+(0.7)*(('C1'!$CF$1-W22)/AL22) -> 1.8879555 | CI22: =CH22-CG22 -> 1.8879555 | CJ22: =CF22/AP22 -> 0 | CK22: =IF(AA22>0,"",'C1'!$CK$1-W22) -> 27.567639 | CL22: =IF(R22="NEW","REV","NON-REV") -> REV | CM22: =IF(CK22="","",IF(CK22<91,"0-3 MONTHS",(IF(CK22<181,"4-6 MONTHS",(IF(CK22<271,"7-9 MONTHS",IF(CK22>270,"10 MONTHS AND ABOVE",))))))) -> 0-3 MONTHS

Sheet C1
D1: PROJECTS | G1: 0 | K1: F | L1: R | X1: PERFORMANCE | AC1: RED(Above 50Days) | AH1: NEW KPI (Starting October 2021) | AL1: COMPUTATION: FOR FCOMP | AQ1: FOR COMP | AT1: (-5) | AU1: 0.75 aspiration | BB1: 0.75 aspiration | BC1: REMARKS | BE1: CERTIFICATE OF COMPLETION | BI1: FIELD AUDIT | BK1: RE-WORK | BO1: MATERIAL BALANCING | BQ1: TRANSMITTAL TO METER | BS1: FOR OLDT DETAILS | CF1: 45869 | CG1: MANUAL | CK1: 45856
A2: Date Received Jacket from P&S | B2: Date Received Awarding of Wo | C2: VIP | D2: WO INITIATOR | E2: WO NO | F2: DESCRIPTION | G2: LOCATION | H2: MUNICIPALITY | I2: AREA OF RESPONSIBILITY | J2: VENDOR REMARKS (free text) | K2: C1 REMARKS (with or without issue) | L2: ASSIGNED | M2: STATUS | N2: SUPERVISOR | O2: C1 CONTRACTOR MANHOUR | P2: TOTAL MANHOURS | Q2: APPLIED LOAD | R2: TYPE | S2: TOTAL PLANNED PROJECT COST | T2: TOTAL ESTIMATED COST (SERVICES) | U2: BILLED / PARTIALLY BILLED COST | V2: % BILLED | W2: DATE WMTRL | X2: DATE SCHED | Y2: DATE RECEIVED BY VC | Z2: ACTUAL DATE COMPLETED ON SITE | AA2: DATE FCOMP | AB2: DATE COMP | AC2: # of days WMTRL TO FCOMP APT Without Exclusion (SPT) | AD2: # of days SCHED TO FCOMP | AE2: # of days COMP | AF2: (0.75) DATE NEEDED FOR WMTRL TO FCOMP | AG2: (0.95) DATE NEEDED FOR FCOMP | AH2: (50 DAYS) DATE NEEDED FOR WMTRL TO FCOMP | AI2: COMPUTED INDEX (WMTRL TO FCOMP) CCTI Without Exclusion | AJ2: COMPUTED INDEX (COMP) | AK2: SPT(M) | AL2: SPT(L) | AM2: 0.75 DURATION (DAYS) | AN2: 0.95 DURATION (DAYS) | AO2: TARGET DAYS | AP2: SPT(M) for comp | AQ2: DURATION (DAYS)COMP | AR2: TARGET DAYS (COMP) | AS2: DATE NEEDED TO COMP | AT2: AGEING DAYS SINCE FCOMP | AU2: REASON (FOR EXCLUSION) | AV2: FOR CCTI EXCLUSION (Y/N) | AW2: ENCODED IN EAM (Y/N) | AX2: VALIDATED BY DCSAM (Y/N) | AY2: For APT Exclusion (Y/N) | AZ2: START DATE | BA2: DURATION FOR EXCLUSION | BB2: END DATE (FOR EXCLUSION) | BC2: REMARKS / FOLLOW UP BY | BD2: REMARKS 2 | BE2: DATE NEEDED TO SUBMIT COC | BF2: AGEING SUBMISSION OF COC | BG2: DATE COMPLETED (FROM COC) | BH2: ACTUAL RECEIVED COC | BI2: DATE AUDIT | BJ2: BY: | BK2: W/ BACK JOB | BL2: BACKJOB TAGGED IN EAM? RE-WORK | BM2: DATE RECEIVED BY CONTRACTOR | BN2: DATE CORRECTED | BO2: DATE MATERIAL BALANCING | BP2: BY | BQ2: Y/N | BR2: EMAILED TO METER | BS2: DT CORRECTION METHOD | BT2: TLN | BU2: WITH POLE REPL? | BV2: ACTUAL FIELD STATUS | BW2: REMARKS3 | BX2: ABF PRINTED BY (FOR AUDIT) | BY2: DATE PRINTED OF POLE TAG FABRICATION FORM | BZ2: POLE / TLN TAGS | CA2: Days for Exclusion based on emails to concerned office/PCTs (Due to customer only - APT) | CB2: APT with Exclusion | CC2: Days for Exclusion based on emails to concerned office/PCTs (All reason - CCTI) | CD2: Duration for CCTI with exclusion | CE2: CCTI With Exclusion | CF2: E2E for PRDI | CG2: CURRENT CCTI (with exclusion) | CH2: CURRENT CCTI | CI2: FINAL CCTI (LESS THAN FCOMP) | CJ2: PRDI | CK2: Days Ageing (as of cell CJ1) | CL2: REV/NON-REV | CM2: AGE BRACKET | CN2: NTC DATE CREATED | CO2: AMOUNT | CP2: NTC | CQ2: DATE RECEIVED BY CONTRACTOR | CR2: DATE COMPLETED NTC | CS2: RUNNING DAYS | CT2: NOV & DEBIT MEMO DATE CREATED | CU2: AMOUNT | CV2: DATE RECEIVED BY CONTRACTOR | CW2: EXT | CX2: UPDATED SUPV | CY2: SUPV NAME | CZ2: STATUS 4/4/25 | DA2: DIFF (in days) FROM WMTRL TO SCHED - 2025 WOs only | DC2: filter | DS2: SUPERVISOR FULL NAME
A3: 44000 | B3: N/A | D3: MN | E3: P2004004805 | F3: MAINT - 44WU_TLN 051257 LOADSPLIT & Inst Addl 25/50/50KVA on CY8-1276/CY8-1275/CY8-1273 | G3: DIAMOND, BERNABE PH 3 SUBD SAN DIONISIO PARAÑAQUE CITY | H3: PARAÑAQUE CITY | I3: PARAÑAQUE | J3: not feasible; for survey team C1 | K3: W/ ISSUE | L3: OPS | M3: SCHED | N3: Dean Carl Borjal | O3: 139.2078 | P3: #N/A | Q3: 0 | R3: OLDT | S3: 560984.1 | T3: 109904.21 | V3: =U3/T3 -> 0 | W3: 43987.697 | X3: 43990.368 | Y3: 43997 | AC3: =AA3-W3 -> -43987.697 | AD3: =AA3-X3 -> -43990.368 | AE3: =AB3-AA3 -> 0 | AF3: =W3+AO3 -> #N/A | AG3: =W3+AN3 -> #N/A | AH3: =W3+50 -> 44037.697 | AI3: =(0.3)*(AC3/AK3)+(0.7)*(AC3/AL3) -> #N/A | AJ3: =AE3/AP3 -> 0 | AK3: =IF(P3<51,20,(IF(P3<101,23,(IF(P3<201,26,IF(P3<301,28,IF(P3<401,30,(IF(P3<501,32,(IF(P3<1001,40,50))))))))))) -> #N/A | AL3: =IF(Q3<51,36,(IF(Q3<101,34,(IF(Q3<201,32,IF(Q3<301,30,IF(Q3<401,28,(IF(Q3<501,26,(IF(Q3<1001,23,20))))))))))) -> 36 | AM3: =(0.75)/((0.3/AK3)+(0.7/AL3)) -> #N/A | AN3: =(0.95)/((0.3/AK3)+(0.7/AL3)) -> #N/A | AO3: =AM3-3 -> #N/A | AP3: 60 | AQ3: =0.95*AP3 -> 57 | AR3: =AQ3-5 -> 52 | AS3: =AA3+AP3 -> 60 | AT3: =IFERROR(TODAY()-AA3,"") -> 45895 | BE3: =AA3+15 -> 15 | BF3: =IF(ISBLANK(AA3),0,IF(ISBLANK(BH3),(BE3-$L$1),(BH3-BE3))) -> 0 | BQ3: N | BS3: Load-splitting | BT3: TLN 051257 | BU3: Y | BV3: With concern | BW3: Transferred from Alvin to Jimmy | CA3: =IF(AY3="Y",BA3,"0") -> 0 | CB3: =AC3-CA3 -> -43987.697 | CC3: =BA3 -> 0 | CD3: =AC3-BA3 -> -43987.697 | CE3: =(0.3)*(CD3/AK3)+(0.7)*(CD3/AL3) -> #N/A | CF3: =IF(AA3="","0",$CF$1-AA3) -> 0 | CH3: =(0.3)*(($CF$1-W3)/AK3)+(0.7)*(($CF$1-W3)/AL3) -> #N/A | CI3: =CH3-CG3 -> #N/A | CJ3: =CF3/AP3 -> 0 | CK3: =IF(AA3>0,"",$CK$1-W3) -> 1868.3028 | CL3: =IF(R3="NEW","REV","NON-REV") -> NON-REV | CM3: =IF(CK3="","",IF(CK3<91,"0-3 MONTHS",(IF(CK3<181,"4-6 MONTHS",(IF(CK3<271,"7-9 MONTHS",IF(CK3>270,"10 MONTHS AND ABOVE",))))))) -> 10 MONTHS AND ABOVE | CP3: =IF(CQ3,"NTC ISSUED","FOR ISSUANCE") -> FOR ISSUANCE | CS3: =IF(AND(CQ3=0,CR3=0), "0",IF(CR3,(CR3-CQ3),TODAY()-CQ3)) -> 0 | CW3: 'P2004004805', | CX3: =VLOOKUP(E3,'[1]List of Work Orders'!$A:$I,9,FALSE) -> ME168443 | DC3: =VLOOKUP(E3,'[2]List of Work Orders'!$A:$F,6,FALSE) -> SCHED | DS3: DCB
A4: 44025 | B4: N/A | D4: MN | E4: P2006000420 | F4: MAINT 45WG TLN 037283; Split Loading Inst Addl 50KVA & 75KVA on A8-0440&ALB1-3102 | G4: BLOCK 32 PUROK 4 UPPER BICUTAN TAGUIG CITY | H4: TAGUIG CITY | I4: PARAÑAQUE | J4: Sept 2023, ayaw magpahukay, for survey wityh design/For survey of C1 Team | K4: W/ ISSUE | L4: VJC | M4: CAN | N4: Jenneth Madrid | O4: 90.9766 | P4: #N/A | Q4: 0 | R4: OLDT | S4: 442337.68 | T4: 91388.65 | V4: =U4/T4 -> 0 | W4: 44022.592 | X4: 44025.524 | Y4: 44025 | AA4: CAN | AC4: =AA4-W4 -> #VALUE! | AD4: =AA4-X4 -> #VALUE! | AE4: =AB4-AA4 -> #VALUE! | AF4: =W4+AO4 -> #N/A | AG4: =W4+AN4 -> #N/A | AH4: =W4+50 -> 44072.592 | AI4: =(0.3)*(AC4/AK4)+(0.7)*(AC4/AL4) -> #VALUE! | AJ4: =AE4/AP4 -> #VALUE! | AK4: =IF(P4<51,20,(IF(P4<101,23,(IF(P4<201,26,IF(P4<301,28,IF(P4<401,30,(IF(P4<501,32,(IF(P4<1001,40,50))))))))))) -> #N/A | AL4: =IF(Q4<51,36,(IF(Q4<101,34,(IF(Q4<201,32,IF(Q4<301,30,IF(Q4<401,28,(IF(Q4<501,26,(IF(Q4<1001,23,20))))))))))) -> 36 | AM4: =(0.75)/((0.3/AK4)+(0.7/AL4)) -> #N/A | AN4: =(0.95)/((0.3/AK4)+(0.7/AL4)) -> #N/A | AO4: =AM4-3 -> #N/A | AP4: 60 | AQ4: =0.95*AP4 -> 57 | AR4: =AQ4-5 -> 52 | AS4: =AA4+AP4 -> #VALUE! | AT4: =IFERROR(TODAY()-AA4,"") | BE4: =AA4+15 -> #VALUE! | BF4: =IF(ISBLANK(AA4),0,IF(ISBLANK(BH4),(BE4-$L$1),(BH4-BE4))) -> #VALUE! | BQ4: N | BS4: Load-splitting | BT4: TLN 037283 | BU4: Y | BV4: For schedule | BW4: Transferred from Marc to Jimmy | CA4: =IF(AY4="Y",BA4,"0") -> 0 | CB4: =AC4-CA4 -> #VALUE! | CC4: =BA4 -> 0 | CD4: =AC4-BA4 -> #VALUE! | CE4: =(0.3)*(CD4/AK4)+(0.7)*(CD4/AL4) -> #VALUE! | CF4: =IF(AA4="","0",$CF$1-AA4) -> #VALUE! | CH4: =(0.3)*(($CF$1-W4)/AK4)+(0.7)*(($CF$1-W4)/AL4) -> #N/A | CI4: =CH4-CG4 -> #N/A | CJ4: =CF4/AP4 -> #VALUE! | CK4: =IF(AA4>0,"",$CK$1-W4) | CL4: =IF(R4="NEW","REV","NON-REV") -> NON-REV | CM4: =IF(CK4="","",IF(CK4<91,"0-3 MONTHS",(IF(CK4<181,"4-6 MONTHS",(IF(CK4<271,"7-9 MONTHS",IF(CK4>270,"10 MONTHS AND ABOVE",))))))) | CP4: =IF(CQ4,"NTC ISSUED","FOR ISSUANCE") -> FOR ISSUANCE | CS4: =IF(AND(CQ4=0,CR4=0), "0",IF(CR4,(CR4-CQ4),TODAY()-CQ4)) -> 0 | CW4: 'P2006000420', | CX4: =VLOOKUP(E4,'[1]List of Work Orders'!$A:$I,9,FALSE) -> ME185284 | DC4: =VLOOKUP(E4,'[2]List of Work Orders'!$A:$F,6,FALSE) -> CAN | DS4: Jenneth Madrid
A5: 44025 | B5: N/A | D5: MN | E5: P2006000610 | F5: MAINT - 55GG_TLN 271296 Split Loading Inst Addl 50KVA on A8-0735 | G5: JASMIN PUROK 6C LOWER BICUTAN TAGUIG CITY | H5: TAGUIG CITY | I5: PARAÑAQUE | J5: Sept 2023, ayaw magpahukay, for survey wityh design/For survey of C1 Team | K5: W/ ISSUE | L5: VJC | M5: CAN | N5: Jenneth Madrid | O5: 22.1094 | P5: #N/A | Q5: 0 | R5: OLDT | S5: 186406.1 | T5: 23237.07 | V5: =U5/T5 -> 0 | W5: 44042.035 | X5: 44048.449 | Y5: 44025 | AA5: CAN | AC5: =AA5-W5 -> #VALUE! | AD5: =AA5-X5 -> #VALUE! | AE5: =AB5-AA5 -> #VALUE! | AF5: =W5+AO5 -> #N/A | AG5: =W5+AN5 -> #N/A | AH5: =W5+50 -> 44092.035 | AI5: =(0.3)*(AC5/AK5)+(0.7)*(AC5/AL5) -> #VALUE! | AJ5: =AE5/AP5 -> #VALUE! | AK5: =IF(P5<51,20,(IF(P5<101,23,(IF(P5<201,26,IF(P5<301,28,IF(P5<401,30,(IF(P5<501,32,(IF(P5<1001,40,50))))))))))) -> #N/A | AL5: =IF(Q5<51,36,(IF(Q5<101,34,(IF(Q5<201,32,IF(Q5<301,30,IF(Q5<401,28,(IF(Q5<501,26,(IF(Q5<1001,23,20))))))))))) -> 36 | AM5: =(0.75)/((0.3/AK5)+(0.7/AL5)) -> #N/A | AN5: =(0.95)/((0.3/AK5)+(0.7/AL5)) -> #N/A | AO5: =AM5-3 -> #N/A | AP5: 60 | AQ5: =0.95*AP5 -> 57 | AR5: =AQ5-5 -> 52 | AS5: =AA5+AP5 -> #VALUE! | AT5: =IFERROR(TODAY()-AA5,"") | BE5: =AA5+15 -> #VALUE! | BF5: =IF(ISBLANK(AA5),0,IF(ISBLANK(BH5),(BE5-$L$1),(BH5-BE5))) -> #VALUE! | BQ5: N | BS5: Load-splitting | BT5: TLN 271296 | BU5: Y | BV5: For schedule | BW5: Transferred from Marc to Jimmy | CA5: =IF(AY5="Y",BA5,"0") -> 0 | CB5: =AC5-CA5 -> #VALUE! | CC5: =BA5 -> 0 | CD5: =AC5-BA5 -> #VALUE! | CE5: =(0.3)*(CD5/AK5)+(0.7)*(CD5/AL5) -> #VALUE! | CF5: =IF(AA5="","0",$CF$1-AA5) -> #VALUE! | CH5: =(0.3)*(($CF$1-W5)/AK5)+(0.7)*(($CF$1-W5)/AL5) -> #N/A | CI5: =CH5-CG5 -> #N/A | CJ5: =CF5/AP5 -> #VALUE! | CK5: =IF(AA5>0,"",$CK$1-W5) | CL5: =IF(R5="NEW","REV","NON-REV") -> NON-REV | CM5: =IF(CK5="","",IF(CK5<91,"0-3 MONTHS",(IF(CK5<181,"4-6 MONTHS",(IF(CK5<271,"7-9 MONTHS",IF(CK5>270,"10 MONTHS AND ABOVE",))))))) | CP5: =IF(CQ5,"NTC ISSUED","FOR ISSUANCE") -> FOR ISSUANCE | CS5: =IF(AND(CQ5=0,CR5=0), "0",IF(CR5,(CR5-CQ5),TODAY()-CQ5)) -> 0 | CW5: 'P2006000610', | CX5: =VLOOKUP(E5,'[1]List of Work Orders'!$A:$I,9,FALSE) -> ME185284 | DC5: =VLOOKUP(E5,'[2]List of Work Orders'!$A:$F,6,FALSE) -> CAN | DS5: Jenneth Madrid
A6: 44125 | B6: N/A | D6: MN | E6: P2006000921 | F6: MAINT- 45WG Load-Split TLN 068256; Inst New 75KVA on DZ1-2057 | G6: ROAD 3 NORTH DAANG HARI BAGONG TANYAG TAGUIG CITY | H6: TAGUIG CITY | I6: PARAÑAQUE | J6: not feasible; for survey team C1; continue digging on Dec 9 | K6: W/ ISSUE | L6: ECOM | M6: FCOMP | N6: Dean Carl Borjal | O6: 40.19 | P6: 40.19 | Q6: 0 | R6: OLDT | S6: 185553.84 | T6: 24087.84 | V6: =U6/T6 -> 0 | W6: 44102.59 | X6: 44104.336 | Y6: 44120 | AA6: 45720 | AC6: =AA6-W6 -> 1617.4097 | AD6: =AA6-X6 -> 1615.6639 | AE6: =AB6-AA6 -> -45720 | AF6: =W6+AO6 -> 44121.364 | AG6: =W6+AN6 -> 44130.171 | AH6: =W6+50 -> 44152.59 | AI6: =(0.3)*(AC6/AK6)+(0.7)*(AC6/AL6) -> 55.710779 | AJ6: =AE6/AP6 -> -762 | AK6: =IF(P6<51,20,(IF(P6<101,23,(IF(P6<201,26,IF(P6<301,28,IF(P6<401,30,(IF(P6<501,32,(IF(P6<1001,40,50))))))))))) -> 20 | AL6: =IF(Q6<51,36,(IF(Q6<101,34,(IF(Q6<201,32,IF(Q6<301,30,IF(Q6<401,28,(IF(Q6<501,26,(IF(Q6<1001,23,20))))))))))) -> 36 | AM6: =(0.75)/((0.3/AK6)+(0.7/AL6)) -> 21.774194 | AN6: =(0.95)/((0.3/AK6)+(0.7/AL6)) -> 27.580645 | AO6: =AM6-3 -> 18.774194 | AP6: 60 | AQ6: =0.95*AP6 -> 57 | AR6: =AQ6-5 -> 52 | AS6: =AA6+AP6 -> 45780 | AT6: =IFERROR(TODAY()-AA6,"") -> 175 | BC6: NO COC | BE6: =AA6+15 -> 45735 | BF6: =IF(ISBLANK(AA6),0,IF(ISBLANK(BH6),(BE6-$L$1),(BH6-BE6))) -> #VALUE! | BQ6: N | BS6: Load-splitting | BT6: TLN 068256 | BU6: Y | BV6: With concern | BW6: Transferred from Alvin to Jimmy | CA6: =IF(AY6="Y",BA6,"0") -> 0 | CB6: =AC6-CA6 -> 1617.4097 | CC6: =BA6 -> 0 | CD6: =AC6-BA6 -> 1617.4097 | CE6: =(0.3)*(CD6/AK6)+(0.7)*(CD6/AL6) -> 55.710779 | CF6: =IF(AA6="","0",$CF$1-AA6) -> 149 | CH6: =(0.3)*(($CF$1-W6)/AK6)+(0.7)*(($CF$1-W6)/AL6) -> 60.843002 | CI6: =CH6-CG6 -> 60.843002 | CJ6: =CF6/AP6 -> 2.4833333 | CK6: =IF(AA6>0,"",$CK$1-W6) | CL6: =IF(R6="NEW","REV","NON-REV") -> NON-REV | CM6: =IF(CK6="","",IF(CK6<91,"0-3 MONTHS",(IF(CK6<181,"4-6 MONTHS",(IF(CK6<271,"7-9 MONTHS",IF(CK6>270,"10 MONTHS AND ABOVE",))))))) | CP6: =IF(CQ6,"NTC ISSUED","FOR ISSUANCE") -> FOR ISSUANCE | CS6: =IF(AND(CQ6=0,CR6=0), "0",IF(CR6,(CR6-CQ6),TODAY()-CQ6)) -> 0 | CW6: 'P2006000921', | CX6: =VLOOKUP(E6,'[1]List of Work Orders'!$A:$I,9,FALSE) -> ME168443 | DC6: =VLOOKUP(E6,'[2]List of Work Orders'!$A:$F,6,FALSE) -> FCOMP | DS6: RONILO GANGE JR.
A7: 44124 | B7: N/A | D7: MN | E7: P2009000813 | F7: MAINT 424WU Uprate from kVA to 75kVA : [039062|WA372558|A5-0334|QS] | G7: ROSAL STO. NINO STO. NINO PARANAQUE | H7: PARAÑAQUE CITY | I7: PARAÑAQUE | J7: for field survey by crew | K7: W/O ISSUE | L7: CHALLENGER | M7: INPRG | N7: Isan Carlo Lazaro | O7: 15.752 | P7: #N/A | Q7: 0 | R7: OLDT | S7: 160243.02 | T7: 10642.55 | V7: =U7/T7 -> 0 | W7: 44118.688 | X7: 44120.381 | Y7: 44103 | AC7: =AA7-W7 -> -44118.688 | AD7: =AA7-X7 -> -44120.381 | AE7: =AB7-AA7 -> 0 | AF7: =W7+AO7 -> #N/A | AG7: =W7+AN7 -> #N/A | AH7: =W7+50 -> 44168.688 | AI7: =(0.3)*(AC7/AK7)+(0.7)*(AC7/AL7) -> #N/A | AJ7: =AE7/AP7 -> 0 | AK7: =IF(P7<51,20,(IF(P7<101,23,(IF(P7<201,26,IF(P7<301,28,IF(P7<401,30,(IF(P7<501,32,(IF(P7<1001,40,50))))))))))) -> #N/A | AL7: =IF(Q7<51,36,(IF(Q7<101,34,(IF(Q7<201,32,IF(Q7<301,30,IF(Q7<401,28,(IF(Q7<501,26,(IF(Q7<1001,23,20))))))))))) -> 36 | AM7: =(0.75)/((0.3/AK7)+(0.7/AL7)) -> #N/A | AN7: =(0.95)/((0.3/AK7)+(0.7/AL7)) -> #N/A | AO7: =AM7-3 -> #N/A | AP7: 60 | AQ7: =0.95*AP7 -> 57 | AR7: =AQ7-5 -> 52 | AS7: =AA7+AP7 -> 60 | AT7: =IFERROR(TODAY()-AA7,"") -> 45895 | BC7: Transferred to DCB (point person for OLDT) | BE7: =AA7+15 -> 15 | BF7: =IF(ISBLANK(AA7),0,IF(ISBLANK(BH7),(BE7-$L$1),(BH7-BE7))) -> 0 | BQ7: N | BS7: Uprating | BT7: TLN 039062 | BU7: N | BV7: For schedule | BW7: Transferred from Alvin to Jimmy | CA7: =IF(AY7="Y",BA7,"0") -> 0 | CB7: =AC7-CA7 -> -44118.688 | CC7: =BA7 -> 0 | CD7: =AC7-BA7 -> -44118.688 | CE7: =(0.3)*(CD7/AK7)+(0.7)*(CD7/AL7) -> #N/A | CF7: =IF(AA7="","0",$CF$1-AA7) -> 0 | CH7: =(0.3)*(($CF$1-W7)/AK7)+(0.7)*(($CF$1-W7)/AL7) -> #N/A | CI7: =CH7-CG7 -> #N/A | CJ7: =CF7/AP7 -> 0 | CK7: =IF(AA7>0,"",$CK$1-W7) -> 1737.3118 | CL7: =IF(R7="NEW","REV","NON-REV") -> NON-REV | CM7: =IF(CK7="","",IF(CK7<91,"0-3 MONTHS",(IF(CK7<181,"4-6 MONTHS",(IF(CK7<271,"7-9 MONTHS",IF(CK7>270,"10 MONTHS AND ABOVE",))))))) -> 10 MONTHS AND ABOVE | CP7: =IF(CQ7,"NTC ISSUED","FOR ISSUANCE") -> FOR ISSUANCE | CS7: =IF(AND(CQ7=0,CR7=0), "0",IF(CR7,(CR7-CQ7),TODAY()-CQ7)) -> 0 | CW7: 'P2009000813', | CX7: =VLOOKUP(E7,'[1]List of Work Orders'!$A:$I,9,FALSE) -> ME166067 | DC7: =VLOOKUP(E7,'[2]List of Work Orders'!$A:$F,6,FALSE) -> INPRG | DS7: DCB
A8: 44133 | B8: N/A | D8: MN | E8: P2006000924 | F8: MAINT- 45WG Load-Split TLN 033207; Inst Addl 75KVA on DZ2-2222 | G8: ROAD 1 BAGONG TANYAG BAGONG TANYAG TAGUIG CITY | H8: TAGUIG CITY | I8: PARAÑAQUE | J8: ongoing | K8: W/ ISSUE | L8: POWERHOUSE | M8: INPRG | N8: Jenneth Madrid | O8: 59.228 | P8: #N/A | Q8: 0 | R8: OLDT | S8: 293278.03 | T8: 52996.47 | V8: =U8/T8 -> 0 | W8: 44125.726 | X8: 44127.658 | Y8: 44133 | AC8: =AA8-W8 -> -44125.726 | AD8: =AA8-X8 -> -44127.658 | AE8: =AB8-AA8 -> 0 | AF8: =W8+AO8 -> #N/A | AG8: =W8+AN8 -> #N/A | AH8: =W8+50 -> 44175.726 | AI8: =(0.3)*(AC8/AK8)+(0.7)*(AC8/AL8) -> #N/A | AJ8: =AE8/AP8 -> 0 | AK8: =IF(P8<51,20,(IF(P8<101,23,(IF(P8<201,26,IF(P8<301,28,IF(P8<401,30,(IF(P8<501,32,(IF(P8<1001,40,50))))))))))) -> #N/A | AL8: =IF(Q8<51,36,(IF(Q8<101,34,(IF(Q8<201,32,IF(Q8<301,30,IF(Q8<401,28,(IF(Q8<501,26,(IF(Q8<1001,23,20))))))))))) -> 36 | AM8: =(0.75)/((0.3/AK8)+(0.7/AL8)) -> #N/A | AN8: =(0.95)/((0.3/AK8)+(0.7/AL8)) -> #N/A | AO8: =AM8-3 -> #N/A | AP8: 60 | AQ8: =0.95*AP8 -> 57 | AR8: =AQ8-5 -> 52 | AS8: =AA8+AP8 -> 60 | AT8: =IFERROR(TODAY()-AA8,"") -> 45895 | BE8: =AA8+15 -> 15 | BF8: =IF(ISBLANK(AA8),0,IF(ISBLANK(BH8),(BE8-$L$1),(BH8-BE8))) -> 0 | BQ8: N | BS8: Load-splitting | BT8: TLN 033207 | BU8: Y | BV8: For schedule | BW8: Transferred from Marc to Jimmy / With picture after | CA8: =IF(AY8="Y",BA8,"0") -> 0 | CB8: =AC8-CA8 -> -44125.726 | CC8: =BA8 -> 0 | CD8: =AC8-BA8 -> -44125.726 | CE8: =(0.3)*(CD8/AK8)+(0.7)*(CD8/AL8) -> #N/A | CF8: =IF(AA8="","0",$CF$1-AA8) -> 0 | CH8: =(0.3)*(($CF$1-W8)/AK8)+(0.7)*(($CF$1-W8)/AL8) -> #N/A | CI8: =CH8-CG8 -> #N/A | CJ8: =CF8/AP8 -> 0 | CK8: =IF(AA8>0,"",$CK$1-W8) -> 1730.2743 | CL8: =IF(R8="NEW","REV","NON-REV") -> NON-REV | CM8: =IF(CK8="","",IF(CK8<91,"0-3 MONTHS",(IF(CK8<181,"4-6 MONTHS",(IF(CK8<271,"7-9 MONTHS",IF(CK8>270,"10 MONTHS AND ABOVE",))))))) -> 10 MONTHS AND ABOVE | CP8: =IF(CQ8,"NTC ISSUED","FOR ISSUANCE") -> FOR ISSUANCE | CS8: =IF(AND(CQ8=0,CR8=0), "0",IF(CR8,(CR8-CQ8),TODAY()-CQ8)) -> 0 | CW8: 'P2006000924', | CX8: =VLOOKUP(E8,'[1]List of Work Orders'!$A:$I,9,FALSE) -> ME185284 | DC8: =VLOOKUP(E8,'[2]List of Work Orders'!$A:$F,6,FALSE) -> INPRG | DS8: Jenneth Madrid
A9: 44168 | B9: N/A | D9: MN | E9: P2009000788 | F9: MN_MA, Uprate from 37.5kVA to 75kVA : [452201|WA200084|A5-1345|421WG|QS] | G9: E. RODRIGUEZ JR. MOONWALK MOONWALK PARANAQUE | H9: PARAÑAQUE CITY | I9: PARAÑAQUE | J9: ongoing | K9: W/O ISSUE | L9: CHALLENGER | M9: INPRG | N9: Isan Carlo Lazaro | O9: 15.952 | P9: #N/A | Q9: 0 | R9: OLDT | S9: 151461.47 | T9: 10764.63 | V9: =U9/T9 -> 0 | W9: 44158.696 | X9: 44160.665 | Y9: 44103 | AC9: =AA9-W9 -> -44158.696 | AD9: =AA9-X9 -> -44160.665 | AE9: =AB9-AA9 -> 0 | AF9: =W9+AO9 -> #N/A | AG9: =W9+AN9 -> #N/A | AH9: =W9+50 -> 44208.696 | AI9: =(0.3)*(AC9/AK9)+(0.7)*(AC9/AL9) -> #N/A | AJ9: =AE9/AP9 -> 0 | AK9: =IF(P9<51,20,(IF(P9<101,23,(IF(P9<201,26,IF(P9<301,28,IF(P9<401,30,(IF(P9<501,32,(IF(P9<1001,40,50))))))))))) -> #N/A | AL9: =IF(Q9<51,36,(IF(Q9<101,34,(IF(Q9<201,32,IF(Q9<301,30,IF(Q9<401,28,(IF(Q9<501,26,(IF(Q9<1001,23,20))))))))))) -> 36 | AM9: =(0.75)/((0.3/AK9)+(0.7/AL9)) -> #N/A | AN9: =(0.95)/((0.3/AK9)+(0.7/AL9)) -> #N/A | AO9: =AM9-3 -> #N/A | AP9: 60 | AQ9: =0.95*AP9 -> 57 | AR9: =AQ9-5 -> 52 | AS9: =AA9+AP9 -> 60 | AT9: =IFERROR(TODAY()-AA9,"") -> 45895 | BC9: Transferred to DCB (point person for OLDT) | BE9: =AA9+15 -> 15 | BF9: =IF(ISBLANK(AA9),0,IF(ISBLANK(BH9),(BE9-$L$1),(BH9-BE9))) -> 0 | BQ9: N | BS9: Uprating | BT9: TLN 452201 | BU9: N | BV9: For schedule | BW9: Transferred from Alvin to Jimmy / Based on pics with 75KVA already | CA9: =IF(AY9="Y",BA9,"0") -> 0 | CB9: =AC9-CA9 -> -44158.696 | CC9: =BA9 -> 0 | CD9: =AC9-BA9 -> -44158.696 | CE9: =(0.3)*(CD9/AK9)+(0.7)*(CD9/AL9) -> #N/A | CF9: =IF(AA9="","0",$CF$1-AA9) -> 0 | CH9: =(0.3)*(($CF$1-W9)/AK9)+(0.7)*(($CF$1-W9)/AL9) -> #N/A | CI9: =CH9-CG9 -> #N/A | CJ9: =CF9/AP9 -> 0 | CK9: =IF(AA9>0,"",$CK$1-W9) -> 1697.3042 | CL9: =IF(R9="NEW","REV","NON-REV") -> NON-REV | CM9: =IF(CK9="","",IF(CK9<91,"0-3 MONTHS",(IF(CK9<181,"4-6 MONTHS",(IF(CK9<271,"7-9 MONTHS",IF(CK9>270,"10 MONTHS AND ABOVE",))))))) -> 10 MONTHS AND ABOVE | CP9: =IF(CQ9,"NTC ISSUED","FOR ISSUANCE") -> FOR ISSUANCE | CS9: =IF(AND(CQ9=0,CR9=0), "0",IF(CR9,(CR9-CQ9),TODAY()-CQ9)) -> 0 | CW9: 'P2009000788', | CX9: =VLOOKUP(E9,'[1]List of Work Orders'!$A:$I,9,FALSE) -> ME166067 | DC9: =VLOOKUP(E9,'[2]List of Work Orders'!$A:$F,6,FALSE) -> INPRG | DS9: DCB
A10: 44168 | B10: N/A | D10: MN | E10: P2007000208 | F10: MAINT 425WG Load-Split 087388/WA345584/100KVA; Inst Addl 75KVA on A7-1008 | G10: KOURUS CAMELLA HOMES MERVILLE PARANAQUE | H10: PARAÑAQUE CITY | I10: PARAÑAQUE | J10: ongoing | K10: W/O ISSUE | L10: CHALLENGER | M10: INPRG | N10: Isan Carlo Lazaro | O10: 36.1285 | P10: #N/A | Q10: 0 | R10: OLDT | S10: 282791.21 | T10: 104391 | V10: =U10/T10 -> 0 | W10: 44166.708 | X10: 44167.411 | Y10: 44168 | AC10: =AA10-W10 -> -44166.708 | AD10: =AA10-X10 -> -44167.411 | AE10: =AB10-AA10 -> 0 | AF10: =W10+AO10 -> #N/A | AG10: =W10+AN10 -> #N/A | AH10: =W10+50 -> 44216.708 | AI10: =(0.3)*(AC10/AK10)+(0.7)*(AC10/AL10) -> #N/A | AJ10: =AE10/AP10 -> 0 | AK10: =IF(P10<51,20,(IF(P10<101,23,(IF(P10<201,26,IF(P10<301,28,IF(P10<401,30,(IF(P10<501,32,(IF(P10<1001,40,50))))))))))) -> #N/A | AL10: =IF(Q10<51,36,(IF(Q10<101,34,(IF(Q10<201,32,IF(Q10<301,30,IF(Q10<401,28,(IF(Q10<501,26,(IF(Q10<1001,23,20))))))))))) -> 36 | AM10: =(0.75)/((0.3/AK10)+(0.7/AL10)) -> #N/A | AN10: =(0.95)/((0.3/AK10)+(0.7/AL10)) -> #N/A | AO10: =AM10-3 -> #N/A | AP10: 60 | AQ10: =0.95*AP10 -> 57 | AR10: =AQ10-5 -> 52 | AS10: =AA10+AP10 -> 60 | AT10: =IFERROR(TODAY()-AA10,"") -> 45895 | BC10: Transferred to DCB (point person for OLDT) | BE10: =AA10+15 -> 15 | BF10: =IF(ISBLANK(AA10),0,IF(ISBLANK(BH10),(BE10-$L$1),(BH10-BE10))) -> 0 | BQ10: N | BS10: Load-splitting | BT10: TLN 087388 | BU10: Y | BV10: For schedule | BW10: Transferred from Alvin to Jimmy | CA10: =IF(AY10="Y",BA10,"0") -> 0 | CB10: =AC10-CA10 -> -44166.708 | CC10: =BA10 -> 0 | CD10: =AC10-BA10 -> -44166.708 | CE10: =(0.3)*(CD10/AK10)+(0.7)*(CD10/AL10) -> #N/A | CF10: =IF(AA10="","0",$CF$1-AA10) -> 0 | CH10: =(0.3)*(($CF$1-W10)/AK10)+(0.7)*(($CF$1-W10)/AL10) -> #N/A | CI10: =CH10-CG10 -> #N/A | CJ10: =CF10/AP10 -> 0 | CK10: =IF(AA10>0,"",$CK$1-W10) -> 1689.2924 | CL10: =IF(R10="NEW","REV","NON-REV") -> NON-REV | CM10: =IF(CK10="","",IF(CK10<91,"0-3 MONTHS",(IF(CK10<181,"4-6 MONTHS",(IF(CK10<271,"7-9 MONTHS",IF(CK10>270,"10 MONTHS AND ABOVE",))))))) -> 10 MONTHS AND ABOVE | CP10: =IF(CQ10,"NTC ISSUED","FOR ISSUANCE") -> FOR ISSUANCE | CS10: =IF(AND(CQ10=0,CR10=0), "0",IF(CR10,(CR10-CQ10),TODAY()-CQ10)) -> 0 | CW10: 'P2007000208', | CX10: =VLOOKUP(E10,'[1]List of Work Orders'!$A:$I,9,FALSE) -> ME166067 | DC10: =VLOOKUP(E10,'[2]List of Work Orders'!$A:$F,6,FALSE) -> INPRG | DS10: DCB
A11: 44180 | B11: N/A | D11: MN | E11: P2009000548 | F11: MAINT 55GG Loadsplit [069426|WA145069|DZ2-0528| Install addl 2-75 kVA on Pole DZ2-0526 | G11: V.P. CRUZ PUROK 5 LOWER BICUTAN TAGUIG CITY | H11: TAGUIG CITY | I11: PARAÑAQUE | J11: ongoing | K11: W/ ISSUE | L11: VJC | M11: CAN | N11: Jenneth Madrid | O11: 50.339 | P11: #N/A | Q11: 0 | R11: OLDT | S11: 366502.48 | T11: 38657.97 | V11: =U11/T11 -> 0 | W11: 44174.681 | X11: 44179.567 | Y11: 44182 | AA11: CAN | AC11: =AA11-W11 -> #VALUE! | AD11: =AA11-X11 -> #VALUE! | AE11: =AB11-AA11 -> #VALUE! | AF11: =W11+AO11 -> #N/A | AG11: =W11+AN11 -> #N/A | AH11: =W11+50 -> 44224.681 | AI11: =(0.3)*(AC11/AK11)+(0.7)*(AC11/AL11) -> #VALUE! | AJ11: =AE11/AP11 -> #VALUE! | AK11: =IF(P11<51,20,(IF(P11<101,23,(IF(P11<201,26,IF(P11<301,28,IF(P11<401,30,(IF(P11<501,32,(IF(P11<1001,40,50))))))))))) -> #N/A | AL11: =IF(Q11<51,36,(IF(Q11<101,34,(IF(Q11<201,32,IF(Q11<301,30,IF(Q11<401,28,(IF(Q11<501,26,(IF(Q11<1001,23,20))))))))))) -> 36 | AM11: =(0.75)/((0.3/AK11)+(0.7/AL11)) -> #N/A | AN11: =(0.95)/((0.3/AK11)+(0.7/AL11)) -> #N/A | AO11: =AM11-3 -> #N/A | AP11: 60 | AQ11: =0.95*AP11 -> 57 | AR11: =AQ11-5 -> 52 | AS11: =AA11+AP11 -> #VALUE! | AT11: =IFERROR(TODAY()-AA11,"") | BE11: =AA11+15 -> #VALUE! | BF11: =IF(ISBLANK(AA11),0,IF(ISBLANK(BH11),(BE11-$L$1),(BH11-BE11))) -> #VALUE! | BQ11: N | BS11: Load-splitting | BT11: TLN 069426 | BU11: Y | BV11: With concern | BW11: Transferred from Alvin to Jimmy | CA11: =IF(AY11="Y",BA11,"0") -> 0 | CB11: =AC11-CA11 -> #VALUE! | CC11: =BA11 -> 0 | CD11: =AC11-BA11 -> #VALUE! | CE11: =(0.3)*(CD11/AK11)+(0.7)*(CD11/AL11) -> #VALUE! | CF11: =IF(AA11="","0",$CF$1-AA11) -> #VALUE! | CH11: =(0.3)*(($CF$1-W11)/AK11)+(0.7)*(($CF$1-W11)/AL11) -> #N/A | CI11: =CH11-CG11 -> #N/A | CJ11: =CF11/AP11 -> #VALUE! | CK11: =IF(AA11>0,"",$CK$1-W11) | CL11: =IF(R11="NEW","REV","NON-REV") -> NON-REV | CM11: =IF(CK11="","",IF(CK11<91,"0-3 MONTHS",(IF(CK11<181,"4-6 MONTHS",(IF(CK11<271,"7-9 MONTHS",IF(CK11>270,"10 MONTHS AND ABOVE",))))))) | CP11: =IF(CQ11,"NTC ISSUED","FOR ISSUANCE") -> FOR ISSUANCE | CS11: =IF(AND(CQ11=0,CR11=0), "0",IF(CR11,(CR11-CQ11),TODAY()-CQ11)) -> 0 | CW11: 'P2009000548', | CX11: =VLOOKUP(E11,'[1]List of Work Orders'!$A:$I,9,FALSE) -> ME185284 | DC11: =VLOOKUP(E11,'[2]List of Work Orders'!$A:$F,6,FALSE) -> CAN | DS11: Jenneth Madrid
A12: 44186 | B12: N/A | D12: MN | E12: P2007000394 | F12: MAINT_55GG Load-Split 111627/WA329429/50KVA; Inst Addl 75KVA on C8-5486 | G12: 7TH GHQ VILL SIGNAL VILLAGE TAGUIG CITY | H12: TAGUIG CITY | I12: PARAÑAQUE | J12: ongoing | K12: W/O ISSUE | L12: CHALLENGER | M12: INPRG | N12: Isan Carlo Lazaro | O12: 45.5807 | P12: #N/A | Q12: 0 | R12: OLDT | S12: 213069.82 | T12: 36545.79 | V12: =U12/T12 -> 0 | W12: 44179.022 | X12: 44181.539 | Y12: 44180 | AC12: =AA12-W12 -> -44179.022 | AD12: =AA12-X12 -> -44181.539 | AE12: =AB12-AA12 -> 0 | AF12: =W12+AO12 -> #N/A | AG12: =W12+AN12 -> #N/A | AH12: =W12+50 -> 44229.022 | AI12: =(0.3)*(AC12/AK12)+(0.7)*(AC12/AL12) -> #N/A | AJ12: =AE12/AP12 -> 0 | AK12: =IF(P12<51,20,(IF(P12<101,23,(IF(P12<201,26,IF(P12<301,28,IF(P12<401,30,(IF(P12<501,32,(IF(P12<1001,40,50))))))))))) -> #N/A | AL12: =IF(Q12<51,36,(IF(Q12<101,34,(IF(Q12<201,32,IF(Q12<301,30,IF(Q12<401,28,(IF(Q12<501,26,(IF(Q12<1001,23,20))))))))))) -> 36 | AM12: =(0.75)/((0.3/AK12)+(0.7/AL12)) -> #N/A | AN12: =(0.95)/((0.3/AK12)+(0.7/AL12)) -> #N/A | AO12: =AM12-3 -> #N/A | AP12: 60 | AQ12: =0.95*AP12 -> 57 | AR12: =AQ12-5 -> 52 | AS12: =AA12+AP12 -> 60 | AT12: =IFERROR(TODAY()-AA12,"") -> 45895 | BC12: Transferred to DCB (point person for OLDT) | BE12: =AA12+15 -> 15 | BF12: =IF(ISBLANK(AA12),0,IF(ISBLANK(BH12),(BE12-$L$1),(BH12-BE12))) -> 0 | BQ12: N | BS12: Load-splitting | BT12: TLN 111627 | BU12: N | BV12: For schedule | BW12: Transferred from Alvin to Jimmy | CA12: =IF(AY12="Y",BA12,"0") -> 0 | CB12: =AC12-CA12 -> -44179.022 | CC12: =BA12 -> 0 | CD12: =AC12-BA12 -> -44179.022 | CE12: =(0.3)*(CD12/AK12)+(0.7)*(CD12/AL12) -> #N/A | CF12: =IF(AA12="","0",$CF$1-AA12) -> 0 | CH12: =(0.3)*(($CF$1-W12)/AK12)+(0.7)*(($CF$1-W12)/AL12) -> #N/A | CI12: =CH12-CG12 -> #N/A | CJ12: =CF12/AP12 -> 0 | CK12: =IF(AA12>0,"",$CK$1-W12) -> 1676.9778 | CL12: =IF(R12="NEW","REV","NON-REV") -> NON-REV | CM12: =IF(CK12="","",IF(CK12<91,"0-3 MONTHS",(IF(CK12<181,"4-6 MONTHS",(IF(CK12<271,"7-9 MONTHS",IF(CK12>270,"10 MONTHS AND ABOVE",))))))) -> 10 MONTHS AND ABOVE | CP12: =IF(CQ12,"NTC ISSUED","FOR ISSUANCE") -> FOR ISSUANCE | CS12: =IF(AND(CQ12=0,CR12=0), "0",IF(CR12,(CR12-CQ12),TODAY()-CQ12)) -> 0 | CW12: 'P2007000394', | CX12: =VLOOKUP(E12,'[1]List of Work Orders'!$A:$I,9,FALSE) -> ME166067 | DC12: =VLOOKUP(E12,'[2]List of Work Orders'!$A:$F,6,FALSE) -> INPRG | DS12: DCB
A13: 44202 | B13: N/A | D13: MN | E13: P2009000586 | F13: MN_MA, Loadsplit from kVA to 0 DT (kVA,kVA,kVA,kVA) : [134661||DV1-0012|56GG|QS] | G13: PRES. M.L. QUEZON CUPANG CUPANG MUNTINLUPA | H13: MUNTINLUPA CITY | I13: PARAÑAQUE | J13: ongoing | K13: W/ ISSUE | L13: ECOM | M13: PCAN3 | N13: Dean Carl Borjal | O13: 13.072 | P13: #N/A | Q13: 0 | R13: OLDT | S13: 169419.8 | T13: 17546.74 | V13: =U13/T13 -> 0 | W13: 44195.854 | X13: 44201.439 | Y13: 44221 | AC13: =AA13-W13 -> -44195.854 | AD13: =AA13-X13 -> -44201.439 | AE13: =AB13-AA13 -> 0 | AF13: =W13+AO13 -> #N/A | AG13: =W13+AN13 -> #N/A | AH13: =W13+50 -> 44245.854 | AI13: =(0.3)*(AC13/AK13)+(0.7)*(AC13/AL13) -> #N/A | AJ13: =AE13/AP13 -> 0 | AK13: =IF(P13<51,20,(IF(P13<101,23,(IF(P13<201,26,IF(P13<301,28,IF(P13<401,30,(IF(P13<501,32,(IF(P13<1001,40,50))))))))))) -> #N/A | AL13: =IF(Q13<51,36,(IF(Q13<101,34,(IF(Q13<201,32,IF(Q13<301,30,IF(Q13<401,28,(IF(Q13<501,26,(IF(Q13<1001,23,20))))))))))) -> 36 | AM13: =(0.75)/((0.3/AK13)+(0.7/AL13)) -> #N/A | AN13: =(0.95)/((0.3/AK13)+(0.7/AL13)) -> #N/A | AO13: =AM13-3 -> #N/A | AP13: 60 | AQ13: =0.95*AP13 -> 57 | AR13: =AQ13-5 -> 52 | AS13: =AA13+AP13 -> 60 | AT13: =IFERROR(TODAY()-AA13,"") -> 45895 | BE13: =AA13+15 -> 15 | BF13: =IF(ISBLANK(AA13),0,IF(ISBLANK(BH13),(BE13-$L$1),(BH13-BE13))) -> 0 | BQ13: N | BS13: Load-splitting | BT13: TLN 134661 | BU13: Y | BV13: For schedule | BW13: Transferred from Alvin to Jimmy / (ERV - ECOM) | CA13: =IF(AY13="Y",BA13,"0") -> 0 | CB13: =AC13-CA13 -> -44195.854 | CC13: =BA13 -> 0 | CD13: =AC13-BA13 -> -44195.854 | CE13: =(0.3)*(CD13/AK13)+(0.7)*(CD13/AL13) -> #N/A | CF13: =IF(AA13="","0",$CF$1-AA13) -> 0 | CH13: =(0.3)*(($CF$1-W13)/AK13)+(0.7)*(($CF$1-W13)/AL13) -> #N/A | CI13: =CH13-CG13 -> #N/A | CJ13: =CF13/AP13 -> 0 | CK13: =IF(AA13>0,"",$CK$1-W13) -> 1660.1458 | CL13: =IF(R13="NEW","REV","NON-REV") -> NON-REV | CM13: =IF(CK13="","",IF(CK13<91,"0-3 MONTHS",(IF(CK13<181,"4-6 MONTHS",(IF(CK13<271,"7-9 MONTHS",IF(CK13>270,"10 MONTHS AND ABOVE",))))))) -> 10 MONTHS AND ABOVE | CP13: =IF(CQ13,"NTC ISSUED","FOR ISSUANCE") -> FOR ISSUANCE | CS13: =IF(AND(CQ13=0,CR13=0), "0",IF(CR13,(CR13-CQ13),TODAY()-CQ13)) -> 0 | CW13: 'P2009000586', | CX13: =VLOOKUP(E13,'[1]List of Work Orders'!$A:$I,9,FALSE) -> ME168443 | DC13: =VLOOKUP(E13,'[2]List of Work Orders'!$A:$F,6,FALSE) -> PCAN3 | DS13: DCB
B14: N/A | D14: MN | E14: P2101102759 | F14: MN_MAJOR, Loadsplit 51XD [037203|WA343521|CV8-1375||] install addl 1-75kVA @ CV8- 1384 | G14: 5TH GOLDEN GATE SUBD TALON III LAS PINAS CITY | H14: LAS PIÑAS CITY | I14: PARAÑAQUE | J14: ongoing | K14: W/O ISSUE | L14: CHALLENGER | M14: SCHED | N14: Isan Carlo Lazaro | O14: 10.482 | P14: #N/A | Q14: 0 | R14: OLDT | S14: 137331.68 | T14: 7006.35 | V14: =U14/T14 -> 0 | W14: 44227.892 | X14: 44229.566 | Y14: 44229 | AC14: =AA14-W14 -> -44227.892 | AD14: =AA14-X14 -> -44229.566 | AE14: =AB14-AA14 -> 0 | AF14: =W14+AO14 -> #N/A | AG14: =W14+AN14 -> #N/A | AH14: =W14+50 -> 44277.892 | AI14: =(0.3)*(AC14/AK14)+(0.7)*(AC14/AL14) -> #N/A | AJ14: =AE14/AP14 -> 0 | AK14: =IF(P14<51,20,(IF(P14<101,23,(IF(P14<201,26,IF(P14<301,28,IF(P14<401,30,(IF(P14<501,32,(IF(P14<1001,40,50))))))))))) -> #N/A | AL14: =IF(Q14<51,36,(IF(Q14<101,34,(IF(Q14<201,32,IF(Q14<301,30,IF(Q14<401,28,(IF(Q14<501,26,(IF(Q14<1001,23,20))))))))))) -> 36 | AM14: =(0.75)/((0.3/AK14)+(0.7/AL14)) -> #N/A | AN14: =(0.95)/((0.3/AK14)+(0.7/AL14)) -> #N/A | AO14: =AM14-3 -> #N/A | AP14: 60 | AQ14: =0.95*AP14 -> 57 | AR14: =AQ14-5 -> 52 | AS14: =AA14+AP14 -> 60 | AT14: =IFERROR(TODAY()-AA14,"") -> 45895 | BC14: Transferred to DCB (point person for OLDT) | BE14: =AA14+15 -> 15 | BF14: =IF(ISBLANK(AA14),0,IF(ISBLANK(BH14),(BE14-$L$1),(BH14-BE14))) -> 0 | BQ14: N | BS14: Load-splitting | BT14: TLN 037203 | BU14: N | BV14: For schedule | BW14: Transferred from Alvin to Jimmy | CA14: =IF(AY14="Y",BA14,"0") -> 0 | CB14: =AC14-CA14 -> -44227.892 | CC14: =BA14 -> 0 | CD14: =AC14-BA14 -> -44227.892 | CE14: =(0.3)*(CD14/AK14)+(0.7)*(CD14/AL14) -> #N/A | CF14: =IF(AA14="","0",$CF$1-AA14) -> 0 | CH14: =(0.3)*(($CF$1-W14)/AK14)+(0.7)*(($CF$1-W14)/AL14) -> #N/A | CI14: =CH14-CG14 -> #N/A | CJ14: =CF14/AP14 -> 0 | CK14: =IF(AA14>0,"",$CK$1-W14) -> 1628.1083 | CL14: =IF(R14="NEW","REV","NON-REV") -> NON-REV | CM14: =IF(CK14="","",IF(CK14<91,"0-3 MONTHS",(IF(CK14<181,"4-6 MONTHS",(IF(CK14<271,"7-9 MONTHS",IF(CK14>270,"10 MONTHS AND ABOVE",))))))) -> 10 MONTHS AND ABOVE | CP14: =IF(CQ14,"NTC ISSUED","FOR ISSUANCE") -> FOR ISSUANCE | CS14: =IF(AND(CQ14=0,CR14=0), "0",IF(CR14,(CR14-CQ14),TODAY()-CQ14)) -> 0 | CW14: 'P2101102759', | CX14: =VLOOKUP(E14,'[1]List of Work Orders'!$A:$I,9,FALSE) -> ME166067 | DC14: =VLOOKUP(E14,'[2]List of Work Orders'!$A:$F,6,FALSE) -> SCHED | DS14: DCB
A15: 44249 | B15: N/A | D15: MN | E15: P2101102674 | F15: MN_MAJOR, Loadsplit from 75kVA : [003404|WA110981|DR1-0404|57GG|] | G15: ESTANISLAO LAKEVIEW HOMES I PUTATAN MUNTINLUPA | H15: MUNTINLUPA CITY | I15: PARAÑAQUE | J15: change vendor/For Re-assignmnet | K15: W/ ISSUE | L15: OPS | M15: FCOMP | N15: Dean Carl Borjal | O15: 243.12 | P15: 243.12 | Q15: 0 | R15: OLDT | S15: 333455.39 | T15: 85386.64 | V15: =U15/T15 -> 0 | W15: 44245.694 | X15: 44246.69 | Y15: 44228 | AA15: 45760 | AC15: =AA15-W15 -> 1514.3056 | AD15: =AA15-X15 -> 1513.3097 | AE15: =AB15-AA15 -> -45760 | AF15: =W15+AO15 -> 44267.563 | AG15: =W15+AN15 -> 44277.194 | AH15: =W15+50 -> 44295.694 | AI15: =(0.3)*(AC15/AK15)+(0.7)*(AC15/AL15) -> 45.669533 | AJ15: =AE15/AP15 -> -762.66667 | AK15: =IF(P15<51,20,(IF(P15<101,23,(IF(P15<201,26,IF(P15<301,28,IF(P15<401,30,(IF(P15<501,32,(IF(P15<1001,40,50))))))))))) -> 28 | AL15: =IF(Q15<51,36,(IF(Q15<101,34,(IF(Q15<201,32,IF(Q15<301,30,IF(Q15<401,28,(IF(Q15<501,26,(IF(Q15<1001,23,20))))))))))) -> 36 | AM15: =(0.75)/((0.3/AK15)+(0.7/AL15)) -> 24.868421 | AN15: =(0.95)/((0.3/AK15)+(0.7/AL15)) -> 31.5 | AO15: =AM15-3 -> 21.868421 | AP15: 60 | AQ15: =0.95*AP15 -> 57 | AR15: =AQ15-5 -> 52 | AS15: =AA15+AP15 -> 45820 | AT15: =IFERROR(TODAY()-AA15,"") -> 135 | BC15: NO COC | BE15: =AA15+15 -> 45775 | BF15: =IF(ISBLANK(AA15),0,IF(ISBLANK(BH15),(BE15-$L$1),(BH15-BE15))) -> #VALUE! | BQ15: N | BS15: Load-splitting | BT15: TLN 003404 | BU15: Y | BV15: With concern | BW15: Transferred from Alvin to Jimmy | CA15: =IF(AY15="Y",BA15,"0") -> 0 | CB15: =AC15-CA15 -> 1514.3056 | CC15: =BA15 -> 0 | CD15: =AC15-BA15 -> 1514.3056 | CE15: =(0.3)*(CD15/AK15)+(0.7)*(CD15/AL15) -> 45.669533 | CF15: =IF(AA15="","0",$CF$1-AA15) -> 109 | CH15: =(0.3)*(($CF$1-W15)/AK15)+(0.7)*(($CF$1-W15)/AL15) -> 48.956834 | CI15: =CH15-CG15 -> 48.956834 | CJ15: =CF15/AP15 -> 1.8166667 | CK15: =IF(AA15>0,"",$CK$1-W15) | CL15: =IF(R15="NEW","REV","NON-REV") -> NON-REV | CM15: =IF(CK15="","",IF(CK15<91,"0-3 MONTHS",(IF(CK15<181,"4-6 MONTHS",(IF(CK15<271,"7-9 MONTHS",IF(CK15>270,"10 MONTHS AND ABOVE",))))))) | CP15: =IF(CQ15,"NTC ISSUED","FOR ISSUANCE") -> FOR ISSUANCE | CS15: =IF(AND(CQ15=0,CR15=0), "0",IF(CR15,(CR15-CQ15),TODAY()-CQ15)) -> 0 | CW15: 'P2101102674', | CX15: =VLOOKUP(E15,'[1]List of Work Orders'!$A:$I,9,FALSE) -> ME168443 | DC15: =VLOOKUP(E15,'[2]List of Work Orders'!$A:$F,6,FALSE) -> FCOMP | DS15: DCB
A16: 44251 | B16: N/A | D16: MN | E16: P2101102720 | F16: MN_MAJOR, Loadsplit from 100kVA : [069436|WA368739|B8-0835|55GG|] | G16: MIRANDA ZONE 1 SIGNAL VILLAGE TAGUIG CITY | H16: TAGUIG CITY | I16: PARAÑAQUE | J16: not feasible; for survey team C1 | K16: W/ ISSUE | L16: ECOM | M16: PCAN3 | N16: Dean Carl Borjal | O16: 43.2905 | P16: #N/A | Q16: 0 | R16: OLDT | S16: 199593.3 | T16: 32150.01 | V16: =U16/T16 -> 0 | W16: 44246.66 | X16: 44250.649 | Y16: 44228 | AC16: =AA16-W16 -> -44246.66 | AD16: =AA16-X16 -> -44250.649 | AE16: =AB16-AA16 -> 0 | AF16: =W16+AO16 -> #N/A | AG16: =W16+AN16 -> #N/A | AH16: =W16+50 -> 44296.66 | AI16: =(0.3)*(AC16/AK16)+(0.7)*(AC16/AL16) -> #N/A | AJ16: =AE16/AP16 -> 0 | AK16: =IF(P16<51,20,(IF(P16<101,23,(IF(P16<201,26,IF(P16<301,28,IF(P16<401,30,(IF(P16<501,32,(IF(P16<1001,40,50))))))))))) -> #N/A | AL16: =IF(Q16<51,36,(IF(Q16<101,34,(IF(Q16<201,32,IF(Q16<301,30,IF(Q16<401,28,(IF(Q16<501,26,(IF(Q16<1001,23,20))))))))))) -> 36 | AM16: =(0.75)/((0.3/AK16)+(0.7/AL16)) -> #N/A | AN16: =(0.95)/((0.3/AK16)+(0.7/AL16)) -> #N/A | AO16: =AM16-3 -> #N/A | AP16: 60 | AQ16: =0.95*AP16 -> 57 | AR16: =AQ16-5 -> 52 | AS16: =AA16+AP16 -> 60 | AT16: =IFERROR(TODAY()-AA16,"") -> 45895 | BE16: =AA16+15 -> 15 | BF16: =IF(ISBLANK(AA16),0,IF(ISBLANK(BH16),(BE16-$L$1),(BH16-BE16))) -> 0 | BQ16: N | BS16: Load-splitting | BT16: TLN 069436 | BU16: Y | BV16: With concern | BW16: Transferred from Alvin to Jimmy | CA16: =IF(AY16="Y",BA16,"0") -> 0 | CB16: =AC16-CA16 -> -44246.66 | CC16: =BA16 -> 0 | CD16: =AC16-BA16 -> -44246.66 | CE16: =(0.3)*(CD16/AK16)+(0.7)*(CD16/AL16) -> #N/A | CF16: =IF(AA16="","0",$CF$1-AA16) -> 0 | CH16: =(0.3)*(($CF$1-W16)/AK16)+(0.7)*(($CF$1-W16)/AL16) -> #N/A | CI16: =CH16-CG16 -> #N/A | CJ16: =CF16/AP16 -> 0 | CK16: =IF(AA16>0,"",$CK$1-W16) -> 1609.3403 | CL16: =IF(R16="NEW","REV","NON-REV") -> NON-REV | CM16: =IF(CK16="","",IF(CK16<91,"0-3 MONTHS",(IF(CK16<181,"4-6 MONTHS",(IF(CK16<271,"7-9 MONTHS",IF(CK16>270,"10 MONTHS AND ABOVE",))))))) -> 10 MONTHS AND ABOVE | CP16: =IF(CQ16,"NTC ISSUED","FOR ISSUANCE") -> FOR ISSUANCE | CS16: =IF(AND(CQ16=0,CR16=0), "0",IF(CR16,(CR16-CQ16),TODAY()-CQ16)) -> 0 | CW16: 'P2101102720', | CX16: =VLOOKUP(E16,'[1]List of Work Orders'!$A:$I,9,FALSE) -> ME168443 | DC16: =VLOOKUP(E16,'[2]List of Work Orders'!$A:$F,6,FALSE) -> PCAN3 | DS16: DCB
A17: 44251 | B17: N/A | D17: MN | E17: P2101102682 | F17: MN_MAJOR, Loadsplit from 75kVA : [063873|WA344251|DR1-1343|46WH|] | G17: BORACAY CAMELLA HOMES ALABANG 4 SUBD POBLACION MUNTINLUPA | H17: MUNTINLUPA CITY | I17: PARAÑAQUE | J17: for crew survey; for C1 survey | K17: W/ ISSUE | L17: ECOM | M17: FCOMP | N17: Dean Carl Borjal | O17: 47.38 | P17: 47.38 | Q17: 0 | R17: OLDT | S17: 187468.53 | T17: 23355.85 | V17: =U17/T17 -> 0 | W17: 44249.591 | X17: 44250.443 | Y17: 44222 | AA17: 45720 | AC17: =AA17-W17 -> 1470.409 | AD17: =AA17-X17 -> 1469.5569 | AE17: =AB17-AA17 -> -45720 | AF17: =W17+AO17 -> 44268.365 | AG17: =W17+AN17 -> 44277.172 | AH17: =W17+50 -> 44299.591 | AI17: =(0.3)*(AC17/AK17)+(0.7)*(AC17/AL17) -> 50.647422 | AJ17: =AE17/AP17 -> -762 | AK17: =IF(P17<51,20,(IF(P17<101,23,(IF(P17<201,26,IF(P17<301,28,IF(P17<401,30,(IF(P17<501,32,(IF(P17<1001,40,50))))))))))) -> 20 | AL17: =IF(Q17<51,36,(IF(Q17<101,34,(IF(Q17<201,32,IF(Q17<301,30,IF(Q17<401,28,(IF(Q17<501,26,(IF(Q17<1001,23,20))))))))))) -> 36 | AM17: =(0.75)/((0.3/AK17)+(0.7/AL17)) -> 21.774194 | AN17: =(0.95)/((0.3/AK17)+(0.7/AL17)) -> 27.580645 | AO17: =AM17-3 -> 18.774194 | AP17: 60 | AQ17: =0.95*AP17 -> 57 | AR17: =AQ17-5 -> 52 | AS17: =AA17+AP17 -> 45780 | AT17: =IFERROR(TODAY()-AA17,"") -> 175 | BC17: NO COC | BE17: =AA17+15 -> 45735 | BF17: =IF(ISBLANK(AA17),0,IF(ISBLANK(BH17),(BE17-$L$1),(BH17-BE17))) -> #VALUE! | BQ17: N | BS17: Load-splitting | BT17: TLN 063873 | BU17: Y | BV17: With concern | BW17: Transferred from Alvin to Jimmy | CA17: =IF(AY17="Y",BA17,"0") -> 0 | CB17: =AC17-CA17 -> 1470.409 | CC17: =BA17 -> 0 | CD17: =AC17-BA17 -> 1470.409 | CE17: =(0.3)*(CD17/AK17)+(0.7)*(CD17/AL17) -> 50.647422 | CF17: =IF(AA17="","0",$CF$1-AA17) -> 149 | CH17: =(0.3)*(($CF$1-W17)/AK17)+(0.7)*(($CF$1-W17)/AL17) -> 55.779644 | CI17: =CH17-CG17 -> 55.779644 | CJ17: =CF17/AP17 -> 2.4833333 | CK17: =IF(AA17>0,"",$CK$1-W17) | CL17: =IF(R17="NEW","REV","NON-REV") -> NON-REV | CM17: =IF(CK17="","",IF(CK17<91,"0-3 MONTHS",(IF(CK17<181,"4-6 MONTHS",(IF(CK17<271,"7-9 MONTHS",IF(CK17>270,"10 MONTHS AND ABOVE",))))))) | CP17: =IF(CQ17,"NTC ISSUED","FOR ISSUANCE") -> FOR ISSUANCE | CS17: =IF(AND(CQ17=0,CR17=0), "0",IF(CR17,(CR17-CQ17),TODAY()-CQ17)) -> 0 | CW17: 'P2101102682', | CX17: =VLOOKUP(E17,'[1]List of Work Orders'!$A:$I,9,FALSE) -> ME168443 | DC17: =VLOOKUP(E17,'[2]List of Work Orders'!$A:$F,6,FALSE) -> FCOMP | DS17: DCB
B18: N/A | D18: MN | E18: 100338058856 | F18: MAINT - 414FIL - Retirement of Idle poles and other facilities pole DU1-2176 | G18: ALABANG-ZAPOTE FILINVEST CORPORATE CITY ALABANG MUNTINLUPA | H18: MUNTINLUPA CITY | I18: PARAÑAQUE | J18: for permit on Feb. 22, 2023; no feed back; permit lapsed (03-08-23); | K18: W/O ISSUE | L18: ECOM | M18: SCHED | N18: Ronilo Gange Jr. | O18: 12.8467 | P18: #N/A | Q18: 0 | R18: RETIREMENT OF IDLE FACILITES | S18: 12290.71 | T18: 11929.02 | V18: =U18/T18 -> 0 | W18: 44383.023 | X18: 44383.367 | Y18: 44473 | AC18: =AA18-W18 -> -44383.023 | AD18: =AA18-X18 -> -44383.367 | AE18: =AB18-AA18 -> 0 | AF18: =W18+AO18 -> #N/A | AG18: =W18+AN18 -> #N/A | AH18: =W18+50 -> 44433.023 | AI18: =(0.3)*(AC18/AK18)+(0.7)*(AC18/AL18) -> #N/A | AJ18: =AE18/AP18 -> 0 | AK18: =IF(P18<51,20,(IF(P18<101,23,(IF(P18<201,26,IF(P18<301,28,IF(P18<401,30,(IF(P18<501,32,(IF(P18<1001,40,50))))))))))) -> #N/A | AL18: =IF(Q18<51,36,(IF(Q18<101,34,(IF(Q18<201,32,IF(Q18<301,30,IF(Q18<401,28,(IF(Q18<501,26,(IF(Q18<1001,23,20))))))))))) -> 36 | AM18: =(0.75)/((0.3/AK18)+(0.7/AL18)) -> #N/A | AN18: =(0.95)/((0.3/AK18)+(0.7/AL18)) -> #N/A | AO18: =AM18-3 -> #N/A | AP18: 60 | AQ18: =0.95*AP18 -> 57 | AR18: =AQ18-5 -> 52 | AS18: =AA18+AP18 -> 60 | AT18: =IFERROR(TODAY()-AA18,"") -> 45895 | BE18: =AA18+15 -> 15 | BF18: =IF(ISBLANK(AA18),0,IF(ISBLANK(BH18),(BE18-$L$1),(BH18-BE18))) -> 0 | BQ18: N | CA18: =IF(AY18="Y",BA18,"0") -> 0 | CB18: =AC18-CA18 -> -44383.023 | CC18: =BA18 -> 0 | CD18: =AC18-BA18 -> -44383.023 | CE18: =(0.3)*(CD18/AK18)+(0.7)*(CD18/AL18) -> #N/A | CF18: =IF(AA18="","0",$CF$1-AA18) -> 0 | CH18: =(0.3)*(($CF$1-W18)/AK18)+(0.7)*(($CF$1-W18)/AL18) -> #N/A | CI18: =CH18-CG18 -> #N/A | CJ18: =CF18/AP18 -> 0 | CK18: =IF(AA18>0,"",$CK$1-W18) -> 1472.9771 | CL18: =IF(R18="NEW","REV","NON-REV") -> NON-REV | CM18: =IF(CK18="","",IF(CK18<91,"0-3 MONTHS",(IF(CK18<181,"4-6 MONTHS",(IF(CK18<271,"7-9 MONTHS",IF(CK18>270,"10 MONTHS AND ABOVE",))))))) -> 10 MONTHS AND ABOVE | CP18: =IF(CQ18,"NTC ISSUED","FOR ISSUANCE") -> FOR ISSUANCE | CS18: =IF(AND(CQ18=0,CR18=0), "0",IF(CR18,(CR18-CQ18),TODAY()-CQ18)) -> 0 | CW18: '100338058856', | CX18: =VLOOKUP(E18,'[1]List of Work Orders'!$A:$I,9,FALSE) -> #N/A | DC18: =VLOOKUP(E18,'[2]List of Work Orders'!$A:$F,6,FALSE) -> #N/A | DS18: RONILO GANGE JR.
A19: 44391 | B19: OK | D19: BIZ | E19: X21062562359 | F19: NO BIA, INC. | G19: LANGKA, FTI CPD, TAGUIG CITY | H19: TAGUIG CITY | I19: PARAÑAQUE | J19: for cancellation, 1/11-transferred to other vendors, 2-22 same remarks | K19: W/ ISSUE | L19: VJC | M19: CAN | N19: Jemuel Peralta | O19: 98.17 | P19: #N/A | Q19: 0 | R19: TERMINATION | S19: 98826.44 | T19: 80129.87 | V19: =U19/T19 -> 0 | W19: 44384.444 | X19: 44390 | Y19: 44386 | AA19: CAN | AC19: =AA19-W19 -> #VALUE! | AD19: =AA19-X19 -> #VALUE! | AE19: =AB19-AA19 -> #VALUE! | AF19: =W19+AO19 -> #N/A | AG19: =W19+AN19 -> #N/A | AH19: =W19+50 -> 44434.444 | AI19: =(0.3)*(AC19/AK19)+(0.7)*(AC19/AL19) -> #VALUE! | AJ19: =AE19/AP19 -> #VALUE! | AK19: =IF(P19<51,20,(IF(P19<101,23,(IF(P19<201,26,IF(P19<301,28,IF(P19<401,30,(IF(P19<501,32,(IF(P19<1001,40,50))))))))))) -> #N/A | AL19: =IF(Q19<51,36,(IF(Q19<101,34,(IF(Q19<201,32,IF(Q19<301,30,IF(Q19<401,28,(IF(Q19<501,26,(IF(Q19<1001,23,20))))))))))) -> 36 | AM19: =(0.75)/((0.3/AK19)+(0.7/AL19)) -> #N/A | AN19: =(0.95)/((0.3/AK19)+(0.7/AL19)) -> #N/A | AO19: =AM19-3 -> #N/A | AP19: 60 | AQ19: =0.95*AP19 -> 57 | AR19: =AQ19-5 -> 52 | AS19: =AA19+AP19 -> #VALUE! | AT19: =IFERROR(TODAY()-AA19,"") | BE19: =AA19+15 -> #VALUE! | BF19: =IF(ISBLANK(AA19),0,IF(ISBLANK(BH19),(BE19-$L$1),(BH19-BE19))) -> #VALUE! | BQ19: Y | BZ19: B8-1847, 662411 | CA19: =IF(AY19="Y",BA19,"0") -> 0 | CB19: =AC19-CA19 -> #VALUE! | CC19: =BA19 -> 0 | CD19: =AC19-BA19 -> #VALUE! | CE19: =(0.3)*(CD19/AK19)+(0.7)*(CD19/AL19) -> #VALUE! | CF19: =IF(AA19="","0",$CF$1-AA19) -> #VALUE! | CH19: =(0.3)*(($CF$1-W19)/AK19)+(0.7)*(($CF$1-W19)/AL19) -> #N/A | CI19: =CH19-CG19 -> #N/A | CJ19: =CF19/AP19 -> #VALUE! | CK19: =IF(AA19>0,"",$CK$1-W19) | CL19: =IF(R19="NEW","REV","NON-REV") -> NON-REV | CM19: =IF(CK19="","",IF(CK19<91,"0-3 MONTHS",(IF(CK19<181,"4-6 MONTHS",(IF(CK19<271,"7-9 MONTHS",IF(CK19>270,"10 MONTHS AND ABOVE",))))))) | CP19: =IF(CQ19,"NTC ISSUED","FOR ISSUANCE") -> FOR ISSUANCE | CS19: =IF(AND(CQ19=0,CR19=0), "0",IF(CR19,(CR19-CQ19),TODAY()-CQ19)) -> 0 | CW19: 'X21062562359', | CX19: =VLOOKUP(E19,'[1]List of Work Orders'!$A:$I,9,FALSE) -> ME185130 | DC19: =VLOOKUP(E19,'[2]List of Work Orders'!$A:$F,6,FALSE) -> PCAN | DS19: JSP
B20: N/A | D20: MN | E20: 100338058959 | F20: MAINT - 414FIL - Retirement of Idle poles and other facilities pole DU1-2307 & DU1-2308 | G20: MALACCA LANE FILINVEST CORPORATE CITY ALABANG MUNTINLUPA | H20: MUNTINLUPA CITY | I20: PARAÑAQUE | J20: w/ pole attachments | K20: W/ ISSUE | L20: ECOM | M20: SCHED | N20: Ronilo Gange Jr. | O20: 21.7214 | P20: #N/A | Q20: 0 | R20: RETIREMENT OF IDLE FACILITES | S20: 22830.98 | T20: 22427.35 | V20: =U20/T20 -> 0 | W20: 44385.367 | X20: 44390.582 | Y20: 44473 | AC20: =AA20-W20 -> -44385.367 | AD20: =AA20-X20 -> -44390.582 | AE20: =AB20-AA20 -> 0 | AF20: =W20+AO20 -> #N/A | AG20: =W20+AN20 -> #N/A | AH20: =W20+50 -> 44435.367 | AI20: =(0.3)*(AC20/AK20)+(0.7)*(AC20/AL20) -> #N/A | AJ20: =AE20/AP20 -> 0 | AK20: =IF(P20<51,20,(IF(P20<101,23,(IF(P20<201,26,IF(P20<301,28,IF(P20<401,30,(IF(P20<501,32,(IF(P20<1001,40,50))))))))))) -> #N/A | AL20: =IF(Q20<51,36,(IF(Q20<101,34,(IF(Q20<201,32,IF(Q20<301,30,IF(Q20<401,28,(IF(Q20<501,26,(IF(Q20<1001,23,20))))))))))) -> 36 | AM20: =(0.75)/((0.3/AK20)+(0.7/AL20)) -> #N/A | AN20: =(0.95)/((0.3/AK20)+(0.7/AL20)) -> #N/A | AO20: =AM20-3 -> #N/A | AP20: 60 | AQ20: =0.95*AP20 -> 57 | AR20: =AQ20-5 -> 52 | AS20: =AA20+AP20 -> 60 | AT20: =IFERROR(TODAY()-AA20,"") -> 45895 | BE20: =AA20+15 -> 15 | BF20: =IF(ISBLANK(AA20),0,IF(ISBLANK(BH20),(BE20-$L$1),(BH20-BE20))) -> 0 | BQ20: N | CA20: =IF(AY20="Y",BA20,"0") -> 0 | CB20: =AC20-CA20 -> -44385.367 | CC20: =BA20 -> 0 | CD20: =AC20-BA20 -> -44385.367 | CE20: =(0.3)*(CD20/AK20)+(0.7)*(CD20/AL20) -> #N/A | CF20: =IF(AA20="","0",$CF$1-AA20) -> 0 | CH20: =(0.3)*(($CF$1-W20)/AK20)+(0.7)*(($CF$1-W20)/AL20) -> #N/A | CI20: =CH20-CG20 -> #N/A | CJ20: =CF20/AP20 -> 0 | CK20: =IF(AA20>0,"",$CK$1-W20) -> 1470.6326 | CL20: =IF(R20="NEW","REV","NON-REV") -> NON-REV | CM20: =IF(CK20="","",IF(CK20<91,"0-3 MONTHS",(IF(CK20<181,"4-6 MONTHS",(IF(CK20<271,"7-9 MONTHS",IF(CK20>270,"10 MONTHS AND ABOVE",))))))) -> 10 MONTHS AND ABOVE | CP20: =IF(CQ20,"NTC ISSUED","FOR ISSUANCE") -> FOR ISSUANCE | CS20: =IF(AND(CQ20=0,CR20=0), "0",IF(CR20,(CR20-CQ20),TODAY()-CQ20)) -> 0 | CW20: '100338058959', | CX20: =VLOOKUP(E20,'[1]List of Work Orders'!$A:$I,9,FALSE) -> #N/A | DC20: =VLOOKUP(E20,'[2]List of Work Orders'!$A:$F,6,FALSE) -> #N/A | DS20: RONILO GANGE JR.
B21: N/A | D21: MN | E21: 100338059056 | F21: MAINT - 414FIL - Retirement of Idle poles and other facilities pole DT1-2353 & DT1-2180 | G21: PARKWAY FILINVEST CORPORATE CITY ALABANG MUNTINLUPA | H21: MUNTINLUPA CITY | I21: PARAÑAQUE | J21: for permit on Feb. 22, 2023; no feed back; permit lapsed (03-08-23); | K21: W/O ISSUE | L21: ECOM | M21: SCHED | N21: Ronilo Gange Jr. | O21: 26.5574 | P21: #N/A | Q21: 0 | R21: RETIREMENT OF IDLE FACILITES | S21: 26074.07 | T21: 25670.44 | V21: =U21/T21 -> 0 | W21: 44404.538 | X21: 44406.377 | Y21: 44473 | AC21: =AA21-W21 -> -44404.538 | AD21: =AA21-X21 -> -44406.377 | AE21: =AB21-AA21 -> 0 | AF21: =W21+AO21 -> #N/A | AG21: =W21+AN21 -> #N/A | AH21: =W21+50 -> 44454.538 | AI21: =(0.3)*(AC21/AK21)+(0.7)*(AC21/AL21) -> #N/A | AJ21: =AE21/AP21 -> 0 | AK21: =IF(P21<51,20,(IF(P21<101,23,(IF(P21<201,26,IF(P21<301,28,IF(P21<401,30,(IF(P21<501,32,(IF(P21<1001,40,50))))))))))) -> #N/A | AL21: =IF(Q21<51,36,(IF(Q21<101,34,(IF(Q21<201,32,IF(Q21<301,30,IF(Q21<401,28,(IF(Q21<501,26,(IF(Q21<1001,23,20))))))))))) -> 36 | AM21: =(0.75)/((0.3/AK21)+(0.7/AL21)) -> #N/A | AN21: =(0.95)/((0.3/AK21)+(0.7/AL21)) -> #N/A | AO21: =AM21-3 -> #N/A | AP21: 60 | AQ21: =0.95*AP21 -> 57 | AR21: =AQ21-5 -> 52 | AS21: =AA21+AP21 -> 60 | AT21: =IFERROR(TODAY()-AA21,"") -> 45895 | BE21: =AA21+15 -> 15 | BF21: =IF(ISBLANK(AA21),0,IF(ISBLANK(BH21),(BE21-$L$1),(BH21-BE21))) -> 0 | BQ21: N | BX21: JDZ | CA21: =IF(AY21="Y",BA21,"0") -> 0 | CB21: =AC21-CA21 -> -44404.538 | CC21: =BA21 -> 0 | CD21: =AC21-BA21 -> -44404.538 | CE21: =(0.3)*(CD21/AK21)+(0.7)*(CD21/AL21) -> #N/A | CF21: =IF(AA21="","0",$CF$1-AA21) -> 0 | CH21: =(0.3)*(($CF$1-W21)/AK21)+(0.7)*(($CF$1-W21)/AL21) -> #N/A | CI21: =CH21-CG21 -> #N/A | CJ21: =CF21/AP21 -> 0 | CK21: =IF(AA21>0,"",$CK$1-W21) -> 1451.4618 | CL21: =IF(R21="NEW","REV","NON-REV") -> NON-REV | CM21: =IF(CK21="","",IF(CK21<91,"0-3 MONTHS",(IF(CK21<181,"4-6 MONTHS",(IF(CK21<271,"7-9 MONTHS",IF(CK21>270,"10 MONTHS AND ABOVE",))))))) -> 10 MONTHS AND ABOVE | CP21: =IF(CQ21,"NTC ISSUED","FOR ISSUANCE") -> FOR ISSUANCE | CS21: =IF(AND(CQ21=0,CR21=0), "0",IF(CR21,(CR21-CQ21),TODAY()-CQ21)) -> 0 | CW21: '100338059056', | CX21: =VLOOKUP(E21,'[1]List of Work Orders'!$A:$I,9,FALSE) -> #N/A | DC21: =VLOOKUP(E21,'[2]List of Work Orders'!$A:$F,6,FALSE) -> #N/A | DS21: RONILO GANGE JR.
B22: N/A | D22: MN | E22: 100338058517 | F22: MAINT - 414FIL - Retirement of Idle poles & facilities P# DU1-2173,DU1-2282,DU1-2172,NPT | G22: MANDARIN PLEASANT VILL BAYANAN MUNTINLUPA | H22: MUNTINLUPA CITY | I22: PARAÑAQUE | J22: w/ pole attachments | K22: W/ ISSUE | L22: ECOM | M22: SCHED | N22: Ronilo Gange Jr. | O22: 44.54 | P22: #N/A | Q22: 0 | R22: RETIREMENT OF IDLE FACILITES | S22: 41109.69 | T22: 40614.53 | V22: =U22/T22 -> 0 | W22: 44414 | X22: 44417.42 | Y22: 44473 | AC22: =AA22-W22 -> -44414 | AD22: =AA22-X22 -> -44417.42 | AE22: =AB22-AA22 -> 0 | AF22: =W22+AO22 -> #N/A | AG22: =W22+AN22 -> #N/A | AH22: =W22+50 -> 44464 | AI22: =(0.3)*(AC22/AK22)+(0.7)*(AC22/AL22) -> #N/A | AJ22: =AE22/AP22 -> 0 | AK22: =IF(P22<51,20,(IF(P22<101,23,(IF(P22<201,26,IF(P22<301,28,IF(P22<401,30,(IF(P22<501,32,(IF(P22<1001,40,50))))))))))) -> #N/A | AL22: =IF(Q22<51,36,(IF(Q22<101,34,(IF(Q22<201,32,IF(Q22<301,30,IF(Q22<401,28,(IF(Q22<501,26,(IF(Q22<1001,23,20))))))))))) -> 36 | AM22: =(0.75)/((0.3/AK22)+(0.7/AL22)) -> #N/A | AN22: =(0.95)/((0.3/AK22)+(0.7/AL22)) -> #N/A | AO22: =AM22-3 -> #N/A | AP22: 60 | AQ22: =0.95*AP22 -> 57 | AR22: =AQ22-5 -> 52 | AS22: =AA22+AP22 -> 60 | AT22: =IFERROR(TODAY()-AA22,"") -> 45895 | BE22: =AA22+15 -> 15 | BF22: =IF(ISBLANK(AA22),0,IF(ISBLANK(BH22),(BE22-$L$1),(BH22-BE22))) -> 0 | BQ22: N | CA22: =IF(AY22="Y",BA22,"0") -> 0 | CB22: =AC22-CA22 -> -44414 | CC22: =BA22 -> 0 | CD22: =AC22-BA22 -> -44414 | CE22: =(0.3)*(CD22/AK22)+(0.7)*(CD22/AL22) -> #N/A | CF22: =IF(AA22="","0",$CF$1-AA22) -> 0 | CH22: =(0.3)*(($CF$1-W22)/AK22)+(0.7)*(($CF$1-W22)/AL22) -> #N/A | CI22: =CH22-CG22 -> #N/A | CJ22: =CF22/AP22 -> 0 | CK22: =IF(AA22>0,"",$CK$1-W22) -> 1442 | CL22: =IF(R22="NEW","REV","NON-REV") -> NON-REV | CM22: =IF(CK22="","",IF(CK22<91,"0-3 MONTHS",(IF(CK22<181,"4-6 MONTHS",(IF(CK22<271,"7-9 MONTHS",IF(CK22>270,"10 MONTHS AND ABOVE",))))))) -> 10 MONTHS AND ABOVE | CP22: =IF(CQ22,"NTC ISSUED","FOR ISSUANCE") -> FOR ISSUANCE | CS22: =IF(AND(CQ22=0,CR22=0), "0",IF(CR22,(CR22-CQ22),TODAY()-CQ22)) -> 0 | CW22: '100338058517', | CX22: =VLOOKUP(E22,'[1]List of Work Orders'!$A:$I,9,FALSE) -> #N/A | DC22: =VLOOKUP(E22,'[2]List of Work Orders'!$A:$F,6,FALSE) -> #N/A | DS22: RONILO GANGE JR.
B23: N/A | D23: MN | E23: 100338058622 | F23: MAINT - 414FIL - Retirement of Idle poles and other facilities pole DU1-0002-T & DU1-2172-B | G23: MANDARIN PLEASANT VILL BAYANAN MUNTINLUPA | H23: MUNTINLUPA CITY | I23: PARAÑAQUE | J23: w/ pole attachments | K23: W/ ISSUE | L23: ECOM | M23: SCHED | N23: Ronilo Gange Jr. | O23: 11.9873 | P23: #N/A | Q23: 0 | R23: RETIREMENT OF IDLE FACILITES | S23: 24337.19 | T23: 23777.68 | V23: =U23/T23 -> 0 | W23: 44414.66 | X23: 44417.421 | Y23: 44473 | AC23: =AA23-W23 -> -44414.66 | AD23: =AA23-X23 -> -44417.421 | AE23: =AB23-AA23 -> 0 | AF23: =W23+AO23 -> #N/A | AG23: =W23+AN23 -> #N/A | AH23: =W23+50 -> 44464.66 | AI23: =(0.3)*(AC23/AK23)+(0.7)*(AC23/AL23) -> #N/A | AJ23: =AE23/AP23 -> 0 | AK23: =IF(P23<51,20,(IF(P23<101,23,(IF(P23<201,26,IF(P23<301,28,IF(P23<401,30,(IF(P23<501,32,(IF(P23<1001,40,50))))))))))) -> #N/A | AL23: =IF(Q23<51,36,(IF(Q23<101,34,(IF(Q23<201,32,IF(Q23<301,30,IF(Q23<401,28,(IF(Q23<501,26,(IF(Q23<1001,23,20))))))))))) -> 36 | AM23: =(0.75)/((0.3/AK23)+(0.7/AL23)) -> #N/A | AN23: =(0.95)/((0.3/AK23)+(0.7/AL23)) -> #N/A | AO23: =AM23-3 -> #N/A | AP23: 60 | AQ23: =0.95*AP23 -> 57 | AR23: =AQ23-5 -> 52 | AS23: =AA23+AP23 -> 60 | AT23: =IFERROR(TODAY()-AA23,"") -> 45895 | BE23: =AA23+15 -> 15 | BF23: =IF(ISBLANK(AA23),0,IF(ISBLANK(BH23),(BE23-$L$1),(BH23-BE23))) -> 0 | BQ23: N | CA23: =IF(AY23="Y",BA23,"0") -> 0 | CB23: =AC23-CA23 -> -44414.66 | CC23: =BA23 -> 0 | CD23: =AC23-BA23 -> -44414.66 | CE23: =(0.3)*(CD23/AK23)+(0.7)*(CD23/AL23) -> #N/A | CF23: =IF(AA23="","0",$CF$1-AA23) -> 0 | CH23: =(0.3)*(($CF$1-W23)/AK23)+(0.7)*(($CF$1-W23)/AL23) -> #N/A | CI23: =CH23-CG23 -> #N/A | CJ23: =CF23/AP23 -> 0 | CK23: =IF(AA23>0,"",$CK$1-W23) -> 1441.3396 | CL23: =IF(R23="NEW","REV","NON-REV") -> NON-REV | CM23: =IF(CK23="","",IF(CK23<91,"0-3 MONTHS",(IF(CK23<181,"4-6 MONTHS",(IF(CK23<271,"7-9 MONTHS",IF(CK23>270,"10 MONTHS AND ABOVE",))))))) -> 10 MONTHS AND ABOVE | CP23: =IF(CQ23,"NTC ISSUED","FOR ISSUANCE") -> FOR ISSUANCE | CS23: =IF(AND(CQ23=0,CR23=0), "0",IF(CR23,(CR23-CQ23),TODAY()-CQ23)) -> 0 | CW23: '100338058622', | CX23: =VLOOKUP(E23,'[1]List of Work Orders'!$A:$I,9,FALSE) -> #N/A | DC23: =VLOOKUP(E23,'[2]List of Work Orders'!$A:$F,6,FALSE) -> #N/A | DS23: RONILO GANGE JR.
A24: 44442 | B24: N/A | D24: MN | E24: P2106111928 | F24: MAINT 43XD Loadsplit [037150|WA196961|CX7-0436||] Install 1-50kVA DT on pole CX7-0434 | G24: KASOY DO?A MANUELA SUBD PH 4-A PAMPLONA III LAS PINAS CITY | H24: LAS PIÑAS CITY | I24: PARAÑAQUE | J24: for confirmation; crew survey of C1 | K24: W/O ISSUE | L24: ECOM | M24: SCHED | N24: Ronilo Gange Jr. | O24: 48.4981 | P24: #N/A | Q24: 0 | R24: OLDT | S24: 193888.88 | T24: 42701.27 | V24: =U24/T24 -> 0 | W24: 44418.663 | X24: 44421.539 | Y24: 44422 | AC24: =AA24-W24 -> -44418.663 | AD24: =AA24-X24 -> -44421.539 | AE24: =AB24-AA24 -> 0 | AF24: =W24+AO24 -> #N/A | AG24: =W24+AN24 -> #N/A | AH24: =W24+50 -> 44468.663 | AI24: =(0.3)*(AC24/AK24)+(0.7)*(AC24/AL24) -> #N/A | AJ24: =AE24/AP24 -> 0 | AK24: =IF(P24<51,20,(IF(P24<101,23,(IF(P24<201,26,IF(P24<301,28,IF(P24<401,30,(IF(P24<501,32,(IF(P24<1001,40,50))))))))))) -> #N/A | AL24: =IF(Q24<51,36,(IF(Q24<101,34,(IF(Q24<201,32,IF(Q24<301,30,IF(Q24<401,28,(IF(Q24<501,26,(IF(Q24<1001,23,20))))))))))) -> 36 | AM24: =(0.75)/((0.3/AK24)+(0.7/AL24)) -> #N/A | AN24: =(0.95)/((0.3/AK24)+(0.7/AL24)) -> #N/A | AO24: =AM24-3 -> #N/A | AP24: 60 | AQ24: =0.95*AP24 -> 57 | AR24: =AQ24-5 -> 52 | AS24: =AA24+AP24 -> 60 | AT24: =IFERROR(TODAY()-AA24,"") -> 45895 | BE24: =AA24+15 -> 15 | BF24: =IF(ISBLANK(AA24),0,IF(ISBLANK(BH24),(BE24-$L$1),(BH24-BE24))) -> 0 | BQ24: N | BS24: Load-splitting | BT24: TLN 037150 | BU24: Y | BV24: Scheduled | BW24: Transferred from Alvin to Jimmy | CA24: =IF(AY24="Y",BA24,"0") -> 0 | CB24: =AC24-CA24 -> -44418.663 | CC24: =BA24 -> 0 | CD24: =AC24-BA24 -> -44418.663 | CE24: =(0.3)*(CD24/AK24)+(0.7)*(CD24/AL24) -> #N/A | CF24: =IF(AA24="","0",$CF$1-AA24) -> 0 | CH24: =(0.3)*(($CF$1-W24)/AK24)+(0.7)*(($CF$1-W24)/AL24) -> #N/A | CI24: =CH24-CG24 -> #N/A | CJ24: =CF24/AP24 -> 0 | CK24: =IF(AA24>0,"",$CK$1-W24) -> 1437.3368 | CL24: =IF(R24="NEW","REV","NON-REV") -> NON-REV | CM24: =IF(CK24="","",IF(CK24<91,"0-3 MONTHS",(IF(CK24<181,"4-6 MONTHS",(IF(CK24<271,"7-9 MONTHS",IF(CK24>270,"10 MONTHS AND ABOVE",))))))) -> 10 MONTHS AND ABOVE | CP24: =IF(CQ24,"NTC ISSUED","FOR ISSUANCE") -> FOR ISSUANCE | CS24: =IF(AND(CQ24=0,CR24=0), "0",IF(CR24,(CR24-CQ24),TODAY()-CQ24)) -> 0 | CW24: 'P2106111928', | CX24: =VLOOKUP(E24,'[1]List of Work Orders'!$A:$I,9,FALSE) -> ME155242 | DC24: =VLOOKUP(E24,'[2]List of Work Orders'!$A:$F,6,FALSE) -> SCHED | DS24: RONILO GANGE JR.
A25: 44453 | B25: N/A | D25: MN | E25: P2007000361 | F25: MAINT Load-Split 086298/WA350686/100KVA; Inst Addl 1-75kVA DT on pole B8-6252 (new pole) | G25: DIRECTO ZONE 2 SIGNAL VILLAGE TAGUIG CITY | H25: TAGUIG CITY | I25: PARAÑAQUE | J25: for survey with QI, refer to design | K25: W/ ISSUE | L25: OPS | M25: FCOMP | N25: Dean Carl Borjal | O25: 0 | P25: 9.77 | Q25: 0 | R25: OLDT | S25: 195433.93 | T25: 25772.59 | V25: =U25/T25 -> 0 | W25: 44437.967 | X25: 44441.438 | Y25: 44454 | AA25: 45735 | AC25: =AA25-W25 -> 1297.0333 | AD25: =AA25-X25 -> 1293.5625 | AE25: =AB25-AA25 -> -45735 | AF25: =W25+AO25 -> 44456.741 | AG25: =W25+AN25 -> 44465.547 | AH25: =W25+50 -> 44487.967 | AI25: =(0.3)*(AC25/AK25)+(0.7)*(AC25/AL25) -> 44.675593 | AJ25: =AE25/AP25 -> -762.25 | AK25: =IF(P25<51,20,(IF(P25<101,23,(IF(P25<201,26,IF(P25<301,28,IF(P25<401,30,(IF(P25<501,32,(IF(P25<1001,40,50))))))))))) -> 20 | AL25: =IF(Q25<51,36,(IF(Q25<101,34,(IF(Q25<201,32,IF(Q25<301,30,IF(Q25<401,28,(IF(Q25<501,26,(IF(Q25<1001,23,20))))))))))) -> 36 | AM25: =(0.75)/((0.3/AK25)+(0.7/AL25)) -> 21.774194 | AN25: =(0.95)/((0.3/AK25)+(0.7/AL25)) -> 27.580645 | AO25: =AM25-3 -> 18.774194 | AP25: 60 | AQ25: =0.95*AP25 -> 57 | AR25: =AQ25-5 -> 52 | AS25: =AA25+AP25 -> 45795 | AT25: =IFERROR(TODAY()-AA25,"") -> 160 | BC25: NO COC | BE25: =AA25+15 -> 45750 | BF25: =IF(ISBLANK(AA25),0,IF(ISBLANK(BH25),(BE25-$L$1),(BH25-BE25))) -> #VALUE! | BQ25: N | BS25: Load-splitting | BT25: TLN 086298 | BU25: Y | BV25: Scheduled | BW25: Transferred from Alvin to Jimmy / With Installation of new pole | CA25: =IF(AY25="Y",BA25,"0") -> 0 | CB25: =AC25-CA25 -> 1297.0333 | CC25: =BA25 -> 0 | CD25: =AC25-BA25 -> 1297.0333 | CE25: =(0.3)*(CD25/AK25)+(0.7)*(CD25/AL25) -> 44.675593 | CF25: =IF(AA25="","0",$CF$1-AA25) -> 134 | CH25: =(0.3)*(($CF$1-W25)/AK25)+(0.7)*(($CF$1-W25)/AL25) -> 49.291148 | CI25: =CH25-CG25 -> 49.291148 | CJ25: =CF25/AP25 -> 2.2333333 | CK25: =IF(AA25>0,"",$CK$1-W25) | CL25: =IF(R25="NEW","REV","NON-REV") -> NON-REV | CM25: =IF(CK25="","",IF(CK25<91,"0-3 MONTHS",(IF(CK25<181,"4-6 MONTHS",(IF(CK25<271,"7-9 MONTHS",IF(CK25>270,"10 MONTHS AND ABOVE",))))))) | CP25: =IF(CQ25,"NTC ISSUED","FOR ISSUANCE") -> FOR ISSUANCE | CS25: =IF(AND(CQ25=0,CR25=0), "0",IF(CR25,(CR25-CQ25),TODAY()-CQ25)) -> 0 | CW25: 'P2007000361', | CX25: =VLOOKUP(E25,'[1]List of Work Orders'!$A:$I,9,FALSE) -> ME168443 | DC25: =VLOOKUP(E25,'[2]List of Work Orders'!$A:$F,6,FALSE) -> FCOMP | DS25: DCB
A26: 44476 | B26: 44469 | D26: HMB | E26: R20784640 | F26: ALLANIQUE REALTY DEVT CORP | G26: L. ALLANIQUE, BARANGAY VILL, PARANAQUE | H26: PARAÑAQUE CITY | I26: PARAÑAQUE | J26: customer refuse on location of pole digging 5/20/2025 for BC coordiantion on WO cancellation 2/15 re-surveyed 07/17/2024 to install pole in-front of existing and use small aleyarm as support | K26: (R) W/O ISSUE | L26: CHALLENGER | M26: SCHED | N26: Isan Carlo Lazaro | O26: 85.05 | P26: 23.26 | Q26: 0 | R26: RELOC | S26: 94979.94 | T26: 33678.6 | V26: =U26/T26 -> 0 | W26: 44463.628 | X26: 44469 | Y26: 44469 | AC26: =AA26-W26 -> -44463.628 | AD26: =AA26-X26 -> -44469 | AE26: =AB26-AA26 -> 0 | AF26: =W26+AO26 -> 44482.402 | AG26: =W26+AN26 -> 44491.208 | AH26: =W26+50 -> 44513.628 | AI26: =(0.3)*(AC26/AK26)+(0.7)*(AC26/AL26) -> -1531.525 | AJ26: =AE26/AP26 -> 0 | AK26: =IF(P26<51,20,(IF(P26<101,23,(IF(P26<201,26,IF(P26<301,28,IF(P26<401,30,(IF(P26<501,32,(IF(P26<1001,40,50))))))))))) -> 20 | AL26: =IF(Q26<51,36,(IF(Q26<101,34,(IF(Q26<201,32,IF(Q26<301,30,IF(Q26<401,28,(IF(Q26<501,26,(IF(Q26<1001,23,20))))))))))) -> 36 | AM26: =(0.75)/((0.3/AK26)+(0.7/AL26)) -> 21.774194 | AN26: =(0.95)/((0.3/AK26)+(0.7/AL26)) -> 27.580645 | AO26: =AM26-3 -> 18.774194 | AP26: 60 | AQ26: =0.95*AP26 -> 57 | AR26: =AQ26-5 -> 52 | AS26: =AA26+AP26 -> 60 | AT26: =IFERROR(TODAY()-AA26,"") -> 45895 | BE26: =AA26+15 -> 15 | BF26: =IF(ISBLANK(AA26),0,IF(ISBLANK(BH26),(BE26-$L$1),(BH26-BE26))) -> 0 | BQ26: N | BZ26: CY9-0440, CY9-5932 | CA26: =IF(AY26="Y",BA26,"0") -> 0 | CB26: =AC26-CA26 -> -44463.628 | CC26: =BA26 -> 0 | CD26: =AC26-BA26 -> -44463.628 | CE26: =(0.3)*(CD26/AK26)+(0.7)*(CD26/AL26) -> -1531.525 | CF26: =IF(AA26="","0",$CF$1-AA26) -> 0 | CH26: =(0.3)*(($CF$1-W26)/AK26)+(0.7)*(($CF$1-W26)/AL26) -> 48.407265 | CI26: =CH26-CG26 -> 48.407265 | CJ26: =CF26/AP26 -> 0 | CK26: =IF(AA26>0,"",$CK$1-W26) -> 1392.3722 | CL26: =IF(R26="NEW","REV","NON-REV") -> NON-REV | CM26: =IF(CK26="","",IF(CK26<91,"0-3 MONTHS",(IF(CK26<181,"4-6 MONTHS",(IF(CK26<271,"7-9 MONTHS",IF(CK26>270,"10 MONTHS AND ABOVE",))))))) -> 10 MONTHS AND ABOVE | CP26: =IF(CQ26,"NTC ISSUED","FOR ISSUANCE") -> FOR ISSUANCE | CS26: =IF(AND(CQ26=0,CR26=0), "0",IF(CR26,(CR26-CQ26),TODAY()-CQ26)) -> 0 | CW26: 'R20784640', | CX26: =VLOOKUP(E26,'[1]List of Work Orders'!$A:$I,9,FALSE) -> ME166067 | DC26: =VLOOKUP(E26,'[2]List of Work Orders'!$A:$F,6,FALSE) -> SCHED | DS26: Isan Carlo Lazaro
A27: 44490 | B27: 44491 | C27: Y | D27: REL | E27: R19617176 | F27: OFFICE OF CONGRESSMAN STRIKE B. REVILLA, | G27: GEN. EMILIO AGUINALDO, PANAPAAN VI, BACOOR | H27: BACOOR CITY | I27: DASMA | J27: Job 3 for SSP/liveline, Job 4 with telco for email to FA, Job 5 for survey live line, Task 10 with issue on hukay, request assistance bacoor, job 7 for PAI sched; | K27: W/ ISSUE | L27: AVECO | M27: SCHED | N27: Ronilo Gange Jr. | O27: 1133.2284 | P27: 1795.22 | Q27: 0 | R27: RELOC | S27: 1921072.2 | T27: 821316.27 | V27: =U27/T27 -> 0 | W27: 44475.812 | X27: 44481 | Y27: 44482 | AC27: =AA27-W27 -> -44475.812 | AD27: =AA27-X27 -> -44481 | AE27: =AB27-AA27 -> 0 | AF27: =W27+AO27 -> 44502.288 | AG27: =W27+AN27 -> 44513.148 | AH27: =W27+50 -> 44525.812 | AI27: =(0.3)*(AC27/AK27)+(0.7)*(AC27/AL27) -> -1131.6623 | AJ27: =AE27/AP27 -> 0 | AK27: =IF(P27<51,20,(IF(P27<101,23,(IF(P27<201,26,IF(P27<301,28,IF(P27<401,30,(IF(P27<501,32,(IF(P27<1001,40,50))))))))))) -> 50 | AL27: =IF(Q27<51,36,(IF(Q27<101,34,(IF(Q27<201,32,IF(Q27<301,30,IF(Q27<401,28,(IF(Q27<501,26,(IF(Q27<1001,23,20))))))))))) -> 36 | AM27: =(0.75)/((0.3/AK27)+(0.7/AL27)) -> 29.475983 | AN27: =(0.95)/((0.3/AK27)+(0.7/AL27)) -> 37.336245 | AO27: =AM27-3 -> 26.475983 | AP27: 60 | AQ27: =0.95*AP27 -> 57 | AR27: =AQ27-5 -> 52 | AS27: =AA27+AP27 -> 60 | AT27: =IFERROR(TODAY()-AA27,"") -> 45895 | BE27: =AA27+15 -> 15 | BF27: =IF(ISBLANK(AA27),0,IF(ISBLANK(BH27),(BE27-$L$1),(BH27-BE27))) -> 0 | BQ27: N | CA27: =IF(AY27="Y",BA27,"0") -> 0 | CB27: =AC27-CA27 -> -44475.812 | CC27: =BA27 -> 0 | CD27: =AC27-BA27 -> -44475.812 | CE27: =(0.3)*(CD27/AK27)+(0.7)*(CD27/AL27) -> -1131.6623 | CF27: =IF(AA27="","0",$CF$1-AA27) -> 0 | CH27: =(0.3)*(($CF$1-W27)/AK27)+(0.7)*(($CF$1-W27)/AL27) -> 35.4489 | CI27: =CH27-CG27 -> 35.4489 | CJ27: =CF27/AP27 -> 0 | CK27: =IF(AA27>0,"",$CK$1-W27) -> 1380.1882 | CL27: =IF(R27="NEW","REV","NON-REV") -> NON-REV | CM27: =IF(CK27="","",IF(CK27<91,"0-3 MONTHS",(IF(CK27<181,"4-6 MONTHS",(IF(CK27<271,"7-9 MONTHS",IF(CK27>270,"10 MONTHS AND ABOVE",))))))) -> 10 MONTHS AND ABOVE | CP27: =IF(CQ27,"NTC ISSUED","FOR ISSUANCE") -> FOR ISSUANCE | CS27: =IF(AND(CQ27=0,CR27=0), "0",IF(CR27,(CR27-CQ27),TODAY()-CQ27)) -> 0 | CW27: 'R19617176', | CX27: =VLOOKUP(E27,'[1]List of Work Orders'!$A:$I,9,FALSE) -> ME155242 | DC27: =VLOOKUP(E27,'[2]List of Work Orders'!$A:$F,6,FALSE) -> SCHED | DS27: RONILO GANGE JR.
A28: 44490 | B28: 44489 | D28: BIZ | E28: X21083519494 | F28: SEVEN TALL TREES EVENTS, INC. | G28: ASEANA, ASEANA BUSINESS PARK, PARANAQUE | H28: PARAÑAQUE CITY | I28: PARAÑAQUE | J28: for permit re application 2/15 | K28: W/ ISSUE | L28: CHALLENGER | M28: CAN | N28: Jemuel Peralta | O28: 97.66 | P28: #N/A | Q28: 0 | R28: TERMINATION | S28: 87040.66 | T28: 73733.14 | V28: =U28/T28 -> 0 | W28: 44482.69 | X28: 44484 | Y28: 44489 | AA28: CAN | AC28: =AA28-W28 -> #VALUE! | AD28: =AA28-X28 -> #VALUE! | AE28: =AB28-AA28 -> #VALUE! | AF28: =W28+AO28 -> #N/A | AG28: =W28+AN28 -> #N/A | AH28: =W28+50 -> 44532.69 | AI28: =(0.3)*(AC28/AK28)+(0.7)*(AC28/AL28) -> #VALUE! | AJ28: =AE28/AP28 -> #VALUE! | AK28: =IF(P28<51,20,(IF(P28<101,23,(IF(P28<201,26,IF(P28<301,28,IF(P28<401,30,(IF(P28<501,32,(IF(P28<1001,40,50))))))))))) -> #N/A | AL28: =IF(Q28<51,36,(IF(Q28<101,34,(IF(Q28<201,32,IF(Q28<301,30,IF(Q28<401,28,(IF(Q28<501,26,(IF(Q28<1001,23,20))))))))))) -> 36 | AM28: =(0.75)/((0.3/AK28)+(0.7/AL28)) -> #N/A | AN28: =(0.95)/((0.3/AK28)+(0.7/AL28)) -> #N/A | AO28: =AM28-3 -> #N/A | AP28: 60 | AQ28: =0.95*AP28 -> 57 | AR28: =AQ28-5 -> 52 | AS28: =AA28+AP28 -> #VALUE! | AT28: =IFERROR(TODAY()-AA28,"") | BE28: =AA28+15 -> #VALUE! | BF28: =IF(ISBLANK(AA28),0,IF(ISBLANK(BH28),(BE28-$L$1),(BH28-BE28))) -> #VALUE! | BQ28: Y | BZ28: C4-5094, 126264 | CA28: =IF(AY28="Y",BA28,"0") -> 0 | CB28: =AC28-CA28 -> #VALUE! | CC28: =BA28 -> 0 | CD28: =AC28-BA28 -> #VALUE! | CE28: =(0.3)*(CD28/AK28)+(0.7)*(CD28/AL28) -> #VALUE! | CF28: =IF(AA28="","0",$CF$1-AA28) -> #VALUE! | CH28: =(0.3)*(($CF$1-W28)/AK28)+(0.7)*(($CF$1-W28)/AL28) -> #N/A | CI28: =CH28-CG28 -> #N/A | CJ28: =CF28/AP28 -> #VALUE! | CK28: =IF(AA28>0,"",$CK$1-W28) | CL28: =IF(R28="NEW","REV","NON-REV") -> NON-REV | CM28: =IF(CK28="","",IF(CK28<91,"0-3 MONTHS",(IF(CK28<181,"4-6 MONTHS",(IF(CK28<271,"7-9 MONTHS",IF(CK28>270,"10 MONTHS AND ABOVE",))))))) | CP28: =IF(CQ28,"NTC ISSUED","FOR ISSUANCE") -> FOR ISSUANCE | CS28: =IF(AND(CQ28=0,CR28=0), "0",IF(CR28,(CR28-CQ28),TODAY()-CQ28)) -> 0 | CW28: 'X21083519494', | CX28: =VLOOKUP(E28,'[1]List of Work Orders'!$A:$I,9,FALSE) -> ME185130 | DC28: =VLOOKUP(E28,'[2]List of Work Orders'!$A:$F,6,FALSE) -> PCAN | DS28: JSP
A29: 45058 | B29: N/A | D29: MN | E29: P2106111943 | F29: MAINT 45XD Loadsplit [035879|WA141444|CX8-0551||] install 1-75kVA DT on pole CX8-0552 | G29: KYOTO BF HOMES BF HOMES PARANAQUE | H29: PARAÑAQUE CITY | I29: PARAÑAQUE | J29: ongoing | L29: POWERHOUSE | M29: INPRG | N29: Jenneth Madrid | O29: 53.3183 | P29: #N/A | Q29: 0 | R29: OLDT | S29: 224779.02 | T29: 49304.03 | V29: =U29/T29 -> 0 | W29: 44484.358 | X29: 44484.522 | Y29: 44967 | AC29: =AA29-W29 -> -44484.358 | AD29: =AA29-X29 -> -44484.522 | AE29: =AB29-AA29 -> 0 | AF29: =W29+AO29 -> #N/A | AG29: =W29+AN29 -> #N/A | AH29: =W29+50 -> 44534.358 | AI29: =(0.3)*(AC29/AK29)+(0.7)*(AC29/AL29) -> #N/A | AJ29: =AE29/AP29 -> 0 | AK29: =IF(P29<51,20,(IF(P29<101,23,(IF(P29<201,26,IF(P29<301,28,IF(P29<401,30,(IF(P29<501,32,(IF(P29<1001,40,50))))))))))) -> #N/A | AL29: =IF(Q29<51,36,(IF(Q29<101,34,(IF(Q29<201,32,IF(Q29<301,30,IF(Q29<401,28,(IF(Q29<501,26,(IF(Q29<1001,23,20))))))))))) -> 36 | AM29: =(0.75)/((0.3/AK29)+(0.7/AL29)) -> #N/A | AN29: =(0.95)/((0.3/AK29)+(0.7/AL29)) -> #N/A | AO29: =AM29-3 -> #N/A | AP29: 60 | AQ29: =0.95*AP29 -> 57 | AR29: =AQ29-5 -> 52 | AS29: =AA29+AP29 -> 60 | AT29: =IFERROR(TODAY()-AA29,"") -> 45895 | BE29: =AA29+15 -> 15 | BF29: =IF(ISBLANK(AA29),0,IF(ISBLANK(BH29),(BE29-$L$1),(BH29-BE29))) -> 0 | BS29: Load-splitting | BT29: TLN 035879 | BU29: Y | BV29: Scheduled | BW29: Transferred from Alvin to Jimmy Issued and returned as surplus, for re-sched by MECO crew but re-assign to C1 and assign to powerhouse | CA29: =IF(AY29="Y",BA29,"0") -> 0 | CB29: =AC29-CA29 -> -44484.358 | CC29: =BA29 -> 0 | CD29: =AC29-BA29 -> -44484.358 | CE29: =(0.3)*(CD29/AK29)+(0.7)*(CD29/AL29) -> #N/A | CF29: =IF(AA29="","0",$CF$1-AA29) -> 0 | CH29: =(0.3)*(($CF$1-W29)/AK29)+(0.7)*(($CF$1-W29)/AL29) -> #N/A | CI29: =CH29-CG29 -> #N/A | CJ29: =CF29/AP29 -> 0 | CK29: =IF(AA29>0,"",$CK$1-W29) -> 1371.6417 | CL29: =IF(R29="NEW","REV","NON-REV") -> NON-REV | CM29: =IF(CK29="","",IF(CK29<91,"0-3 MONTHS",(IF(CK29<181,"4-6 MONTHS",(IF(CK29<271,"7-9 MONTHS",IF(CK29>270,"10 MONTHS AND ABOVE",))))))) -> 10 MONTHS AND ABOVE | CP29: =IF(CQ29,"NTC ISSUED","FOR ISSUANCE") -> FOR ISSUANCE | CS29: =IF(AND(CQ29=0,CR29=0), "0",IF(CR29,(CR29-CQ29),TODAY()-CQ29)) -> 0 | CW29: 'P2106111943', | CX29: =VLOOKUP(E29,'[1]List of Work Orders'!$A:$I,9,FALSE) -> ME185284 | DC29: =VLOOKUP(E29,'[2]List of Work Orders'!$A:$F,6,FALSE) -> INPRG | DS29: Jenneth Madrid
A30: 44518 | B30: 44499 | D30: CBG | E30: X21094255140 | F30: BAYPRIME PROPERTIES INC. | G30: ASEANA, ASEANA BUSINESS PARK, PARANAQUE | H30: PARAÑAQUE CITY | I30: PARAÑAQUE | J30: for WO cancellation? DT still in used | K30: FOR CANCELLATION | L30: CHALLENGER | M30: CLOSED-CAN | N30: Isan Carlo Lazaro | O30: 118.9334 | P30: #N/A | Q30: 0 | R30: TERMINATION | S30: 139589.22 | T30: 107671.04 | V30: =U30/T30 -> 0 | W30: 44496.597 | X30: 44498.635 | Y30: 44499 | AA30: CLOSED-CAN | AC30: =AA30-W30 -> #VALUE! | AD30: =AA30-X30 -> #VALUE! | AE30: =AB30-AA30 -> #VALUE! | AF30: =W30+AO30 -> #N/A | AG30: =W30+AN30 -> #N/A | AH30: =W30+50 -> 44546.597 | AI30: =(0.3)*(AC30/AK30)+(0.7)*(AC30/AL30) -> #VALUE! | AJ30: =AE30/AP30 -> #VALUE! | AK30: =IF(P30<51,20,(IF(P30<101,23,(IF(P30<201,26,IF(P30<301,28,IF(P30<401,30,(IF(P30<501,32,(IF(P30<1001,40,50))))))))))) -> #N/A | AL30: =IF(Q30<51,36,(IF(Q30<101,34,(IF(Q30<201,32,IF(Q30<301,30,IF(Q30<401,28,(IF(Q30<501,26,(IF(Q30<1001,23,20))))))))))) -> 36 | AM30: =(0.75)/((0.3/AK30)+(0.7/AL30)) -> #N/A | AN30: =(0.95)/((0.3/AK30)+(0.7/AL30)) -> #N/A | AO30: =AM30-3 -> #N/A | AP30: 60 | AQ30: =0.95*AP30 -> 57 | AR30: =AQ30-5 -> 52 | AS30: =AA30+AP30 -> #VALUE! | AT30: =IFERROR(TODAY()-AA30,"") | BC30: COMP-CAN 6/26/2025 | BD30: EXECUTED THRU WO X21094255140 | BE30: =AA30+15 -> #VALUE! | BF30: =IF(ISBLANK(AA30),0,IF(ISBLANK(BH30),(BE30-$L$1),(BH30-BE30))) -> #VALUE! | BQ30: Y | BZ30: C5-5085, C5-5500, C5-5501, 169547 | CA30: =IF(AY30="Y",BA30,"0") -> 0 | CB30: =AC30-CA30 -> #VALUE! | CC30: =BA30 -> 0 | CD30: =AC30-BA30 -> #VALUE! | CE30: =(0.3)*(CD30/AK30)+(0.7)*(CD30/AL30) -> #VALUE! | CF30: =IF(AA30="","0",$CF$1-AA30) -> #VALUE! | CH30: =(0.3)*(($CF$1-W30)/AK30)+(0.7)*(($CF$1-W30)/AL30) -> #N/A | CI30: =CH30-CG30 -> #N/A | CJ30: =CF30/AP30 -> #VALUE! | CK30: =IF(AA30>0,"",$CK$1-W30) | CL30: =IF(R30="NEW","REV","NON-REV") -> NON-REV | CM30: =IF(CK30="","",IF(CK30<91,"0-3 MONTHS",(IF(CK30<181,"4-6 MONTHS",(IF(CK30<271,"7-9 MONTHS",IF(CK30>270,"10 MONTHS AND ABOVE",))))))) | CP30: =IF(CQ30,"NTC ISSUED","FOR ISSUANCE") -> FOR ISSUANCE | CS30: =IF(AND(CQ30=0,CR30=0), "0",IF(CR30,(CR30-CQ30),TODAY()-CQ30)) -> 0 | CW30: 'X21094255140', | CX30: =VLOOKUP(E30,'[1]List of Work Orders'!$A:$I,9,FALSE) -> ME166067 | DC30: =VLOOKUP(E30,'[2]List of Work Orders'!$A:$F,6,FALSE) -> SCHED | DS30: Isan Carlo Lazaro
A31: 44532 | B31: 44518 | D31: BIZ | E31: R21040226 | F31: YIELDERS TRADING CORPORATION | G31: STA. AGUEDA, STO. NINO, PARANAQUE | H31: PARAÑAQUE CITY | I31: PARAÑAQUE | K31: W/ ISSUE | L31: CHALLENGER | M31: SCHED | N31: Isan Carlo Lazaro | O31: 97.3259 | P31: 256.04 | Q31: 0 | R31: RELOC | S31: 541158.15 | T31: 110955.08 | V31: =U31/T31 -> 0 | W31: 44512.696 | X31: 44518.528 | Y31: 44518 | AC31: =AA31-W31 -> -44512.696 | AD31: =AA31-X31 -> -44518.528 | AE31: =AB31-AA31 -> 0 | AF31: =W31+AO31 -> 44534.564 | AG31: =W31+AN31 -> 44544.196 | AH31: =W31+50 -> 44562.696 | AI31: =(0.3)*(AC31/AK31)+(0.7)*(AC31/AL31) -> -1342.4464 | AJ31: =AE31/AP31 -> 0 | AK31: =IF(P31<51,20,(IF(P31<101,23,(IF(P31<201,26,IF(P31<301,28,IF(P31<401,30,(IF(P31<501,32,(IF(P31<1001,40,50))))))))))) -> 28 | AL31: =IF(Q31<51,36,(IF(Q31<101,34,(IF(Q31<201,32,IF(Q31<301,30,IF(Q31<401,28,(IF(Q31<501,26,(IF(Q31<1001,23,20))))))))))) -> 36 | AM31: =(0.75)/((0.3/AK31)+(0.7/AL31)) -> 24.868421 | AN31: =(0.95)/((0.3/AK31)+(0.7/AL31)) -> 31.5 | AO31: =AM31-3 -> 21.868421 | AP31: 60 | AQ31: =0.95*AP31 -> 57 | AR31: =AQ31-5 -> 52 | AS31: =AA31+AP31 -> 60 | AT31: =IFERROR(TODAY()-AA31,"") -> 45895 | BE31: =AA31+15 -> 15 | BF31: =IF(ISBLANK(AA31),0,IF(ISBLANK(BH31),(BE31-$L$1),(BH31-BE31))) -> 0 | BQ31: Y | BZ31: B5-1677, B5-5719, B5-0469, 674317, B5-5649, 201042 | CA31: =IF(AY31="Y",BA31,"0") -> 0 | CB31: =AC31-CA31 -> -44512.696 | CC31: =BA31 -> 0 | CD31: =AC31-BA31 -> -44512.696 | CE31: =(0.3)*(CD31/AK31)+(0.7)*(CD31/AL31) -> -1342.4464 | CF31: =IF(AA31="","0",$CF$1-AA31) -> 0 | CH31: =(0.3)*(($CF$1-W31)/AK31)+(0.7)*(($CF$1-W31)/AL31) -> 40.904411 | CI31: =CH31-CG31 -> 40.904411 | CJ31: =CF31/AP31 -> 0 | CK31: =IF(AA31>0,"",$CK$1-W31) -> 1343.3042 | CL31: =IF(R31="NEW","REV","NON-REV") -> NON-REV | CM31: =IF(CK31="","",IF(CK31<91,"0-3 MONTHS",(IF(CK31<181,"4-6 MONTHS",(IF(CK31<271,"7-9 MONTHS",IF(CK31>270,"10 MONTHS AND ABOVE",))))))) -> 10 MONTHS AND ABOVE | CP31: =IF(CQ31,"NTC ISSUED","FOR ISSUANCE") -> FOR ISSUANCE | CS31: =IF(AND(CQ31=0,CR31=0), "0",IF(CR31,(CR31-CQ31),TODAY()-CQ31)) -> 0 | CW31: 'R21040226', | CX31: =VLOOKUP(E31,'[1]List of Work Orders'!$A:$I,9,FALSE) -> ME166067 | DC31: =VLOOKUP(E31,'[2]List of Work Orders'!$A:$F,6,FALSE) -> SCHED | DS31: Isan Carlo Lazaro
A32: 44551 | B32: 44524 | D32: HMB | E32: X21104486609 | F32: JEFFREY SAGUN CHAN | G32: MATTHEW, MULTINATIONAL VILL, PARANAQUE | H32: PARAÑAQUE CITY | I32: PARAÑAQUE | J32: for follow up Pque BC, DT location issue, 1/11-customer doesn't want DT in front of house, task 3, neighbor holds execution, DT already installed on site - 2/22 | K32: W/ ISSUE | L32: VJC | M32: PCAN3 | N32: Jenneth Madrid | O32: 26.168 | P32: #N/A | Q32: 44 | R32: MODIFICATION | S32: 201770.89 | T32: 30870.26 | V32: =U32/T32 -> 0 | W32: 44518.701 | X32: 44524 | Y32: 44524 | AC32: =AA32-W32 -> -44518.701 | AD32: =AA32-X32 -> -44524 | AE32: =AB32-AA32 -> 0 | AF32: =W32+AO32 -> #N/A | AG32: =W32+AN32 -> #N/A | AH32: =W32+50 -> 44568.701 | AI32: =(0.3)*(AC32/AK32)+(0.7)*(AC32/AL32) -> #N/A | AJ32: =AE32/AP32 -> 0 | AK32: =IF(P32<51,20,(IF(P32<101,23,(IF(P32<201,26,IF(P32<301,28,IF(P32<401,30,(IF(P32<501,32,(IF(P32<1001,40,50))))))))))) -> #N/A | AL32: =IF(Q32<51,36,(IF(Q32<101,34,(IF(Q32<201,32,IF(Q32<301,30,IF(Q32<401,28,(IF(Q32<501,26,(IF(Q32<1001,23,20))))))))))) -> 36 | AM32: =(0.75)/((0.3/AK32)+(0.7/AL32)) -> #N/A | AN32: =(0.95)/((0.3/AK32)+(0.7/AL32)) -> #N/A | AO32: =AM32-3 -> #N/A | AP32: 60 | AQ32: =0.95*AP32 -> 57 | AR32: =AQ32-5 -> 52 | AS32: =AA32+AP32 -> 60 | AT32: =IFERROR(TODAY()-AA32,"") -> 45895 | BE32: =AA32+15 -> 15 | BF32: =IF(ISBLANK(AA32),0,IF(ISBLANK(BH32),(BE32-$L$1),(BH32-BE32))) -> 0 | BQ32: Y | BZ32: CZ8-0312, CZ8-0313, 204233 | CA32: =IF(AY32="Y",BA32,"0") -> 0 | CB32: =AC32-CA32 -> -44518.701 | CC32: =BA32 -> 0 | CD32: =AC32-BA32 -> -44518.701 | CE32: =(0.3)*(CD32/AK32)+(0.7)*(CD32/AL32) -> #N/A | CF32: =IF(AA32="","0",$CF$1-AA32) -> 0 | CH32: =(0.3)*(($CF$1-W32)/AK32)+(0.7)*(($CF$1-W32)/AL32) -> #N/A | CI32: =CH32-CG32 -> #N/A | CJ32: =CF32/AP32 -> 0 | CK32: =IF(AA32>0,"",$CK$1-W32) -> 1337.2986 | CL32: =IF(R32="NEW","REV","NON-REV") -> NON-REV | CM32: =IF(CK32="","",IF(CK32<91,"0-3 MONTHS",(IF(CK32<181,"4-6 MONTHS",(IF(CK32<271,"7-9 MONTHS",IF(CK32>270,"10 MONTHS AND ABOVE",))))))) -> 10 MONTHS AND ABOVE | CP32: =IF(CQ32,"NTC ISSUED","FOR ISSUANCE") -> FOR ISSUANCE | CS32: =IF(AND(CQ32=0,CR32=0), "0",IF(CR32,(CR32-CQ32),TODAY()-CQ32)) -> 0 | CW32: 'X21104486609', | CX32: =VLOOKUP(E32,'[1]List of Work Orders'!$A:$I,9,FALSE) -> ME185284 | DC32: =VLOOKUP(E32,'[2]List of Work Orders'!$A:$F,6,FALSE) -> PCAN3 | DS32: Jenneth Madrid
A33: 44532 | B33: 44532 | D33: HMB | E33: X21030949643 | F33: ROBERTO DE MESA BUNYI | G33: HENRY IDE, KATARUNGAN VILLAGE, MUNTINLUPA | H33: MUNTINLUPA CITY | I33: PARAÑAQUE | J33: HOA ISSUE; HOA holds exection of project; FOR CANCELLATION (superseded by WO X23010211288) | K33: W/ ISSUE | L33: ECOM | M33: PCAN | N33: Ronilo Gange Jr. | O33: 169.1834 | P33: #N/A | Q33: 14 | R33: MODIFICATION | S33: 814987.11 | T33: 132587.33 | V33: =U33/T33 -> 0 | W33: 44524.494 | X33: 44529.524 | Y33: 44531 | AC33: =AA33-W33 -> -44524.494 | AD33: =AA33-X33 -> -44529.524 | AE33: =AB33-AA33 -> 0 | AF33: =W33+AO33 -> #N/A | AG33: =W33+AN33 -> #N/A | AH33: =W33+50 -> 44574.494 | AI33: =(0.3)*(AC33/AK33)+(0.7)*(AC33/AL33) -> #N/A | AJ33: =AE33/AP33 -> 0 | AK33: =IF(P33<51,20,(IF(P33<101,23,(IF(P33<201,26,IF(P33<301,28,IF(P33<401,30,(IF(P33<501,32,(IF(P33<1001,40,50))))))))))) -> #N/A | AL33: =IF(Q33<51,36,(IF(Q33<101,34,(IF(Q33<201,32,IF(Q33<301,30,IF(Q33<401,28,(IF(Q33<501,26,(IF(Q33<1001,23,20))))))))))) -> 36 | AM33: =(0.75)/((0.3/AK33)+(0.7/AL33)) -> #N/A | AN33: =(0.95)/((0.3/AK33)+(0.7/AL33)) -> #N/A | AO33: =AM33-3 -> #N/A | AP33: 60 | AQ33: =0.95*AP33 -> 57 | AR33: =AQ33-5 -> 52 | AS33: =AA33+AP33 -> 60 | AT33: =IFERROR(TODAY()-AA33,"") -> 45895 | BC33: ON GOING MAT RETURN | BE33: =AA33+15 -> 15 | BF33: =IF(ISBLANK(AA33),0,IF(ISBLANK(BH33),(BE33-$L$1),(BH33-BE33))) -> 0 | BQ33: Y | BZ33: CS9-5807, CS9-5808, CS9-5809, 195424, CS9-5812, CS9-5810, CS9-5811 | CA33: =IF(AY33="Y",BA33,"0") -> 0 | CB33: =AC33-CA33 -> -44524.494 | CC33: =BA33 -> 0 | CD33: =AC33-BA33 -> -44524.494 | CE33: =(0.3)*(CD33/AK33)+(0.7)*(CD33/AL33) -> #N/A | CF33: =IF(AA33="","0",$CF$1-AA33) -> 0 | CH33: =(0.3)*(($CF$1-W33)/AK33)+(0.7)*(($CF$1-W33)/AL33) -> #N/A | CI33: =CH33-CG33 -> #N/A | CJ33: =CF33/AP33 -> 0 | CK33: =IF(AA33>0,"",$CK$1-W33) -> 1331.5056 | CL33: =IF(R33="NEW","REV","NON-REV") -> NON-REV | CM33: =IF(CK33="","",IF(CK33<91,"0-3 MONTHS",(IF(CK33<181,"4-6 MONTHS",(IF(CK33<271,"7-9 MONTHS",IF(CK33>270,"10 MONTHS AND ABOVE",))))))) -> 10 MONTHS AND ABOVE | CN33: 45839 | CO33: 18334.94 | CP33: =IF(CQ33,"NTC ISSUED","FOR ISSUANCE") -> NTC ISSUED | CQ33: 45841 | CS33: =IF(AND(CQ33=0,CR33=0), "0",IF(CR33,(CR33-CQ33),TODAY()-CQ33)) -> 54 | CW33: 'X21030949643', | CX33: =VLOOKUP(E33,'[1]List of Work Orders'!$A:$I,9,FALSE) -> ME155242 | DC33: =VLOOKUP(E33,'[2]List of Work Orders'!$A:$F,6,FALSE) -> PCAN | DS33: RONILO GANGE JR.
A34: 44544 | B34: 44534 | D34: HMB | E34: R19291776 | F34: CITY GOVERNMENT OF BACOOR | G34: GEN. TIRONA, HABAY I, BACOOR | H34: BACOOR CITY | I34: DASMA | J34: pole location issue (02-15-23); +1 POLE TASK 1 | K34: W/ ISSUE | L34: DASMA | M34: SCHED | N34: Karl Ferdinand Ruiz | O34: 261.8848 | P34: 708.58 | Q34: 0 | R34: RELOC | S34: 1370048.4 | T34: 323549.72 | V34: =U34/T34 -> 0 | W34: 44531.655 | X34: 44533 | Y34: 44533 | AC34: =AA34-W34 -> -44531.655 | AD34: =AA34-X34 -> -44533 | AE34: =AB34-AA34 -> 0 | AF34: =W34+AO34 -> 44556.49 | AG34: =W34+AN34 -> 44566.913 | AH34: =W34+50 -> 44581.655 | AI34: =(0.3)*(AC34/AK34)+(0.7)*(AC34/AL34) -> -1199.8807 | AJ34: =AE34/AP34 -> 0 | AK34: =IF(P34<51,20,(IF(P34<101,23,(IF(P34<201,26,IF(P34<301,28,IF(P34<401,30,(IF(P34<501,32,(IF(P34<1001,40,50))))))))))) -> 40 | AL34: =IF(Q34<51,36,(IF(Q34<101,34,(IF(Q34<201,32,IF(Q34<301,30,IF(Q34<401,28,(IF(Q34<501,26,(IF(Q34<1001,23,20))))))))))) -> 36 | AM34: =(0.75)/((0.3/AK34)+(0.7/AL34)) -> 27.835052 | AN34: =(0.95)/((0.3/AK34)+(0.7/AL34)) -> 35.257732 | AO34: =AM34-3 -> 24.835052 | AP34: 60 | AQ34: =0.95*AP34 -> 57 | AR34: =AQ34-5 -> 52 | AS34: =AA34+AP34 -> 60 | AT34: =IFERROR(TODAY()-AA34,"") -> 45895 | BE34: =AA34+15 -> 15 | BF34: =IF(ISBLANK(AA34),0,IF(ISBLANK(BH34),(BE34-$L$1),(BH34-BE34))) -> 0 | BQ34: N | BZ34: CW5-5786, CW5-5786, CW5-5785, CW5-5785, CW5-6392, CW5-6393, CX5-0074-T, CW5-0737, 084258, 016045, CW5-0919, 047121, CW5-5787 | CA34: =IF(AY34="Y",BA34,"0") -> 0 | CB34: =AC34-CA34 -> -44531.655 | CC34: =BA34 -> 0 | CD34: =AC34-BA34 -> -44531.655 | CE34: =(0.3)*(CD34/AK34)+(0.7)*(CD34/AL34) -> -1199.8807 | CF34: =IF(AA34="","0",$CF$1-AA34) -> 0 | CH34: =(0.3)*(($CF$1-W34)/AK34)+(0.7)*(($CF$1-W34)/AL34) -> 36.034022 | CI34: =CH34-CG34 -> 36.034022 | CJ34: =CF34/AP34 -> 0 | CK34: =IF(AA34>0,"",$CK$1-W34) -> 1324.3451 | CL34: =IF(R34="NEW","REV","NON-REV") -> NON-REV | CM34: =IF(CK34="","",IF(CK34<91,"0-3 MONTHS",(IF(CK34<181,"4-6 MONTHS",(IF(CK34<271,"7-9 MONTHS",IF(CK34>270,"10 MONTHS AND ABOVE",))))))) -> 10 MONTHS AND ABOVE | CP34: =IF(CQ34,"NTC ISSUED","FOR ISSUANCE") -> FOR ISSUANCE | CS34: =IF(AND(CQ34=0,CR34=0), "0",IF(CR34,(CR34-CQ34),TODAY()-CQ34)) -> 0 | CW34: 'R19291776', | CX34: =VLOOKUP(E34,'[1]List of Work Orders'!$A:$I,9,FALSE) -> ME155242 | DC34: =VLOOKUP(E34,'[2]List of Work Orders'!$A:$F,6,FALSE) -> SCHED | DS34: RONILO GANGE JR.
A35: 44623 | B35: OK | C35: Y | D35: CBG | E35: R21631238 | F35: CAVITEX INFRASTRUCTURE CORP. | G35: N. ARMSTRONG, MOONWALK, PARANAQUE | H35: PARAÑAQUE CITY | I35: PARAÑAQUE | J35: awaiting clearance from CAVITEX on completion of project, task 11 modification | K35: W/ ISSUE | L35: CHALLENGER | M35: FCOMP | N35: Isan Carlo Lazaro | O35: 382.9296 | P35: 638.83 | Q35: 0 | R35: PCA RELOC | S35: 1414835.6 | T35: 433240.12 | V35: =U35/T35 -> 0 | W35: 44621.6 | X35: 44623.523 | Y35: 44623 | AA35: 45818 | AC35: =AA35-W35 -> 1196.4 | AD35: =AA35-X35 -> 1194.4771 | AE35: =AB35-AA35 -> -45818 | AF35: =W35+AO35 -> 44646.435 | AG35: =W35+AN35 -> 44656.858 | AH35: =W35+50 -> 44671.6 | AI35: =(0.3)*(AC35/AK35)+(0.7)*(AC35/AL35) -> 32.236333 | AJ35: =AE35/AP35 -> -763.63333 | AK35: =IF(P35<51,20,(IF(P35<101,23,(IF(P35<201,26,IF(P35<301,28,IF(P35<401,30,(IF(P35<501,32,(IF(P35<1001,40,50))))))))))) -> 40 | AL35: =IF(Q35<51,36,(IF(Q35<101,34,(IF(Q35<201,32,IF(Q35<301,30,IF(Q35<401,28,(IF(Q35<501,26,(IF(Q35<1001,23,20))))))))))) -> 36 | AM35: =(0.75)/((0.3/AK35)+(0.7/AL35)) -> 27.835052 | AN35: =(0.95)/((0.3/AK35)+(0.7/AL35)) -> 35.257732 | AO35: =AM35-3 -> 24.835052 | AP35: 60 | AQ35: =0.95*AP35 -> 57 | AR35: =AQ35-5 -> 52 | AS35: =AA35+AP35 -> 45878 | AT35: =IFERROR(TODAY()-AA35,"") -> 77 | BC35: NO COC | BE35: =AA35+15 -> 45833 | BF35: =IF(ISBLANK(AA35),0,IF(ISBLANK(BH35),(BE35-$L$1),(BH35-BE35))) -> #VALUE! | BQ35: Y | CA35: =IF(AY35="Y",BA35,"0") -> 0 | CB35: =AC35-CA35 -> 1196.4 | CC35: =BA35 -> 0 | CD35: =AC35-BA35 -> 1196.4 | CE35: =(0.3)*(CD35/AK35)+(0.7)*(CD35/AL35) -> 32.236333 | CF35: =IF(AA35="","0",$CF$1-AA35) -> 51 | CH35: =(0.3)*(($CF$1-W35)/AK35)+(0.7)*(($CF$1-W35)/AL35) -> 33.6105 | CI35: =CH35-CG35 -> 33.6105 | CJ35: =CF35/AP35 -> 0.85 | CK35: =IF(AA35>0,"",$CK$1-W35) | CL35: =IF(R35="NEW","REV","NON-REV") -> NON-REV | CM35: =IF(CK35="","",IF(CK35<91,"0-3 MONTHS",(IF(CK35<181,"4-6 MONTHS",(IF(CK35<271,"7-9 MONTHS",IF(CK35>270,"10 MONTHS AND ABOVE",))))))) | CP35: =IF(CQ35,"NTC ISSUED","FOR ISSUANCE") -> FOR ISSUANCE | CS35: =IF(AND(CQ35=0,CR35=0), "0",IF(CR35,(CR35-CQ35),TODAY()-CQ35)) -> 0 | CW35: 'R21631238', | CX35: =VLOOKUP(E35,'[1]List of Work Orders'!$A:$I,9,FALSE) -> ME166067 | DC35: =VLOOKUP(E35,'[2]List of Work Orders'!$A:$F,6,FALSE) -> SCHED | DS35: Isan Carlo Lazaro
A36: 44697 | B36: N/A | D36: REL | E36: P2107115141 | F36: MN_MAJOR (WDESIGN), CONGRESSMAN OFFICE STRIKE B. REVILLA, Relocation Request along Bacoor,Cavite | G36: MOLINO BLVD., BAYANAN, BACOOR | H36: BACOOR CITY | I36: DASMA | J36: ongoing pole installation - with overlapping to P2111120001; for prioritization; for execution on 5th week of March; for execution for the month of May; job 3 done; job 4 hotline works; job 2 hotline works; job 1 PAI remaining site 1 site 2 and site 4 | K36: W/O ISSUE | L36: AVECO | M36: FCOMP | N36: Ronilo Gange Jr. | O36: 635.52 | P36: 1991.66 | Q36: 0 | R36: MN MAJOR | S36: 2185454.3 | T36: 433474.43 | V36: =U36/T36 -> 0 | W36: 44669.79 | X36: 44687.572 | Y36: 44686 | AA36: 45770 | AC36: =AA36-W36 -> 1100.2104 | AD36: =AA36-X36 -> 1082.4278 | AE36: =AB36-AA36 -> -45770 | AF36: =W36+AO36 -> 44696.266 | AG36: =W36+AN36 -> 44707.126 | AH36: =W36+50 -> 44719.79 | AI36: =(0.3)*(AC36/AK36)+(0.7)*(AC36/AL36) -> 27.994243 | AJ36: =AE36/AP36 -> -762.83333 | AK36: =IF(P36<51,20,(IF(P36<101,23,(IF(P36<201,26,IF(P36<301,28,IF(P36<401,30,(IF(P36<501,32,(IF(P36<1001,40,50))))))))))) -> 50 | AL36: =IF(Q36<51,36,(IF(Q36<101,34,(IF(Q36<201,32,IF(Q36<301,30,IF(Q36<401,28,(IF(Q36<501,26,(IF(Q36<1001,23,20))))))))))) -> 36 | AM36: =(0.75)/((0.3/AK36)+(0.7/AL36)) -> 29.475983 | AN36: =(0.95)/((0.3/AK36)+(0.7/AL36)) -> 37.336245 | AO36: =AM36-3 -> 26.475983 | AP36: 60 | AQ36: =0.95*AP36 -> 57 | AR36: =AQ36-5 -> 52 | AS36: =AA36+AP36 -> 45830 | AT36: =IFERROR(TODAY()-AA36,"") -> 125 | BC36: NO COC | BE36: =AA36+15 -> 45785 | BF36: =IF(ISBLANK(AA36),0,IF(ISBLANK(BH36),(BE36-$L$1),(BH36-BE36))) -> #VALUE! | BQ36: N | CA36: =IF(AY36="Y",BA36,"0") -> 0 | CB36: =AC36-CA36 -> 1100.2104 | CC36: =BA36 -> 0 | CD36: =AC36-BA36 -> 1100.2104 | CE36: =(0.3)*(CD36/AK36)+(0.7)*(CD36/AL36) -> 27.994243 | CF36: =IF(AA36="","0",$CF$1-AA36) -> 99 | CH36: =(0.3)*(($CF$1-W36)/AK36)+(0.7)*(($CF$1-W36)/AL36) -> 30.513243 | CI36: =CH36-CG36 -> 30.513243 | CJ36: =CF36/AP36 -> 1.65 | CK36: =IF(AA36>0,"",$CK$1-W36) | CL36: =IF(R36="NEW","REV","NON-REV") -> NON-REV | CM36: =IF(CK36="","",IF(CK36<91,"0-3 MONTHS",(IF(CK36<181,"4-6 MONTHS",(IF(CK36<271,"7-9 MONTHS",IF(CK36>270,"10 MONTHS AND ABOVE",))))))) | CP36: =IF(CQ36,"NTC ISSUED","FOR ISSUANCE") -> FOR ISSUANCE | CS36: =IF(AND(CQ36=0,CR36=0), "0",IF(CR36,(CR36-CQ36),TODAY()-CQ36)) -> 0 | CW36: 'P2107115141', | CX36: =VLOOKUP(E36,'[1]List of Work Orders'!$A:$I,9,FALSE) -> ME155242 | DC36: =VLOOKUP(E36,'[2]List of Work Orders'!$A:$F,6,FALSE) -> FCOMP | DS36: RONILO GANGE JR.
A37: 44680 | B37: OK | C37: Y | D37: CBG | E37: R21662615 | F37: FOOD TERMINAL, INC. | G37: LANGKA, FTI CPD, TAGUIG CITY | H37: TAGUIG CITY | I37: PARAÑAQUE | J37: for completion May 2022 | K37: W/O ISSUE | L37: VJC | M37: DPRG-PCR | N37: Raeven De Quiroz | O37: 102.0535 | P37: #N/A | Q37: 0 | R37: RELOC | S37: 160444.02 | T37: 92012.91 | U37: 83552.45 | V37: =U37/T37 -> 0.90805138 | W37: 44673.324 | X37: 44679 | Y37: 44678 | AC37: =AA37-W37 -> -44673.324 | AD37: =AA37-X37 -> -44679 | AE37: =AB37-AA37 -> 0 | AF37: =W37+AO37 -> #N/A | AG37: =W37+AN37 -> #N/A | AH37: =W37+50 -> 44723.324 | AI37: =(0.3)*(AC37/AK37)+(0.7)*(AC37/AL37) -> #N/A | AJ37: =AE37/AP37 -> 0 | AK37: =IF(P37<51,20,(IF(P37<101,23,(IF(P37<201,26,IF(P37<301,28,IF(P37<401,30,(IF(P37<501,32,(IF(P37<1001,40,50))))))))))) -> #N/A | AL37: =IF(Q37<51,36,(IF(Q37<101,34,(IF(Q37<201,32,IF(Q37<301,30,IF(Q37<401,28,(IF(Q37<501,26,(IF(Q37<1001,23,20))))))))))) -> 36 | AM37: =(0.75)/((0.3/AK37)+(0.7/AL37)) -> #N/A | AN37: =(0.95)/((0.3/AK37)+(0.7/AL37)) -> #N/A | AO37: =AM37-3 -> #N/A | AP37: 60 | AQ37: =0.95*AP37 -> 57 | AR37: =AQ37-5 -> 52 | AS37: =AA37+AP37 -> 60 | AT37: =IFERROR(TODAY()-AA37,"") -> 45895 | BC37: CHECKING OF SERVICE ITEM | BD37: WITH BACKJOB , BILLED | BE37: =AA37+15 -> 15 | BF37: =IF(ISBLANK(AA37),0,IF(ISBLANK(BH37),(BE37-$L$1),(BH37-BE37))) -> 0 | BG37: 44700 | BH37: 44737 | BI37: 44762 | BJ37: ECI | BK37: Y | BL37: Y | BM37: 44762 | BQ37: N | BX37: AZT | BZ37: B8-6279, B8-6280, B8-6281 | CA37: =IF(AY37="Y",BA37,"0") -> 0 | CB37: =AC37-CA37 -> -44673.324 | CC37: =BA37 -> 0 | CD37: =AC37-BA37 -> -44673.324 | CE37: =(0.3)*(CD37/AK37)+(0.7)*(CD37/AL37) -> #N/A | CF37: =IF(AA37="","0",$CF$1-AA37) -> 0 | CH37: =(0.3)*(($CF$1-W37)/AK37)+(0.7)*(($CF$1-W37)/AL37) -> #N/A | CI37: =CH37-CG37 -> #N/A | CJ37: =CF37/AP37 -> 0 | CK37: =IF(AA37>0,"",$CK$1-W37) -> 1182.6757 | CL37: =IF(R37="NEW","REV","NON-REV") -> NON-REV | CM37: =IF(CK37="","",IF(CK37<91,"0-3 MONTHS",(IF(CK37<181,"4-6 MONTHS",(IF(CK37<271,"7-9 MONTHS",IF(CK37>270,"10 MONTHS AND ABOVE",))))))) -> 10 MONTHS AND ABOVE | CP37: =IF(CQ37,"NTC ISSUED","FOR ISSUANCE") -> FOR ISSUANCE | CS37: =IF(AND(CQ37=0,CR37=0), "0",IF(CR37,(CR37-CQ37),TODAY()-CQ37)) -> 0 | CW37: 'R21662615', | CX37: =VLOOKUP(E37,'[1]List of Work Orders'!$A:$I,9,FALSE) -> ME164318 | DC37: =VLOOKUP(E37,'[2]List of Work Orders'!$A:$F,6,FALSE) -> DPRG-PCR | DS37: MBF
A38: 44680 | B38: OK | C38: Y | D38: REL | E38: R20609999 | F38: CAVITEX INFRASTRUCTURE CORP. | G38: KAINGIN RD., KAINGIN, PARANAQUE | H38: PARAÑAQUE CITY | I38: PARAÑAQUE | J38: PENDING MPTS | K38: W/ ISSUE | L38: ECOM | M38: SCHED | N38: Ronilo Gange Jr. | O38: 717.716 | P38: 1361.61 | Q38: 0 | R38: RELOC | S38: 1575766.4 | T38: 923509.73 | V38: =U38/T38 -> 0 | W38: 44677.562 | X38: 44680.637 | Y38: 44680 | AC38: =AA38-W38 -> -44677.562 | AD38: =AA38-X38 -> -44680.637 | AE38: =AB38-AA38 -> 0 | AF38: =W38+AO38 -> 44704.038 | AG38: =W38+AN38 -> 44714.898 | AH38: =W38+50 -> 44727.562 | AI38: =(0.3)*(AC38/AK38)+(0.7)*(AC38/AL38) -> -1136.7957 | AJ38: =AE38/AP38 -> 0 | AK38: =IF(P38<51,20,(IF(P38<101,23,(IF(P38<201,26,IF(P38<301,28,IF(P38<401,30,(IF(P38<501,32,(IF(P38<1001,40,50))))))))))) -> 50 | AL38: =IF(Q38<51,36,(IF(Q38<101,34,(IF(Q38<201,32,IF(Q38<301,30,IF(Q38<401,28,(IF(Q38<501,26,(IF(Q38<1001,23,20))))))))))) -> 36 | AM38: =(0.75)/((0.3/AK38)+(0.7/AL38)) -> 29.475983 | AN38: =(0.95)/((0.3/AK38)+(0.7/AL38)) -> 37.336245 | AO38: =AM38-3 -> 26.475983 | AP38: 60 | AQ38: =0.95*AP38 -> 57 | AR38: =AQ38-5 -> 52 | AS38: =AA38+AP38 -> 60 | AT38: =IFERROR(TODAY()-AA38,"") -> 45895 | BE38: =AA38+15 -> 15 | BF38: =IF(ISBLANK(AA38),0,IF(ISBLANK(BH38),(BE38-$L$1),(BH38-BE38))) -> 0 | BQ38: N | BX38: PDZC | CA38: =IF(AY38="Y",BA38,"0") -> 0 | CB38: =AC38-CA38 -> -44677.562 | CC38: =BA38 -> 0 | CD38: =AC38-BA38 -> -44677.562 | CE38: =(0.3)*(CD38/AK38)+(0.7)*(CD38/AL38) -> -1136.7957 | CF38: =IF(AA38="","0",$CF$1-AA38) -> 0 | CH38: =(0.3)*(($CF$1-W38)/AK38)+(0.7)*(($CF$1-W38)/AL38) -> 30.315483 | CI38: =CH38-CG38 -> 30.315483 | CJ38: =CF38/AP38 -> 0 | CK38: =IF(AA38>0,"",$CK$1-W38) -> 1178.4382 | CL38: =IF(R38="NEW","REV","NON-REV") -> NON-REV | CM38: =IF(CK38="","",IF(CK38<91,"0-3 MONTHS",(IF(CK38<181,"4-6 MONTHS",(IF(CK38<271,"7-9 MONTHS",IF(CK38>270,"10 MONTHS AND ABOVE",))))))) -> 10 MONTHS AND ABOVE | CP38: =IF(CQ38,"NTC ISSUED","FOR ISSUANCE") -> FOR ISSUANCE | CS38: =IF(AND(CQ38=0,CR38=0), "0",IF(CR38,(CR38-CQ38),TODAY()-CQ38)) -> 0 | CW38: 'R20609999', | CX38: =VLOOKUP(E38,'[1]List of Work Orders'!$A:$I,9,FALSE) -> ME155242 | DC38: =VLOOKUP(E38,'[2]List of Work Orders'!$A:$F,6,FALSE) -> SCHED | DS38: RONILO GANGE JR.
A39: 44805 | B39: 44797 | C39: Y | D39: HMB | E39: X22052042329 | F39: MARIA IMELDA BUYOC SANDWEG | G39: JOY, DREAMLAND SUBD, PARANAQUE | H39: PARAÑAQUE CITY | I39: PARAÑAQUE | J39: with issue, 1/11-with cash bond | K39: W/ ISSUE | L39: VJC | M39: PCAN3 | N39: Jemuel Peralta | O39: 162.5766 | P39: #N/A | Q39: 45 | R39: MODIFICATION | S39: 803861.8 | T39: 139773.08 | V39: =U39/T39 -> 0 | W39: 44796.469 | X39: 44804 | Y39: 44804 | AC39: =AA39-W39 -> -44796.469 | AD39: =AA39-X39 -> -44804 | AE39: =AB39-AA39 -> 0 | AF39: =W39+AO39 -> #N/A | AG39: =W39+AN39 -> #N/A | AH39: =W39+50 -> 44846.469 | AI39: =(0.3)*(AC39/AK39)+(0.7)*(AC39/AL39) -> #N/A | AJ39: =AE39/AP39 -> 0 | AK39: =IF(P39<51,20,(IF(P39<101,23,(IF(P39<201,26,IF(P39<301,28,IF(P39<401,30,(IF(P39<501,32,(IF(P39<1001,40,50))))))))))) -> #N/A | AL39: =IF(Q39<51,36,(IF(Q39<101,34,(IF(Q39<201,32,IF(Q39<301,30,IF(Q39<401,28,(IF(Q39<501,26,(IF(Q39<1001,23,20))))))))))) -> 36 | AM39: =(0.75)/((0.3/AK39)+(0.7/AL39)) -> #N/A | AN39: =(0.95)/((0.3/AK39)+(0.7/AL39)) -> #N/A | AO39: =AM39-3 -> #N/A | AP39: 60 | AQ39: =0.95*AP39 -> 57 | AR39: =AQ39-5 -> 52 | AS39: =AA39+AP39 -> 60 | AT39: =IFERROR(TODAY()-AA39,"") -> 45895 | BE39: =AA39+15 -> 15 | BF39: =IF(ISBLANK(AA39),0,IF(ISBLANK(BH39),(BE39-$L$1),(BH39-BE39))) -> 0 | BQ39: Y | BZ39: CX9-0863, 034987, CX9-2040, 212355, CX9-0862, CX9-5935 | CA39: =IF(AY39="Y",BA39,"0") -> 0 | CB39: =AC39-CA39 -> -44796.469 | CC39: =BA39 -> 0 | CD39: =AC39-BA39 -> -44796.469 | CE39: =(0.3)*(CD39/AK39)+(0.7)*(CD39/AL39) -> #N/A | CF39: =IF(AA39="","0",$CF$1-AA39) -> 0 | CH39: =(0.3)*(($CF$1-W39)/AK39)+(0.7)*(($CF$1-W39)/AL39) -> #N/A | CI39: =CH39-CG39 -> #N/A | CJ39: =CF39/AP39 -> 0 | CK39: =IF(AA39>0,"",$CK$1-W39) -> 1059.5312 | CL39: =IF(R39="NEW","REV","NON-REV") -> NON-REV | CM39: =IF(CK39="","",IF(CK39<91,"0-3 MONTHS",(IF(CK39<181,"4-6 MONTHS",(IF(CK39<271,"7-9 MONTHS",IF(CK39>270,"10 MONTHS AND ABOVE",))))))) -> 10 MONTHS AND ABOVE | CP39: =IF(CQ39,"NTC ISSUED","FOR ISSUANCE") -> FOR ISSUANCE | CS39: =IF(AND(CQ39=0,CR39=0), "0",IF(CR39,(CR39-CQ39),TODAY()-CQ39)) -> 0 | CW39: 'X22052042329', | CX39: =VLOOKUP(E39,'[1]List of Work Orders'!$A:$I,9,FALSE) -> ME185130 | DC39: =VLOOKUP(E39,'[2]List of Work Orders'!$A:$F,6,FALSE) -> PCAN3 | DS39: JSP
A40: 44814 | B40: 44813 | D40: CBG | E40: R21631255 | F40: CAVITEX INFRASTRUCTURE CORP., | G40: E. RODRIGUEZ JR. INT, STO. NINO, PARANAQUE | H40: PARAÑAQUE CITY | I40: PARAÑAQUE | J40: for completion within September; w/ ROW issue w/ SM; pending MPTS | K40: W/ ISSUE | L40: ECOM | M40: FCOMP | N40: Ronilo Gange Jr. | O40: 79.6756 | P40: 155.01 | Q40: 0 | R40: RELOC | S40: 412145.24 | T40: 84176.76 | U40: 98865.27 | V40: =U40/T40 -> 1.174496 | W40: 44809.64 | X40: 44811 | Y40: 44811 | Z40: 45687 | AA40: 45687 | AC40: =AA40-W40 -> 877.35972 | AD40: =AA40-X40 -> 876 | AE40: =AB40-AA40 -> -45687 | AF40: =W40+AO40 -> 44830.847 | AG40: =W40+AN40 -> 44840.302 | AH40: =W40+50 -> 44859.64 | AI40: =(0.3)*(AC40/AK40)+(0.7)*(AC40/AL40) -> 27.183154 | AJ40: =AE40/AP40 -> -761.45 | AK40: =IF(P40<51,20,(IF(P40<101,23,(IF(P40<201,26,IF(P40<301,28,IF(P40<401,30,(IF(P40<501,32,(IF(P40<1001,40,50))))))))))) -> 26 | AL40: =IF(Q40<51,36,(IF(Q40<101,34,(IF(Q40<201,32,IF(Q40<301,30,IF(Q40<401,28,(IF(Q40<501,26,(IF(Q40<1001,23,20))))))))))) -> 36 | AM40: =(0.75)/((0.3/AK40)+(0.7/AL40)) -> 24.206897 | AN40: =(0.95)/((0.3/AK40)+(0.7/AL40)) -> 30.662069 | AO40: =AM40-3 -> 21.206897 | AP40: 60 | AQ40: =0.95*AP40 -> 57 | AR40: =AQ40-5 -> 52 | AS40: =AA40+AP40 -> 45747 | AT40: =IFERROR(TODAY()-AA40,"") -> 208 | BC40: NO COC | BD40: PARTIALLY BILLED | BE40: =AA40+15 -> 45702 | BF40: =IF(ISBLANK(AA40),0,IF(ISBLANK(BH40),(BE40-$L$1),(BH40-BE40))) -> #VALUE! | BQ40: N | CA40: =IF(AY40="Y",BA40,"0") -> 0 | CB40: =AC40-CA40 -> 877.35972 | CC40: =BA40 -> 0 | CD40: =AC40-BA40 -> 877.35972 | CE40: =(0.3)*(CD40/AK40)+(0.7)*(CD40/AL40) -> 27.183154 | CF40: =IF(AA40="","0",$CF$1-AA40) -> 182 | CH40: =(0.3)*(($CF$1-W40)/AK40)+(0.7)*(($CF$1-W40)/AL40) -> 32.822043 | CI40: =CH40-CG40 -> 32.822043 | CJ40: =CF40/AP40 -> 3.0333333 | CK40: =IF(AA40>0,"",$CK$1-W40) | CL40: =IF(R40="NEW","REV","NON-REV") -> NON-REV | CM40: =IF(CK40="","",IF(CK40<91,"0-3 MONTHS",(IF(CK40<181,"4-6 MONTHS",(IF(CK40<271,"7-9 MONTHS",IF(CK40>270,"10 MONTHS AND ABOVE",))))))) | CP40: =IF(CQ40,"NTC ISSUED","FOR ISSUANCE") -> FOR ISSUANCE | CS40: =IF(AND(CQ40=0,CR40=0), "0",IF(CR40,(CR40-CQ40),TODAY()-CQ40)) -> 0 | CW40: 'R21631255', | CX40: =VLOOKUP(E40,'[1]List of Work Orders'!$A:$I,9,FALSE) -> ME155242 | DC40: =VLOOKUP(E40,'[2]List of Work Orders'!$A:$F,6,FALSE) -> FCOMP | DS40: RONILO GANGE JR.
A41: 44814 | B41: OK | C41: Y | D41: REL | E41: R21135764 | F41: CAVITEX INFRASTRUCTURE CORP. | G41: MULTINATIONAL VILL, MULTINATIONAL VILL, PARANAQUE | H41: PARAÑAQUE CITY | I41: PARAÑAQUE | J41: for completion within October; on going digging, tasks 5 and 7(90 ft), 11; asking for assistance w/ MPTS | K41: W/ ISSUE | L41: ECOM | M41: FCOMP | N41: Ronilo Gange Jr. | O41: 812.4623 | P41: 1110.82 | Q41: 0 | R41: RELOC | S41: 2403133.2 | T41: 809631.02 | U41: =101348.51+73663.35 -> 175011.86 | V41: =U41/T41 -> 0.21616249 | W41: 44811.328 | X41: 44813 | Y41: 44816 | Z41: 45758 | AA41: 45769 | AC41: =AA41-W41 -> 957.67153 | AD41: =AA41-X41 -> 956 | AE41: =AB41-AA41 -> -45769 | AF41: =W41+AO41 -> 44837.804 | AG41: =W41+AN41 -> 44848.665 | AH41: =W41+50 -> 44861.328 | AI41: =(0.3)*(AC41/AK41)+(0.7)*(AC41/AL41) -> 24.36742 | AJ41: =AE41/AP41 -> -762.81667 | AK41: =IF(P41<51,20,(IF(P41<101,23,(IF(P41<201,26,IF(P41<301,28,IF(P41<401,30,(IF(P41<501,32,(IF(P41<1001,40,50))))))))))) -> 50 | AL41: =IF(Q41<51,36,(IF(Q41<101,34,(IF(Q41<201,32,IF(Q41<301,30,IF(Q41<401,28,(IF(Q41<501,26,(IF(Q41<1001,23,20))))))))))) -> 36 | AM41: =(0.75)/((0.3/AK41)+(0.7/AL41)) -> 29.475983 | AN41: =(0.95)/((0.3/AK41)+(0.7/AL41)) -> 37.336245 | AO41: =AM41-3 -> 26.475983 | AP41: 60 | AQ41: =0.95*AP41 -> 57 | AR41: =AQ41-5 -> 52 | AS41: =AA41+AP41 -> 45829 | AT41: =IFERROR(TODAY()-AA41,"") -> 126 | BC41: NO COC | BD41: PARTIALLY BILLED | BE41: =AA41+15 -> 45784 | BF41: =IF(ISBLANK(AA41),0,IF(ISBLANK(BH41),(BE41-$L$1),(BH41-BE41))) -> #VALUE! | BQ41: N | CA41: =IF(AY41="Y",BA41,"0") -> 0 | CB41: =AC41-CA41 -> 957.67153 | CC41: =BA41 -> 0 | CD41: =AC41-BA41 -> 957.67153 | CE41: =(0.3)*(CD41/AK41)+(0.7)*(CD41/AL41) -> 24.36742 | CF41: =IF(AA41="","0",$CF$1-AA41) -> 100 | CH41: =(0.3)*(($CF$1-W41)/AK41)+(0.7)*(($CF$1-W41)/AL41) -> 26.911864 | CI41: =CH41-CG41 -> 26.911864 | CJ41: =CF41/AP41 -> 1.6666667 | CK41: =IF(AA41>0,"",$CK$1-W41) | CL41: =IF(R41="NEW","REV","NON-REV") -> NON-REV | CM41: =IF(CK41="","",IF(CK41<91,"0-3 MONTHS",(IF(CK41<181,"4-6 MONTHS",(IF(CK41<271,"7-9 MONTHS",IF(CK41>270,"10 MONTHS AND ABOVE",))))))) | CP41: =IF(CQ41,"NTC ISSUED","FOR ISSUANCE") -> FOR ISSUANCE | CS41: =IF(AND(CQ41=0,CR41=0), "0",IF(CR41,(CR41-CQ41),TODAY()-CQ41)) -> 0 | CW41: 'R21135764', | CX41: =VLOOKUP(E41,'[1]List of Work Orders'!$A:$I,9,FALSE) -> ME155242 | DC41: =VLOOKUP(E41,'[2]List of Work Orders'!$A:$F,6,FALSE) -> FCOMP | DS41: RONILO GANGE JR.
A42: 44852 | B42: 44847 | D42: HMB | E42: X22093866615 | F42: DULCINEA BALCE SANTOS | G42: HAITI, BETTER LIVING SUBD, PARANAQUE | H42: PARAÑAQUE CITY | I42: PARAÑAQUE | J42: joint survey within September 2023/ Pole location issue for Survey 3/20/25- sched for digging ; WO COMPLETED CONJUCT WO (X25041157540) | K42: W/ ISSUE | L42: VJC | M42: SCHED | N42: Jenneth Madrid | O42: 29.89 | P42: 109.96 | Q42: 45 | R42: MODIFICATION | S42: 167939.25 | T42: 22082.54 | V42: =U42/T42 -> 0 | W42: 44845.652 | X42: 44848 | Y42: 44847 | AC42: =AA42-W42 -> -44845.652 | AD42: =AA42-X42 -> -44848 | AE42: =AB42-AA42 -> 0 | AF42: =W42+AO42 -> 44866.859 | AG42: =W42+AN42 -> 44876.314 | AH42: =W42+50 -> 44895.652 | AI42: =(0.3)*(AC42/AK42)+(0.7)*(AC42/AL42) -> -1389.4486 | AJ42: =AE42/AP42 -> 0 | AK42: =IF(P42<51,20,(IF(P42<101,23,(IF(P42<201,26,IF(P42<301,28,IF(P42<401,30,(IF(P42<501,32,(IF(P42<1001,40,50))))))))))) -> 26 | AL42: =IF(Q42<51,36,(IF(Q42<101,34,(IF(Q42<201,32,IF(Q42<301,30,IF(Q42<401,28,(IF(Q42<501,26,(IF(Q42<1001,23,20))))))))))) -> 36 | AM42: =(0.75)/((0.3/AK42)+(0.7/AL42)) -> 24.206897 | AN42: =(0.95)/((0.3/AK42)+(0.7/AL42)) -> 30.662069 | AO42: =AM42-3 -> 21.206897 | AP42: 60 | AQ42: =0.95*AP42 -> 57 | AR42: =AQ42-5 -> 52 | AS42: =AA42+AP42 -> 60 | AT42: =IFERROR(TODAY()-AA42,"") -> 45895 | BE42: =AA42+15 -> 15 | BF42: =IF(ISBLANK(AA42),0,IF(ISBLANK(BH42),(BE42-$L$1),(BH42-BE42))) -> 0 | BQ42: N | BZ42: DY1-5978 | CA42: =IF(AY42="Y",BA42,"0") -> 0 | CB42: =AC42-CA42 -> -44845.652 | CC42: =BA42 -> 0 | CD42: =AC42-BA42 -> -44845.652 | CE42: =(0.3)*(CD42/AK42)+(0.7)*(CD42/AL42) -> -1389.4486 | CF42: =IF(AA42="","0",$CF$1-AA42) -> 0 | CH42: =(0.3)*(($CF$1-W42)/AK42)+(0.7)*(($CF$1-W42)/AL42) -> 31.706292 | CI42: =CH42-CG42 -> 31.706292 | CJ42: =CF42/AP42 -> 0 | CK42: =IF(AA42>0,"",$CK$1-W42) -> 1010.3479 | CL42: =IF(R42="NEW","REV","NON-REV") -> NON-REV | CM42: =IF(CK42="","",IF(CK42<91,"0-3 MONTHS",(IF(CK42<181,"4-6 MONTHS",(IF(CK42<271,"7-9 MONTHS",IF(CK42>270,"10 MONTHS AND ABOVE",))))))) -> 10 MONTHS AND ABOVE | CP42: =IF(CQ42,"NTC ISSUED","FOR ISSUANCE") -> FOR ISSUANCE | CS42: =IF(AND(CQ42=0,CR42=0), "0",IF(CR42,(CR42-CQ42),TODAY()-CQ42)) -> 0 | CW42: 'X22093866615', | CX42: =VLOOKUP(E42,'[1]List of Work Orders'!$A:$I,9,FALSE) -> ME185284 | DC42: =VLOOKUP(E42,'[2]List of Work Orders'!$A:$F,6,FALSE) -> SCHED | DS42: Jenneth Madrid
A43: 44888 | B43: 44883 | C43: Y | D43: CBG | E43: X22031018462 | F43: GLOBE TELECOM, INC. | G43: BLOCK 13, BERNABE CPD, LAS PINAS CITY | H43: LAS PIÑAS CITY | I43: PARAÑAQUE | J43: with digging issue; w/ ROW issue (03-16-23); for digging (03-23-23); follow up to BC Pole location issue (with drainage) - resolved (with revised plan / new pole location and tapping point - revised last 05/16/2023) 09192023 ROW issue - MIDC and GLOBE has on-going negotiation for the neighbor's concent as per CRS TSE 11242023 ROW issue - waiting for update from Globe for the neighbor's concent as per TSE | K43: W/ ISSUE | L43: AVECO | M43: CAN | N43: Ronilo Gange Jr. | O43: 76.2585 | P43: #N/A | Q43: 23 | R43: MODIFICATION | S43: 359981.35 | T43: 63350.41 | V43: =U43/T43 -> 0 | W43: 44881.38 | X43: 44886 | Y43: 44883 | AA43: CAN | AC43: =AA43-W43 -> #VALUE! | AD43: =AA43-X43 -> #VALUE! | AE43: =AB43-AA43 -> #VALUE! | AF43: =W43+AO43 -> #N/A | AG43: =W43+AN43 -> #N/A | AH43: =W43+50 -> 44931.38 | AI43: =(0.3)*(AC43/AK43)+(0.7)*(AC43/AL43) -> #VALUE! | AJ43: =AE43/AP43 -> #VALUE! | AK43: =IF(P43<51,20,(IF(P43<101,23,(IF(P43<201,26,IF(P43<301,28,IF(P43<401,30,(IF(P43<501,32,(IF(P43<1001,40,50))))))))))) -> #N/A | AL43: =IF(Q43<51,36,(IF(Q43<101,34,(IF(Q43<201,32,IF(Q43<301,30,IF(Q43<401,28,(IF(Q43<501,26,(IF(Q43<1001,23,20))))))))))) -> 36 | AM43: =(0.75)/((0.3/AK43)+(0.7/AL43)) -> #N/A | AN43: =(0.95)/((0.3/AK43)+(0.7/AL43)) -> #N/A | AO43: =AM43-3 -> #N/A | AP43: 60 | AQ43: =0.95*AP43 -> 57 | AR43: =AQ43-5 -> 52 | AS43: =AA43+AP43 -> #VALUE! | AT43: =IFERROR(TODAY()-AA43,"") | BE43: =AA43+15 -> #VALUE! | BF43: =IF(ISBLANK(AA43),0,IF(ISBLANK(BH43),(BE43-$L$1),(BH43-BE43))) -> #VALUE! | BQ43: Y | BZ43: CY7-2464, CY7-6092, CY7-6085, 204030 | CA43: =IF(AY43="Y",BA43,"0") -> 0 | CB43: =AC43-CA43 -> #VALUE! | CC43: =BA43 -> 0 | CD43: =AC43-BA43 -> #VALUE! | CE43: =(0.3)*(CD43/AK43)+(0.7)*(CD43/AL43) -> #VALUE! | CF43: =IF(AA43="","0",$CF$1-AA43) -> #VALUE! | CH43: =(0.3)*(($CF$1-W43)/AK43)+(0.7)*(($CF$1-W43)/AL43) -> #N/A | CI43: =CH43-CG43 -> #N/A | CJ43: =CF43/AP43 -> #VALUE! | CK43: =IF(AA43>0,"",$CK$1-W43) | CL43: =IF(R43="NEW","REV","NON-REV") -> NON-REV | CM43: =IF(CK43="","",IF(CK43<91,"0-3 MONTHS",(IF(CK43<181,"4-6 MONTHS",(IF(CK43<271,"7-9 MONTHS",IF(CK43>270,"10 MONTHS AND ABOVE",))))))) | CP43: =IF(CQ43,"NTC ISSUED","FOR ISSUANCE") -> FOR ISSUANCE | CS43: =IF(AND(CQ43=0,CR43=0), "0",IF(CR43,(CR43-CQ43),TODAY()-CQ43)) -> 0 | CW43: 'X22031018462', | CX43: =VLOOKUP(E43,'[1]List of Work Orders'!$A:$I,9,FALSE) -> ME155242 | DC43: =VLOOKUP(E43,'[2]List of Work Orders'!$A:$F,6,FALSE) -> CAN | DS43: RONILO GANGE JR.
A44: 44938 | B44: N/A | D44: MN | E44: P2207136641 | F44: RTA MN_ 415FIL Replacement of Wood Pole on DU1-0017 | G44: ILAYA ALABANG ALABANG MUNTINLUPA | H44: MUNTINLUPA CITY | I44: PARAÑAQUE | J44: contact person needed from BC; for checking w/ PnS | K44: W/O ISSUE | L44: AVECO | M44: SCHED | N44: Ronilo Gange Jr. | O44: 111.413 | P44: #N/A | Q44: 0 | R44: RTA | S44: 223165.1 | T44: 121601.58 | V44: =U44/T44 -> 0 | W44: 44897.615 | X44: 44937.443 | Y44: 44939 | AC44: =AA44-W44 -> -44897.615 | AD44: =AA44-X44 -> -44937.443 | AE44: =AB44-AA44 -> 0 | AF44: =W44+AO44 -> #N/A | AG44: =W44+AN44 -> #N/A | AH44: =W44+50 -> 44947.615 | AI44: =(0.3)*(AC44/AK44)+(0.7)*(AC44/AL44) -> #N/A | AJ44: =AE44/AP44 -> 0 | AK44: =IF(P44<51,20,(IF(P44<101,23,(IF(P44<201,26,IF(P44<301,28,IF(P44<401,30,(IF(P44<501,32,(IF(P44<1001,40,50))))))))))) -> #N/A | AL44: =IF(Q44<51,36,(IF(Q44<101,34,(IF(Q44<201,32,IF(Q44<301,30,IF(Q44<401,28,(IF(Q44<501,26,(IF(Q44<1001,23,20))))))))))) -> 36 | AM44: =(0.75)/((0.3/AK44)+(0.7/AL44)) -> #N/A | AN44: =(0.95)/((0.3/AK44)+(0.7/AL44)) -> #N/A | AO44: =AM44-3 -> #N/A | AP44: 60 | AQ44: =0.95*AP44 -> 57 | AR44: =AQ44-5 -> 52 | AS44: =AA44+AP44 -> 60 | AT44: =IFERROR(TODAY()-AA44,"") -> 45895 | BE44: =AA44+15 -> 15 | BF44: =IF(ISBLANK(AA44),0,IF(ISBLANK(BH44),(BE44-$L$1),(BH44-BE44))) -> 0 | BQ44: N | CA44: =IF(AY44="Y",BA44,"0") -> 0 | CB44: =AC44-CA44 -> -44897.615 | CC44: =BA44 -> 0 | CD44: =AC44-BA44 -> -44897.615 | CE44: =(0.3)*(CD44/AK44)+(0.7)*(CD44/AL44) -> #N/A | CF44: =IF(AA44="","0",$CF$1-AA44) -> 0 | CH44: =(0.3)*(($CF$1-W44)/AK44)+(0.7)*(($CF$1-W44)/AL44) -> #N/A | CI44: =CH44-CG44 -> #N/A | CJ44: =CF44/AP44 -> 0 | CK44: =IF(AA44>0,"",$CK$1-W44) -> 958.38542 | CL44: =IF(R44="NEW","REV","NON-REV") -> NON-REV | CM44: =IF(CK44="","",IF(CK44<91,"0-3 MONTHS",(IF(CK44<181,"4-6 MONTHS",(IF(CK44<271,"7-9 MONTHS",IF(CK44>270,"10 MONTHS AND ABOVE",))))))) -> 10 MONTHS AND ABOVE | CP44: =IF(CQ44,"NTC ISSUED","FOR ISSUANCE") -> FOR ISSUANCE | CS44: =IF(AND(CQ44=0,CR44=0), "0",IF(CR44,(CR44-CQ44),TODAY()-CQ44)) -> 0 | CW44: 'P2207136641', | CX44: =VLOOKUP(E44,'[1]List of Work Orders'!$A:$I,9,FALSE) -> ME155242 | DC44: =VLOOKUP(E44,'[2]List of Work Orders'!$A:$F,6,FALSE) -> SCHED | DS44: RONILO GANGE JR.
A45: 44938 | B45: N/A | D45: MN | E45: P2211141348 | F45: RTA MN - 415FIL - DT1-0065 - Replacement of rotten, hazardous and old standard pole | G45: T. MOLINA ALABANG ALABANG MUNTINLUPA | H45: MUNTINLUPA CITY | I45: PARAÑAQUE | J45: for crew survey; for C1 survey | K45: W/O ISSUE | L45: ECOM | M45: SCHED | N45: Ronilo Gange Jr. | O45: 39.2801 | P45: #N/A | Q45: 0 | R45: RTA | S45: 69142.18 | T45: 30610.91 | V45: =U45/T45 -> 0 | W45: 44899.901 | X45: 44937.438 | Y45: 44940 | AC45: =AA45-W45 -> -44899.901 | AD45: =AA45-X45 -> -44937.438 | AE45: =AB45-AA45 -> 0 | AF45: =W45+AO45 -> #N/A | AG45: =W45+AN45 -> #N/A | AH45: =W45+50 -> 44949.901 | AI45: =(0.3)*(AC45/AK45)+(0.7)*(AC45/AL45) -> #N/A | AJ45: =AE45/AP45 -> 0 | AK45: =IF(P45<51,20,(IF(P45<101,23,(IF(P45<201,26,IF(P45<301,28,IF(P45<401,30,(IF(P45<501,32,(IF(P45<1001,40,50))))))))))) -> #N/A | AL45: =IF(Q45<51,36,(IF(Q45<101,34,(IF(Q45<201,32,IF(Q45<301,30,IF(Q45<401,28,(IF(Q45<501,26,(IF(Q45<1001,23,20))))))))))) -> 36 | AM45: =(0.75)/((0.3/AK45)+(0.7/AL45)) -> #N/A | AN45: =(0.95)/((0.3/AK45)+(0.7/AL45)) -> #N/A | AO45: =AM45-3 -> #N/A | AP45: 60 | AQ45: =0.95*AP45 -> 57 | AR45: =AQ45-5 -> 52 | AS45: =AA45+AP45 -> 60 | AT45: =IFERROR(TODAY()-AA45,"") -> 45895 | BE45: =AA45+15 -> 15 | BF45: =IF(ISBLANK(AA45),0,IF(ISBLANK(BH45),(BE45-$L$1),(BH45-BE45))) -> 0 | BQ45: N | CA45: =IF(AY45="Y",BA45,"0") -> 0 | CB45: =AC45-CA45 -> -44899.901 | CC45: =BA45 -> 0 | CD45: =AC45-BA45 -> -44899.901 | CE45: =(0.3)*(CD45/AK45)+(0.7)*(CD45/AL45) -> #N/A | CF45: =IF(AA45="","0",$CF$1-AA45) -> 0 | CH45: =(0.3)*(($CF$1-W45)/AK45)+(0.7)*(($CF$1-W45)/AL45) -> #N/A | CI45: =CH45-CG45 -> #N/A | CJ45: =CF45/AP45 -> 0 | CK45: =IF(AA45>0,"",$CK$1-W45) -> 956.09931 | CL45: =IF(R45="NEW","REV","NON-REV") -> NON-REV | CM45: =IF(CK45="","",IF(CK45<91,"0-3 MONTHS",(IF(CK45<181,"4-6 MONTHS",(IF(CK45<271,"7-9 MONTHS",IF(CK45>270,"10 MONTHS AND ABOVE",))))))) -> 10 MONTHS AND ABOVE | CP45: =IF(CQ45,"NTC ISSUED","FOR ISSUANCE") -> FOR ISSUANCE | CS45: =IF(AND(CQ45=0,CR45=0), "0",IF(CR45,(CR45-CQ45),TODAY()-CQ45)) -> 0 | CW45: 'P2211141348', | CX45: =VLOOKUP(E45,'[1]List of Work Orders'!$A:$I,9,FALSE) -> ME155242 | DC45: =VLOOKUP(E45,'[2]List of Work Orders'!$A:$F,6,FALSE) -> SCHED | DS45: RONILO GANGE JR.
A46: 44938 | B46: N/A | D46: MN | E46: P2211141350 | F46: RTA MN - 415FIL - DU1-0445 - Replacement of rotten, hazardous and old standard pole | G46: T. MOLINA ALABANG ALABANG MUNTINLUPA | H46: MUNTINLUPA CITY | I46: PARAÑAQUE | J46: contact person needed from BC; for checking w/ PnS | K46: W/O ISSUE | L46: AVECO | M46: SCHED | N46: Ronilo Gange Jr. | O46: 40.3024 | P46: #N/A | Q46: 0 | R46: RTA | S46: 70118.66 | T46: 31407.59 | V46: =U46/T46 -> 0 | W46: 44900.447 | X46: 44937.44 | Y46: 44939 | AC46: =AA46-W46 -> -44900.447 | AD46: =AA46-X46 -> -44937.44 | AE46: =AB46-AA46 -> 0 | AF46: =W46+AO46 -> #N/A | AG46: =W46+AN46 -> #N/A | AH46: =W46+50 -> 44950.447 | AI46: =(0.3)*(AC46/AK46)+(0.7)*(AC46/AL46) -> #N/A | AJ46: =AE46/AP46 -> 0 | AK46: =IF(P46<51,20,(IF(P46<101,23,(IF(P46<201,26,IF(P46<301,28,IF(P46<401,30,(IF(P46<501,32,(IF(P46<1001,40,50))))))))))) -> #N/A | AL46: =IF(Q46<51,36,(IF(Q46<101,34,(IF(Q46<201,32,IF(Q46<301,30,IF(Q46<401,28,(IF(Q46<501,26,(IF(Q46<1001,23,20))))))))))) -> 36 | AM46: =(0.75)/((0.3/AK46)+(0.7/AL46)) -> #N/A | AN46: =(0.95)/((0.3/AK46)+(0.7/AL46)) -> #N/A | AO46: =AM46-3 -> #N/A | AP46: 60 | AQ46: =0.95*AP46 -> 57 | AR46: =AQ46-5 -> 52 | AS46: =AA46+AP46 -> 60 | AT46: =IFERROR(TODAY()-AA46,"") -> 45895 | BE46: =AA46+15 -> 15 | BF46: =IF(ISBLANK(AA46),0,IF(ISBLANK(BH46),(BE46-$L$1),(BH46-BE46))) -> 0 | BQ46: N | CA46: =IF(AY46="Y",BA46,"0") -> 0 | CB46: =AC46-CA46 -> -44900.447 | CC46: =BA46 -> 0 | CD46: =AC46-BA46 -> -44900.447 | CE46: =(0.3)*(CD46/AK46)+(0.7)*(CD46/AL46) -> #N/A | CF46: =IF(AA46="","0",$CF$1-AA46) -> 0 | CH46: =(0.3)*(($CF$1-W46)/AK46)+(0.7)*(($CF$1-W46)/AL46) -> #N/A | CI46: =CH46-CG46 -> #N/A | CJ46: =CF46/AP46 -> 0 | CK46: =IF(AA46>0,"",$CK$1-W46) -> 955.55347 | CL46: =IF(R46="NEW","REV","NON-REV") -> NON-REV | CM46: =IF(CK46="","",IF(CK46<91,"0-3 MONTHS",(IF(CK46<181,"4-6 MONTHS",(IF(CK46<271,"7-9 MONTHS",IF(CK46>270,"10 MONTHS AND ABOVE",))))))) -> 10 MONTHS AND ABOVE | CP46: =IF(CQ46,"NTC ISSUED","FOR ISSUANCE") -> FOR ISSUANCE | CS46: =IF(AND(CQ46=0,CR46=0), "0",IF(CR46,(CR46-CQ46),TODAY()-CQ46)) -> 0 | CW46: 'P2211141350', | CX46: =VLOOKUP(E46,'[1]List of Work Orders'!$A:$I,9,FALSE) -> ME155242 | DC46: =VLOOKUP(E46,'[2]List of Work Orders'!$A:$F,6,FALSE) -> SCHED | DS46: RONILO GANGE JR.
A47: 44938 | B47: N/A | D47: MN | E47: P2211141356 | F47: RTA MN - 415FIL - DT1-0057 - Replacement of rotten, hazardous and old standard pole | G47: ILAYA PUROK 7 ALABANG MUNTINLUPA | H47: MUNTINLUPA CITY | I47: PARAÑAQUE | J47: for crew survey; for C1 survey | K47: W/O ISSUE | L47: ECOM | M47: SCHED | N47: Ronilo Gange Jr. | O47: 42.5861 | P47: #N/A | Q47: 0 | R47: RTA | S47: 73123.35 | T47: 33187.27 | V47: =U47/T47 -> 0 | W47: 44901.942 | X47: 44937.597 | Y47: 44940 | AC47: =AA47-W47 -> -44901.942 | AD47: =AA47-X47 -> -44937.597 | AE47: =AB47-AA47 -> 0 | AF47: =W47+AO47 -> #N/A | AG47: =W47+AN47 -> #N/A | AH47: =W47+50 -> 44951.942 | AI47: =(0.3)*(AC47/AK47)+(0.7)*(AC47/AL47) -> #N/A | AJ47: =AE47/AP47 -> 0 | AK47: =IF(P47<51,20,(IF(P47<101,23,(IF(P47<201,26,IF(P47<301,28,IF(P47<401,30,(IF(P47<501,32,(IF(P47<1001,40,50))))))))))) -> #N/A | AL47: =IF(Q47<51,36,(IF(Q47<101,34,(IF(Q47<201,32,IF(Q47<301,30,IF(Q47<401,28,(IF(Q47<501,26,(IF(Q47<1001,23,20))))))))))) -> 36 | AM47: =(0.75)/((0.3/AK47)+(0.7/AL47)) -> #N/A | AN47: =(0.95)/((0.3/AK47)+(0.7/AL47)) -> #N/A | AO47: =AM47-3 -> #N/A | AP47: 60 | AQ47: =0.95*AP47 -> 57 | AR47: =AQ47-5 -> 52 | AS47: =AA47+AP47 -> 60 | AT47: =IFERROR(TODAY()-AA47,"") -> 45895 | BE47: =AA47+15 -> 15 | BF47: =IF(ISBLANK(AA47),0,IF(ISBLANK(BH47),(BE47-$L$1),(BH47-BE47))) -> 0 | BQ47: N | CA47: =IF(AY47="Y",BA47,"0") -> 0 | CB47: =AC47-CA47 -> -44901.942 | CC47: =BA47 -> 0 | CD47: =AC47-BA47 -> -44901.942 | CE47: =(0.3)*(CD47/AK47)+(0.7)*(CD47/AL47) -> #N/A | CF47: =IF(AA47="","0",$CF$1-AA47) -> 0 | CH47: =(0.3)*(($CF$1-W47)/AK47)+(0.7)*(($CF$1-W47)/AL47) -> #N/A | CI47: =CH47-CG47 -> #N/A | CJ47: =CF47/AP47 -> 0 | CK47: =IF(AA47>0,"",$CK$1-W47) -> 954.05833 | CL47: =IF(R47="NEW","REV","NON-REV") -> NON-REV | CM47: =IF(CK47="","",IF(CK47<91,"0-3 MONTHS",(IF(CK47<181,"4-6 MONTHS",(IF(CK47<271,"7-9 MONTHS",IF(CK47>270,"10 MONTHS AND ABOVE",))))))) -> 10 MONTHS AND ABOVE | CP47: =IF(CQ47,"NTC ISSUED","FOR ISSUANCE") -> FOR ISSUANCE | CS47: =IF(AND(CQ47=0,CR47=0), "0",IF(CR47,(CR47-CQ47),TODAY()-CQ47)) -> 0 | CW47: 'P2211141356', | CX47: =VLOOKUP(E47,'[1]List of Work Orders'!$A:$I,9,FALSE) -> ME155242 | DC47: =VLOOKUP(E47,'[2]List of Work Orders'!$A:$F,6,FALSE) -> SCHED | DS47: RONILO GANGE JR.
A48: 44938 | B48: N/A | D48: MN | E48: P2211141357 | F48: RTA MN - 415FIL - DU1-0003 - Replacement of rotten, hazardous and old standard pole | G48: ILAYA ALABANG ALABANG MUNTINLUPA | H48: MUNTINLUPA CITY | I48: PARAÑAQUE | J48: contact person needed from BC; for checking w/ PnS | K48: W/O ISSUE | L48: AVECO | M48: SCHED | N48: Ronilo Gange Jr. | O48: 51.0125 | P48: #N/A | Q48: 0 | R48: RTA | S48: 80899.28 | T48: 39753.95 | V48: =U48/T48 -> 0 | W48: 44901.943 | X48: 44937.6 | Y48: 44939 | AC48: =AA48-W48 -> -44901.943 | AD48: =AA48-X48 -> -44937.6 | AE48: =AB48-AA48 -> 0 | AF48: =W48+AO48 -> #N/A | AG48: =W48+AN48 -> #N/A | AH48: =W48+50 -> 44951.943 | AI48: =(0.3)*(AC48/AK48)+(0.7)*(AC48/AL48) -> #N/A | AJ48: =AE48/AP48 -> 0 | AK48: =IF(P48<51,20,(IF(P48<101,23,(IF(P48<201,26,IF(P48<301,28,IF(P48<401,30,(IF(P48<501,32,(IF(P48<1001,40,50))))))))))) -> #N/A | AL48: =IF(Q48<51,36,(IF(Q48<101,34,(IF(Q48<201,32,IF(Q48<301,30,IF(Q48<401,28,(IF(Q48<501,26,(IF(Q48<1001,23,20))))))))))) -> 36 | AM48: =(0.75)/((0.3/AK48)+(0.7/AL48)) -> #N/A | AN48: =(0.95)/((0.3/AK48)+(0.7/AL48)) -> #N/A | AO48: =AM48-3 -> #N/A | AP48: 60 | AQ48: =0.95*AP48 -> 57 | AR48: =AQ48-5 -> 52 | AS48: =AA48+AP48 -> 60 | AT48: =IFERROR(TODAY()-AA48,"") -> 45895 | BE48: =AA48+15 -> 15 | BF48: =IF(ISBLANK(AA48),0,IF(ISBLANK(BH48),(BE48-$L$1),(BH48-BE48))) -> 0 | BQ48: N | CA48: =IF(AY48="Y",BA48,"0") -> 0 | CB48: =AC48-CA48 -> -44901.943 | CC48: =BA48 -> 0 | CD48: =AC48-BA48 -> -44901.943 | CE48: =(0.3)*(CD48/AK48)+(0.7)*(CD48/AL48) -> #N/A | CF48: =IF(AA48="","0",$CF$1-AA48) -> 0 | CH48: =(0.3)*(($CF$1-W48)/AK48)+(0.7)*(($CF$1-W48)/AL48) -> #N/A | CI48: =CH48-CG48 -> #N/A | CJ48: =CF48/AP48 -> 0 | CK48: =IF(AA48>0,"",$CK$1-W48) -> 954.05694 | CL48: =IF(R48="NEW","REV","NON-REV") -> NON-REV | CM48: =IF(CK48="","",IF(CK48<91,"0-3 MONTHS",(IF(CK48<181,"4-6 MONTHS",(IF(CK48<271,"7-9 MONTHS",IF(CK48>270,"10 MONTHS AND ABOVE",))))))) -> 10 MONTHS AND ABOVE | CP48: =IF(CQ48,"NTC ISSUED","FOR ISSUANCE") -> FOR ISSUANCE | CS48: =IF(AND(CQ48=0,CR48=0), "0",IF(CR48,(CR48-CQ48),TODAY()-CQ48)) -> 0 | CW48: 'P2211141357', | CX48: =VLOOKUP(E48,'[1]List of Work Orders'!$A:$I,9,FALSE) -> ME155242 | DC48: =VLOOKUP(E48,'[2]List of Work Orders'!$A:$F,6,FALSE) -> SCHED | DS48: RONILO GANGE JR.
A49: 44938 | B49: N/A | D49: MN | E49: P2211141358 | F49: RTA MN - 415FIL - DV1-0001 - Replacement of rotten, hazardous and old standard pole | G49: VINALON PUROK 3 CUPANG MUNTINLUPA | H49: MUNTINLUPA CITY | I49: PARAÑAQUE | J49: contact person needed from BC; for checking w/ PnS | K49: W/O ISSUE | L49: AVECO | M49: SCHED | N49: Ronilo Gange Jr. | O49: 39.2801 | P49: #N/A | Q49: 0 | R49: RTA | S49: 69142.18 | T49: 30610.91 | V49: =U49/T49 -> 0 | W49: 44901.944 | X49: 44937.603 | Y49: 44939 | AC49: =AA49-W49 -> -44901.944 | AD49: =AA49-X49 -> -44937.603 | AE49: =AB49-AA49 -> 0 | AF49: =W49+AO49 -> #N/A | AG49: =W49+AN49 -> #N/A | AH49: =W49+50 -> 44951.944 | AI49: =(0.3)*(AC49/AK49)+(0.7)*(AC49/AL49) -> #N/A | AJ49: =AE49/AP49 -> 0 | AK49: =IF(P49<51,20,(IF(P49<101,23,(IF(P49<201,26,IF(P49<301,28,IF(P49<401,30,(IF(P49<501,32,(IF(P49<1001,40,50))))))))))) -> #N/A | AL49: =IF(Q49<51,36,(IF(Q49<101,34,(IF(Q49<201,32,IF(Q49<301,30,IF(Q49<401,28,(IF(Q49<501,26,(IF(Q49<1001,23,20))))))))))) -> 36 | AM49: =(0.75)/((0.3/AK49)+(0.7/AL49)) -> #N/A | AN49: =(0.95)/((0.3/AK49)+(0.7/AL49)) -> #N/A | AO49: =AM49-3 -> #N/A | AP49: 60 | AQ49: =0.95*AP49 -> 57 | AR49: =AQ49-5 -> 52 | AS49: =AA49+AP49 -> 60 | AT49: =IFERROR(TODAY()-AA49,"") -> 45895 | BE49: =AA49+15 -> 15 | BF49: =IF(ISBLANK(AA49),0,IF(ISBLANK(BH49),(BE49-$L$1),(BH49-BE49))) -> 0 | BQ49: N | CA49: =IF(AY49="Y",BA49,"0") -> 0 | CB49: =AC49-CA49 -> -44901.944 | CC49: =BA49 -> 0 | CD49: =AC49-BA49 -> -44901.944 | CE49: =(0.3)*(CD49/AK49)+(0.7)*(CD49/AL49) -> #N/A | CF49: =IF(AA49="","0",$CF$1-AA49) -> 0 | CH49: =(0.3)*(($CF$1-W49)/AK49)+(0.7)*(($CF$1-W49)/AL49) -> #N/A | CI49: =CH49-CG49 -> #N/A | CJ49: =CF49/AP49 -> 0 | CK49: =IF(AA49>0,"",$CK$1-W49) -> 954.05625 | CL49: =IF(R49="NEW","REV","NON-REV") -> NON-REV | CM49: =IF(CK49="","",IF(CK49<91,"0-3 MONTHS",(IF(CK49<181,"4-6 MONTHS",(IF(CK49<271,"7-9 MONTHS",IF(CK49>270,"10 MONTHS AND ABOVE",))))))) -> 10 MONTHS AND ABOVE | CP49: =IF(CQ49,"NTC ISSUED","FOR ISSUANCE") -> FOR ISSUANCE | CS49: =IF(AND(CQ49=0,CR49=0), "0",IF(CR49,(CR49-CQ49),TODAY()-CQ49)) -> 0 | CW49: 'P2211141358', | CX49: =VLOOKUP(E49,'[1]List of Work Orders'!$A:$I,9,FALSE) -> ME155242 | DC49: =VLOOKUP(E49,'[2]List of Work Orders'!$A:$F,6,FALSE) -> SCHED | DS49: RONILO GANGE JR.
A50: 44938 | B50: N/A | D50: MN | E50: P2211141362 | F50: RTA MN - 415FIL - DT1-0050 - Replacement of rotten, hazardous and old standard pole | G50: ILAYA PUROK 7 ALABANG MUNTINLUPA | H50: MUNTINLUPA CITY | I50: PARAÑAQUE | J50: for crew survey; for C1 survey | K50: W/O ISSUE | L50: ECOM | M50: SCHED | N50: Ronilo Gange Jr. | O50: 51.0125 | P50: #N/A | Q50: 0 | R50: RTA | S50: 80899.28 | T50: 29912.66 | V50: =U50/T50 -> 0 | W50: 44901.944 | X50: 44937.597 | Y50: 44940 | AC50: =AA50-W50 -> -44901.944 | AD50: =AA50-X50 -> -44937.597 | AE50: =AB50-AA50 -> 0 | AF50: =W50+AO50 -> #N/A | AG50: =W50+AN50 -> #N/A | AH50: =W50+50 -> 44951.944 | AI50: =(0.3)*(AC50/AK50)+(0.7)*(AC50/AL50) -> #N/A | AJ50: =AE50/AP50 -> 0 | AK50: =IF(P50<51,20,(IF(P50<101,23,(IF(P50<201,26,IF(P50<301,28,IF(P50<401,30,(IF(P50<501,32,(IF(P50<1001,40,50))))))))))) -> #N/A | AL50: =IF(Q50<51,36,(IF(Q50<101,34,(IF(Q50<201,32,IF(Q50<301,30,IF(Q50<401,28,(IF(Q50<501,26,(IF(Q50<1001,23,20))))))))))) -> 36 | AM50: =(0.75)/((0.3/AK50)+(0.7/AL50)) -> #N/A | AN50: =(0.95)/((0.3/AK50)+(0.7/AL50)) -> #N/A | AO50: =AM50-3 -> #N/A | AP50: 60 | AQ50: =0.95*AP50 -> 57 | AR50: =AQ50-5 -> 52 | AS50: =AA50+AP50 -> 60 | AT50: =IFERROR(TODAY()-AA50,"") -> 45895 | BE50: =AA50+15 -> 15 | BF50: =IF(ISBLANK(AA50),0,IF(ISBLANK(BH50),(BE50-$L$1),(BH50-BE50))) -> 0 | BQ50: N | CA50: =IF(AY50="Y",BA50,"0") -> 0 | CB50: =AC50-CA50 -> -44901.944 | CC50: =BA50 -> 0 | CD50: =AC50-BA50 -> -44901.944 | CE50: =(0.3)*(CD50/AK50)+(0.7)*(CD50/AL50) -> #N/A | CF50: =IF(AA50="","0",$CF$1-AA50) -> 0 | CH50: =(0.3)*(($CF$1-W50)/AK50)+(0.7)*(($CF$1-W50)/AL50) -> #N/A | CI50: =CH50-CG50 -> #N/A | CJ50: =CF50/AP50 -> 0 | CK50: =IF(AA50>0,"",$CK$1-W50) -> 954.05556 | CL50: =IF(R50="NEW","REV","NON-REV") -> NON-REV | CM50: =IF(CK50="","",IF(CK50<91,"0-3 MONTHS",(IF(CK50<181,"4-6 MONTHS",(IF(CK50<271,"7-9 MONTHS",IF(CK50>270,"10 MONTHS AND ABOVE",))))))) -> 10 MONTHS AND ABOVE | CP50: =IF(CQ50,"NTC ISSUED","FOR ISSUANCE") -> FOR ISSUANCE | CS50: =IF(AND(CQ50=0,CR50=0), "0",IF(CR50,(CR50-CQ50),TODAY()-CQ50)) -> 0 | CW50: 'P2211141362', | CX50: =VLOOKUP(E50,'[1]List of Work Orders'!$A:$I,9,FALSE) -> ME155242 | DC50: =VLOOKUP(E50,'[2]List of Work Orders'!$A:$F,6,FALSE) -> SCHED | DS50: RONILO GANGE JR.
A51: 44938 | B51: N/A | D51: MN | E51: P2211141366 | F51: RTA MN - 425FIL - DT1-0140 - Replacement of rotten, hazardous and old standard pole | G51: NATIONAL ALABANG ALABANG MUNTINLUPA | H51: MUNTINLUPA CITY | I51: PARAÑAQUE | J51: contact person needed from BC; for checking w/ PnS | K51: W/O ISSUE | L51: AVECO | M51: SCHED | N51: Ronilo Gange Jr. | O51: 39.2801 | P51: #N/A | Q51: 0 | R51: RTA | S51: 69142.18 | T51: 30610.91 | V51: =U51/T51 -> 0 | W51: 44901.945 | X51: 44938 | Y51: 44939 | AC51: =AA51-W51 -> -44901.945 | AD51: =AA51-X51 -> -44938 | AE51: =AB51-AA51 -> 0 | AF51: =W51+AO51 -> #N/A | AG51: =W51+AN51 -> #N/A | AH51: =W51+50 -> 44951.945 | AI51: =(0.3)*(AC51/AK51)+(0.7)*(AC51/AL51) -> #N/A | AJ51: =AE51/AP51 -> 0 | AK51: =IF(P51<51,20,(IF(P51<101,23,(IF(P51<201,26,IF(P51<301,28,IF(P51<401,30,(IF(P51<501,32,(IF(P51<1001,40,50))))))))))) -> #N/A | AL51: =IF(Q51<51,36,(IF(Q51<101,34,(IF(Q51<201,32,IF(Q51<301,30,IF(Q51<401,28,(IF(Q51<501,26,(IF(Q51<1001,23,20))))))))))) -> 36 | AM51: =(0.75)/((0.3/AK51)+(0.7/AL51)) -> #N/A | AN51: =(0.95)/((0.3/AK51)+(0.7/AL51)) -> #N/A | AO51: =AM51-3 -> #N/A | AP51: 60 | AQ51: =0.95*AP51 -> 57 | AR51: =AQ51-5 -> 52 | AS51: =AA51+AP51 -> 60 | AT51: =IFERROR(TODAY()-AA51,"") -> 45895 | BE51: =AA51+15 -> 15 | BF51: =IF(ISBLANK(AA51),0,IF(ISBLANK(BH51),(BE51-$L$1),(BH51-BE51))) -> 0 | BQ51: N | CA51: =IF(AY51="Y",BA51,"0") -> 0 | CB51: =AC51-CA51 -> -44901.945 | CC51: =BA51 -> 0 | CD51: =AC51-BA51 -> -44901.945 | CE51: =(0.3)*(CD51/AK51)+(0.7)*(CD51/AL51) -> #N/A | CF51: =IF(AA51="","0",$CF$1-AA51) -> 0 | CH51: =(0.3)*(($CF$1-W51)/AK51)+(0.7)*(($CF$1-W51)/AL51) -> #N/A | CI51: =CH51-CG51 -> #N/A | CJ51: =CF51/AP51 -> 0 | CK51: =IF(AA51>0,"",$CK$1-W51) -> 954.05486 | CL51: =IF(R51="NEW","REV","NON-REV") -> NON-REV | CM51: =IF(CK51="","",IF(CK51<91,"0-3 MONTHS",(IF(CK51<181,"4-6 MONTHS",(IF(CK51<271,"7-9 MONTHS",IF(CK51>270,"10 MONTHS AND ABOVE",))))))) -> 10 MONTHS AND ABOVE | CP51: =IF(CQ51,"NTC ISSUED","FOR ISSUANCE") -> FOR ISSUANCE | CS51: =IF(AND(CQ51=0,CR51=0), "0",IF(CR51,(CR51-CQ51),TODAY()-CQ51)) -> 0 | CW51: 'P2211141366', | CX51: =VLOOKUP(E51,'[1]List of Work Orders'!$A:$I,9,FALSE) -> ME155242 | DC51: =VLOOKUP(E51,'[2]List of Work Orders'!$A:$F,6,FALSE) -> SCHED | DS51: RONILO GANGE JR.
A52: 44938 | B52: N/A | D52: MN | E52: P2211141368 | F52: RTA MN - 425FIL - DT1-0264 - Replacement of rotten, hazardous and old standard pole | G52: M. DOLLETON PUROK 1 BAYANAN MUNTINLUPA | H52: MUNTINLUPA CITY | I52: PARAÑAQUE | J52: for scheduling, drainage and waterline | K52: W/ ISSUE | L52: CHALLENGER | M52: SCHED | N52: Isan Carlo Lazaro | O52: 39.2801 | P52: #N/A | Q52: 0 | R52: RTA | S52: 69142.18 | T52: 30610.91 | V52: =U52/T52 -> 0 | W52: 44901.949 | X52: 44938 | Y52: 44940 | AC52: =AA52-W52 -> -44901.949 | AD52: =AA52-X52 -> -44938 | AE52: =AB52-AA52 -> 0 | AF52: =W52+AO52 -> #N/A | AG52: =W52+AN52 -> #N/A | AH52: =W52+50 -> 44951.949 | AI52: =(0.3)*(AC52/AK52)+(0.7)*(AC52/AL52) -> #N/A | AJ52: =AE52/AP52 -> 0 | AK52: =IF(P52<51,20,(IF(P52<101,23,(IF(P52<201,26,IF(P52<301,28,IF(P52<401,30,(IF(P52<501,32,(IF(P52<1001,40,50))))))))))) -> #N/A | AL52: =IF(Q52<51,36,(IF(Q52<101,34,(IF(Q52<201,32,IF(Q52<301,30,IF(Q52<401,28,(IF(Q52<501,26,(IF(Q52<1001,23,20))))))))))) -> 36 | AM52: =(0.75)/((0.3/AK52)+(0.7/AL52)) -> #N/A | AN52: =(0.95)/((0.3/AK52)+(0.7/AL52)) -> #N/A | AO52: =AM52-3 -> #N/A | AP52: 60 | AQ52: =0.95*AP52 -> 57 | AR52: =AQ52-5 -> 52 | AS52: =AA52+AP52 -> 60 | AT52: =IFERROR(TODAY()-AA52,"") -> 45895 | BE52: =AA52+15 -> 15 | BF52: =IF(ISBLANK(AA52),0,IF(ISBLANK(BH52),(BE52-$L$1),(BH52-BE52))) -> 0 | BQ52: N | CA52: =IF(AY52="Y",BA52,"0") -> 0 | CB52: =AC52-CA52 -> -44901.949 | CC52: =BA52 -> 0 | CD52: =AC52-BA52 -> -44901.949 | CE52: =(0.3)*(CD52/AK52)+(0.7)*(CD52/AL52) -> #N/A | CF52: =IF(AA52="","0",$CF$1-AA52) -> 0 | CH52: =(0.3)*(($CF$1-W52)/AK52)+(0.7)*(($CF$1-W52)/AL52) -> #N/A | CI52: =CH52-CG52 -> #N/A | CJ52: =CF52/AP52 -> 0 | CK52: =IF(AA52>0,"",$CK$1-W52) -> 954.05139 | CL52: =IF(R52="NEW","REV","NON-REV") -> NON-REV | CM52: =IF(CK52="","",IF(CK52<91,"0-3 MONTHS",(IF(CK52<181,"4-6 MONTHS",(IF(CK52<271,"7-9 MONTHS",IF(CK52>270,"10 MONTHS AND ABOVE",))))))) -> 10 MONTHS AND ABOVE | CP52: =IF(CQ52,"NTC ISSUED","FOR ISSUANCE") -> FOR ISSUANCE | CS52: =IF(AND(CQ52=0,CR52=0), "0",IF(CR52,(CR52-CQ52),TODAY()-CQ52)) -> 0 | CW52: 'P2211141368', | CX52: =VLOOKUP(E52,'[1]List of Work Orders'!$A:$I,9,FALSE) -> ME166067 | DC52: =VLOOKUP(E52,'[2]List of Work Orders'!$A:$F,6,FALSE) -> SCHED | DS52: Isan Carlo Lazaro
A53: 44938 | B53: N/A | D53: MN | E53: P2211141370 | F53: RTA MN - 425FIL - ALB1-1897 - Replacement of rotten, hazardous and old standard pole | G53: HERRERA JR. PUROK 1 BAYANAN MUNTINLUPA | H53: MUNTINLUPA CITY | I53: PARAÑAQUE | J53: for scheduling, check pole tag | K53: W/O ISSUE | L53: CHALLENGER | M53: SCHED | N53: Isan Carlo Lazaro | O53: 38.3841 | P53: #N/A | Q53: 0 | R53: RTA | S53: 68226.09 | T53: 29912.66 | V53: =U53/T53 -> 0 | W53: 44901.95 | X53: 44938 | Y53: 44940 | AC53: =AA53-W53 -> -44901.95 | AD53: =AA53-X53 -> -44938 | AE53: =AB53-AA53 -> 0 | AF53: =W53+AO53 -> #N/A | AG53: =W53+AN53 -> #N/A | AH53: =W53+50 -> 44951.95 | AI53: =(0.3)*(AC53/AK53)+(0.7)*(AC53/AL53) -> #N/A | AJ53: =AE53/AP53 -> 0 | AK53: =IF(P53<51,20,(IF(P53<101,23,(IF(P53<201,26,IF(P53<301,28,IF(P53<401,30,(IF(P53<501,32,(IF(P53<1001,40,50))))))))))) -> #N/A | AL53: =IF(Q53<51,36,(IF(Q53<101,34,(IF(Q53<201,32,IF(Q53<301,30,IF(Q53<401,28,(IF(Q53<501,26,(IF(Q53<1001,23,20))))))))))) -> 36 | AM53: =(0.75)/((0.3/AK53)+(0.7/AL53)) -> #N/A | AN53: =(0.95)/((0.3/AK53)+(0.7/AL53)) -> #N/A | AO53: =AM53-3 -> #N/A | AP53: 60 | AQ53: =0.95*AP53 -> 57 | AR53: =AQ53-5 -> 52 | AS53: =AA53+AP53 -> 60 | AT53: =IFERROR(TODAY()-AA53,"") -> 45895 | BE53: =AA53+15 -> 15 | BF53: =IF(ISBLANK(AA53),0,IF(ISBLANK(BH53),(BE53-$L$1),(BH53-BE53))) -> 0 | BQ53: N | CA53: =IF(AY53="Y",BA53,"0") -> 0 | CB53: =AC53-CA53 -> -44901.95 | CC53: =BA53 -> 0 | CD53: =AC53-BA53 -> -44901.95 | CE53: =(0.3)*(CD53/AK53)+(0.7)*(CD53/AL53) -> #N/A | CF53: =IF(AA53="","0",$CF$1-AA53) -> 0 | CH53: =(0.3)*(($CF$1-W53)/AK53)+(0.7)*(($CF$1-W53)/AL53) -> #N/A | CI53: =CH53-CG53 -> #N/A | CJ53: =CF53/AP53 -> 0 | CK53: =IF(AA53>0,"",$CK$1-W53) -> 954.05 | CL53: =IF(R53="NEW","REV","NON-REV") -> NON-REV | CM53: =IF(CK53="","",IF(CK53<91,"0-3 MONTHS",(IF(CK53<181,"4-6 MONTHS",(IF(CK53<271,"7-9 MONTHS",IF(CK53>270,"10 MONTHS AND ABOVE",))))))) -> 10 MONTHS AND ABOVE | CP53: =IF(CQ53,"NTC ISSUED","FOR ISSUANCE") -> FOR ISSUANCE | CS53: =IF(AND(CQ53=0,CR53=0), "0",IF(CR53,(CR53-CQ53),TODAY()-CQ53)) -> 0 | CW53: 'P2211141370', | CX53: =VLOOKUP(E53,'[1]List of Work Orders'!$A:$I,9,FALSE) -> ME166067 | DC53: =VLOOKUP(E53,'[2]List of Work Orders'!$A:$F,6,FALSE) -> SCHED | DS53: Isan Carlo Lazaro
A54: 44938 | B54: N/A | D54: MN | E54: P2211141364 | F54: RTA MN - 425FIL - DS1-0169 - Replacement of rotten, hazardous and old standard pole | G54: VIRGO PUROK 1 BAYANAN MUNTINLUPA | H54: MUNTINLUPA CITY | I54: PARAÑAQUE | J54: for scheduling | K54: W/O ISSUE | L54: CHALLENGER | M54: SCHED | N54: Isan Carlo Lazaro | O54: 39.2801 | P54: #N/A | Q54: 0 | R54: RTA | S54: 69095.41 | T54: 30610.91 | V54: =U54/T54 -> 0 | W54: 44903.963 | X54: 44938 | Y54: 44940 | AC54: =AA54-W54 -> -44903.963 | AD54: =AA54-X54 -> -44938 | AE54: =AB54-AA54 -> 0 | AF54: =W54+AO54 -> #N/A | AG54: =W54+AN54 -> #N/A | AH54: =W54+50 -> 44953.963 | AI54: =(0.3)*(AC54/AK54)+(0.7)*(AC54/AL54) -> #N/A | AJ54: =AE54/AP54 -> 0 | AK54: =IF(P54<51,20,(IF(P54<101,23,(IF(P54<201,26,IF(P54<301,28,IF(P54<401,30,(IF(P54<501,32,(IF(P54<1001,40,50))))))))))) -> #N/A | AL54: =IF(Q54<51,36,(IF(Q54<101,34,(IF(Q54<201,32,IF(Q54<301,30,IF(Q54<401,28,(IF(Q54<501,26,(IF(Q54<1001,23,20))))))))))) -> 36 | AM54: =(0.75)/((0.3/AK54)+(0.7/AL54)) -> #N/A | AN54: =(0.95)/((0.3/AK54)+(0.7/AL54)) -> #N/A | AO54: =AM54-3 -> #N/A | AP54: 60 | AQ54: =0.95*AP54 -> 57 | AR54: =AQ54-5 -> 52 | AS54: =AA54+AP54 -> 60 | AT54: =IFERROR(TODAY()-AA54,"") -> 45895 | BE54: =AA54+15 -> 15 | BF54: =IF(ISBLANK(AA54),0,IF(ISBLANK(BH54),(BE54-$L$1),(BH54-BE54))) -> 0 | BQ54: N | CA54: =IF(AY54="Y",BA54,"0") -> 0 | CB54: =AC54-CA54 -> -44903.963 | CC54: =BA54 -> 0 | CD54: =AC54-BA54 -> -44903.963 | CE54: =(0.3)*(CD54/AK54)+(0.7)*(CD54/AL54) -> #N/A | CF54: =IF(AA54="","0",$CF$1-AA54) -> 0 | CH54: =(0.3)*(($CF$1-W54)/AK54)+(0.7)*(($CF$1-W54)/AL54) -> #N/A | CI54: =CH54-CG54 -> #N/A | CJ54: =CF54/AP54 -> 0 | CK54: =IF(AA54>0,"",$CK$1-W54) -> 952.0375 | CL54: =IF(R54="NEW","REV","NON-REV") -> NON-REV | CM54: =IF(CK54="","",IF(CK54<91,"0-3 MONTHS",(IF(CK54<181,"4-6 MONTHS",(IF(CK54<271,"7-9 MONTHS",IF(CK54>270,"10 MONTHS AND ABOVE",))))))) -> 10 MONTHS AND ABOVE | CP54: =IF(CQ54,"NTC ISSUED","FOR ISSUANCE") -> FOR ISSUANCE | CS54: =IF(AND(CQ54=0,CR54=0), "0",IF(CR54,(CR54-CQ54),TODAY()-CQ54)) -> 0 | CW54: 'P2211141364', | CX54: =VLOOKUP(E54,'[1]List of Work Orders'!$A:$I,9,FALSE) -> ME166067 | DC54: =VLOOKUP(E54,'[2]List of Work Orders'!$A:$F,6,FALSE) -> SCHED | DS54: Isan Carlo Lazaro
A55: 44911 | B55: OK | D55: HMB | E55: R21956925 | F55: MACAGGA DANICA RUTH RABENA | G55: REYVILLE I SUBD, REYVILLE I SUBD, BACOOR | H55: BACOOR CITY | I55: DASMA | J55: current plan cannot be executed due to the lack of space for installing a down guy; contractor cannot execute; for digging on Feb. 21, 2023; w/ customer issue: FOR CANCELLATION | K55: W/ ISSUE | L55: ECOM | M55: PCAN4 | N55: Ronilo Gange Jr. | O55: 13.0041 | P55: #N/A | Q55: 0 | R55: RELOC | S55: 37045.87 | T55: 13135.2 | V55: =U55/T55 -> 0 | W55: 44904 | X55: 44909 | Y55: 44910 | AC55: =AA55-W55 -> -44904 | AD55: =AA55-X55 -> -44909 | AE55: =AB55-AA55 -> 0 | AF55: =W55+AO55 -> #N/A | AG55: =W55+AN55 -> #N/A | AH55: =W55+50 -> 44954 | AI55: =(0.3)*(AC55/AK55)+(0.7)*(AC55/AL55) -> #N/A | AJ55: =AE55/AP55 -> 0 | AK55: =IF(P55<51,20,(IF(P55<101,23,(IF(P55<201,26,IF(P55<301,28,IF(P55<401,30,(IF(P55<501,32,(IF(P55<1001,40,50))))))))))) -> #N/A | AL55: =IF(Q55<51,36,(IF(Q55<101,34,(IF(Q55<201,32,IF(Q55<301,30,IF(Q55<401,28,(IF(Q55<501,26,(IF(Q55<1001,23,20))))))))))) -> 36 | AM55: =(0.75)/((0.3/AK55)+(0.7/AL55)) -> #N/A | AN55: =(0.95)/((0.3/AK55)+(0.7/AL55)) -> #N/A | AO55: =AM55-3 -> #N/A | AP55: 60 | AQ55: =0.95*AP55 -> 57 | AR55: =AQ55-5 -> 52 | AS55: =AA55+AP55 -> 60 | AT55: =IFERROR(TODAY()-AA55,"") -> 45895 | BE55: =AA55+15 -> 15 | BF55: =IF(ISBLANK(AA55),0,IF(ISBLANK(BH55),(BE55-$L$1),(BH55-BE55))) -> 0 | BQ55: N | CA55: =IF(AY55="Y",BA55,"0") -> 0 | CB55: =AC55-CA55 -> -44904 | CC55: =BA55 -> 0 | CD55: =AC55-BA55 -> -44904 | CE55: =(0.3)*(CD55/AK55)+(0.7)*(CD55/AL55) -> #N/A | CF55: =IF(AA55="","0",$CF$1-AA55) -> 0 | CH55: =(0.3)*(($CF$1-W55)/AK55)+(0.7)*(($CF$1-W55)/AL55) -> #N/A | CI55: =CH55-CG55 -> #N/A | CJ55: =CF55/AP55 -> 0 | CK55: =IF(AA55>0,"",$CK$1-W55) -> 952 | CL55: =IF(R55="NEW","REV","NON-REV") -> NON-REV | CM55: =IF(CK55="","",IF(CK55<91,"0-3 MONTHS",(IF(CK55<181,"4-6 MONTHS",(IF(CK55<271,"7-9 MONTHS",IF(CK55>270,"10 MONTHS AND ABOVE",))))))) -> 10 MONTHS AND ABOVE | CP55: =IF(CQ55,"NTC ISSUED","FOR ISSUANCE") -> FOR ISSUANCE | CS55: =IF(AND(CQ55=0,CR55=0), "0",IF(CR55,(CR55-CQ55),TODAY()-CQ55)) -> 0 | CW55: 'R21956925', | CX55: =VLOOKUP(E55,'[1]List of Work Orders'!$A:$I,9,FALSE) -> ME155242 | DC55: =VLOOKUP(E55,'[2]List of Work Orders'!$A:$F,6,FALSE) -> PCAN4 | DS55: RONILO GANGE JR.
... A66: 44938 | B66: N/A | D66: MN | E66: P2211141377 | F66: RTA MN 425FIL - NPT (DR1-0242) Replacement of rotten, hazardous and old standard pole | G66: P. DIAZ POBLACION POBLACION MUNTINLUPA | H66: MUNTINLUPA CITY | I66: PARAÑAQUE | J66: contact person needed from BC; for checking w/ PnS | K66: W/O ISSUE | L66: AVECO | M66: SCHED | N66: Ronilo Gange Jr. | O66: 39.2801 | P66: #N/A | Q66: 0 | R66: RTA | S66: 69101.47 | T66: 30610.91 | V66: =U66/T66 -> 0 | W66: 44906.977 | X66: 44938 | Y66: 44939 | AC66: =AA66-W66 -> -44906.977 | AD66: =AA66-X66 -> -44938 | AE66: =AB66-AA66 -> 0 | AF66: =W66+AO66 -> #N/A | AG66: =W66+AN66 -> #N/A | AH66: =W66+50 -> 44956.977 | AI66: =(0.3)*(AC66/AK66)+(0.7)*(AC66/AL66) -> #N/A | AJ66: =AE66/AP66 -> 0 | AK66: =IF(P66<51,20,(IF(P66<101,23,(IF(P66<201,26,IF(P66<301,28,IF(P66<401,30,(IF(P66<501,32,(IF(P66<1001,40,50))))))))))) -> #N/A | AL66: =IF(Q66<51,36,(IF(Q66<101,34,(IF(Q66<201,32,IF(Q66<301,30,IF(Q66<401,28,(IF(Q66<501,26,(IF(Q66<1001,23,20))))))))))) -> 36 | AM66: =(0.75)/((0.3/AK66)+(0.7/AL66)) -> #N/A | AN66: =(0.95)/((0.3/AK66)+(0.7/AL66)) -> #N/A | AO66: =AM66-3 -> #N/A | AP66: 60 | AQ66: =0.95*AP66 -> 57 | AR66: =AQ66-5 -> 52 | AS66: =AA66+AP66 -> 60 | AT66: =IFERROR(TODAY()-AA66,"") -> 45895 | BE66: =AA66+15 -> 15 | BF66: =IF(ISBLANK(AA66),0,IF(ISBLANK(BH66),(BE66-$L$1),(BH66-BE66))) -> 0 | BQ66: N | CA66: =IF(AY66="Y",BA66,"0") -> 0 | CB66: =AC66-CA66 -> -44906.977 | CC66: =BA66 -> 0 | CD66: =AC66-BA66 -> -44906.977 | CE66: =(0.3)*(CD66/AK66)+(0.7)*(CD66/AL66) -> #N/A | CF66: =IF(AA66="","0",$CF$1-AA66) -> 0 | CH66: =(0.3)*(($CF$1-W66)/AK66)+(0.7)*(($CF$1-W66)/AL66) -> #N/A | CI66: =CH66-CG66 -> #N/A | CJ66: =CF66/AP66 -> 0 | CK66: =IF(AA66>0,"",$CK$1-W66) -> 949.02292 | CL66: =IF(R66="NEW","REV","NON-REV") -> NON-REV | CM66: =IF(CK66="","",IF(CK66<91,"0-3 MONTHS",(IF(CK66<181,"4-6 MONTHS",(IF(CK66<271,"7-9 MONTHS",IF(CK66>270,"10 MONTHS AND ABOVE",))))))) -> 10 MONTHS AND ABOVE | CP66: =IF(CQ66,"NTC ISSUED","FOR ISSUANCE") -> FOR ISSUANCE | CS66: =IF(AND(CQ66=0,CR66=0), "0",IF(CR66,(CR66-CQ66),TODAY()-CQ66)) -> 0 | CW66: 'P2211141377', | CX66: =VLOOKUP(E66,'[1]List of Work Orders'!$A:$I,9,FALSE) -> ME155242 | DC66: =VLOOKUP(E66,'[2]List of Work Orders'!$A:$F,6,FALSE) -> SCHED | DS66: RONILO GANGE JR.
A67: 44929 | B67: 44922 | D67: BIZ | E67: X22125127907 | F67: MEGAWIDE CONSTRUCTION CORPORATION | G67: ALABANG-ZAPOTE, PAMPLONA I, LAS PINAS CITY | H67: LAS PIÑAS CITY | I67: PARAÑAQUE | J67: for execution on March 7, 2023; for execution on March 30, 2023; for execution on April 28, 2023 | K67: W/O ISSUE | L67: AVECO | M67: PCAN | N67: Ronilo Gange Jr. | O67: 112.4467 | P67: #N/A | Q67: 0 | R67: TERMINATION | S67: 139047.8 | T67: 104815.37 | V67: =U67/T67 -> 0 | W67: 44916.529 | X67: 44924 | Y67: 44922 | AC67: =AA67-W67 -> -44916.529 | AD67: =AA67-X67 -> -44924 | AE67: =AB67-AA67 -> 0 | AF67: =W67+AO67 -> #N/A | AG67: =W67+AN67 -> #N/A | AH67: =W67+50 -> 44966.529 | AI67: =(0.3)*(AC67/AK67)+(0.7)*(AC67/AL67) -> #N/A | AJ67: =AE67/AP67 -> 0 | AK67: =IF(P67<51,20,(IF(P67<101,23,(IF(P67<201,26,IF(P67<301,28,IF(P67<401,30,(IF(P67<501,32,(IF(P67<1001,40,50))))))))))) -> #N/A | AL67: =IF(Q67<51,36,(IF(Q67<101,34,(IF(Q67<201,32,IF(Q67<301,30,IF(Q67<401,28,(IF(Q67<501,26,(IF(Q67<1001,23,20))))))))))) -> 36 | AM67: =(0.75)/((0.3/AK67)+(0.7/AL67)) -> #N/A | AN67: =(0.95)/((0.3/AK67)+(0.7/AL67)) -> #N/A | AO67: =AM67-3 -> #N/A | AP67: 60 | AQ67: =0.95*AP67 -> 57 | AR67: =AQ67-5 -> 52 | AS67: =AA67+AP67 -> 60 | AT67: =IFERROR(TODAY()-AA67,"") -> 45895 | BE67: =AA67+15 -> 15 | BF67: =IF(ISBLANK(AA67),0,IF(ISBLANK(BH67),(BE67-$L$1),(BH67-BE67))) -> 0 | BQ67: Y | BZ67: CX7-5836, CX7-5837, 171617 | CA67: =IF(AY67="Y",BA67,"0") -> 0 | CB67: =AC67-CA67 -> -44916.529 | CC67: =BA67 -> 0 | CD67: =AC67-BA67 -> -44916.529 | CE67: =(0.3)*(CD67/AK67)+(0.7)*(CD67/AL67) -> #N/A | CF67: =IF(AA67="","0",$CF$1-AA67) -> 0 | CH67: =(0.3)*(($CF$1-W67)/AK67)+(0.7)*(($CF$1-W67)/AL67) -> #N/A | CI67: =CH67-CG67 -> #N/A | CJ67: =CF67/AP67 -> 0 | CK67: =IF(AA67>0,"",$CK$1-W67) -> 939.47083 | CL67: =IF(R67="NEW","REV","NON-REV") -> NON-REV | CM67: =IF(CK67="","",IF(CK67<91,"0-3 MONTHS",(IF(CK67<181,"4-6 MONTHS",(IF(CK67<271,"7-9 MONTHS",IF(CK67>270,"10 MONTHS AND ABOVE",))))))) -> 10 MONTHS AND ABOVE | CP67: =IF(CQ67,"NTC ISSUED","FOR ISSUANCE") -> FOR ISSUANCE | CS67: =IF(AND(CQ67=0,CR67=0), "0",IF(CR67,(CR67-CQ67),TODAY()-CQ67)) -> 0 | CW67: 'X22125127907', | CX67: =VLOOKUP(E67,'[1]List of Work Orders'!$A:$I,9,FALSE) -> ME155242 | DC67: =VLOOKUP(E67,'[2]List of Work Orders'!$A:$F,6,FALSE) -> PCAN | DS67: RONILO GANGE JR.
A68: 44972 | B68: N/A | D68: MN | E68: P2301143548 | F68: PQUE 43WU Loadsplit [035817|WA359894|CW9-0271|Install 1-75kVA DT on pole CW9-0211 W/POLE | G68: ADELITA CHIOCO BF HOMES BF HOMES PARANAQUE | H68: PARAÑAQUE CITY | I68: PARAÑAQUE | J68: with customer opposition sa bunot tayong poste 0419 | K68: W/ ISSUE | L68: OPS | M68: INPRG | N68: Dean Carl Borjal | O68: 84.0239 | P68: #N/A | Q68: 0 | R68: OLDT | S68: 310484.15 | T68: 76106.73 | V68: =U68/T68 -> 0 | W68: 44958.423 | X68: 44972.517 | Y68: 44960 | AC68: =AA68-W68 -> -44958.423 | AD68: =AA68-X68 -> -44972.517 | AE68: =AB68-AA68 -> 0 | AF68: =W68+AO68 -> #N/A | AG68: =W68+AN68 -> #N/A | AH68: =W68+50 -> 45008.423 | AI68: =(0.3)*(AC68/AK68)+(0.7)*(AC68/AL68) -> #N/A | AJ68: =AE68/AP68 -> 0 | AK68: =IF(P68<51,20,(IF(P68<101,23,(IF(P68<201,26,IF(P68<301,28,IF(P68<401,30,(IF(P68<501,32,(IF(P68<1001,40,50))))))))))) -> #N/A | AL68: =IF(Q68<51,36,(IF(Q68<101,34,(IF(Q68<201,32,IF(Q68<301,30,IF(Q68<401,28,(IF(Q68<501,26,(IF(Q68<1001,23,20))))))))))) -> 36 | AM68: =(0.75)/((0.3/AK68)+(0.7/AL68)) -> #N/A | AN68: =(0.95)/((0.3/AK68)+(0.7/AL68)) -> #N/A | AO68: =AM68-3 -> #N/A | AP68: 60 | AQ68: =0.95*AP68 -> 57 | AR68: =AQ68-5 -> 52 | AS68: =AA68+AP68 -> 60 | AT68: =IFERROR(TODAY()-AA68,"") -> 45895 | BE68: =AA68+15 -> 15 | BF68: =IF(ISBLANK(AA68),0,IF(ISBLANK(BH68),(BE68-$L$1),(BH68-BE68))) -> 0 | BQ68: N | BS68: Load-splitting | BT68: TLN 035817 | BU68: Y | BV68: For schedule | BZ68: CW9-0211, 035817 | CA68: =IF(AY68="Y",BA68,"0") -> 0 | CB68: =AC68-CA68 -> -44958.423 | CC68: =BA68 -> 0 | CD68: =AC68-BA68 -> -44958.423 | CE68: =(0.3)*(CD68/AK68)+(0.7)*(CD68/AL68) -> #N/A | CF68: =IF(AA68="","0",$CF$1-AA68) -> 0 | CH68: =(0.3)*(($CF$1-W68)/AK68)+(0.7)*(($CF$1-W68)/AL68) -> #N/A | CI68: =CH68-CG68 -> #N/A | CJ68: =CF68/AP68 -> 0 | CK68: =IF(AA68>0,"",$CK$1-W68) -> 897.57708 | CL68: =IF(R68="NEW","REV","NON-REV") -> NON-REV | CM68: =IF(CK68="","",IF(CK68<91,"0-3 MONTHS",(IF(CK68<181,"4-6 MONTHS",(IF(CK68<271,"7-9 MONTHS",IF(CK68>270,"10 MONTHS AND ABOVE",))))))) -> 10 MONTHS AND ABOVE | CP68: =IF(CQ68,"NTC ISSUED","FOR ISSUANCE") -> FOR ISSUANCE | CS68: =IF(AND(CQ68=0,CR68=0), "0",IF(CR68,(CR68-CQ68),TODAY()-CQ68)) -> 0 | CW68: 'P2301143548', | CX68: =VLOOKUP(E68,'[1]List of Work Orders'!$A:$I,9,FALSE) -> ME168443 | DC68: =VLOOKUP(E68,'[2]List of Work Orders'!$A:$F,6,FALSE) -> INPRG | DS68: DCB
A69: 44972 | B69: N/A | D69: MN | E69: P2301143554 | F69: PQUE 415FIL Loadsplit [419127|WA196183|DT2-2061|Install additional 1-50kVA DT on pole DT2-2060 | G69: 3RD L & B CPD 2 ALABANG MUNTINLUPA | H69: MUNTINLUPA CITY | I69: PARAÑAQUE | J69: with execution issue; accessibility; for survey c/o C1 | K69: W/ ISSUE | L69: AVECO | M69: TECO | N69: Dean Carl Borjal | O69: 45.82 | P69: 45.82 | Q69: 0 | R69: OLDT | S69: 161415.96 | T69: 10396.61 | V69: =U69/T69 -> 0 | W69: 44958.424 | X69: 44972.517 | Y69: 44963 | AA69: 45672 | AB69: 45808.713 | AC69: =AA69-W69 -> 713.57569 | AD69: =AA69-X69 -> 699.48264 | AE69: =AB69-AA69 -> 136.7125 | AF69: =W69+AO69 -> 44977.198 | AG69: =W69+AN69 -> 44986.005 | AH69: =W69+50 -> 45008.424 | AI69: =(0.3)*(AC69/AK69)+(0.7)*(AC69/AL69) -> 24.578718 | AJ69: =AE69/AP69 -> 2.2785417 | AK69: =IF(P69<51,20,(IF(P69<101,23,(IF(P69<201,26,IF(P69<301,28,IF(P69<401,30,(IF(P69<501,32,(IF(P69<1001,40,50))))))))))) -> 20 | AL69: =IF(Q69<51,36,(IF(Q69<101,34,(IF(Q69<201,32,IF(Q69<301,30,IF(Q69<401,28,(IF(Q69<501,26,(IF(Q69<1001,23,20))))))))))) -> 36 | AM69: =(0.75)/((0.3/AK69)+(0.7/AL69)) -> 21.774194 | AN69: =(0.95)/((0.3/AK69)+(0.7/AL69)) -> 27.580645 | AO69: =AM69-3 -> 18.774194 | AP69: 60 | AQ69: =0.95*AP69 -> 57 | AR69: =AQ69-5 -> 52 | AS69: =AA69+AP69 -> 45732 | AT69: =IFERROR(TODAY()-AA69,"") -> 223 | BC69: PAID | BD69: NO COC | BE69: =AA69+15 -> 45687 | BF69: =IF(ISBLANK(AA69),0,IF(ISBLANK(BH69),(BE69-$L$1),(BH69-BE69))) -> #VALUE! | BQ69: N | BS69: Load-splitting | BT69: TLN 419127 | BU69: N | BV69: For schedule | BZ69: DT2-2060, 419127 | CA69: =IF(AY69="Y",BA69,"0") -> 0 | CB69: =AC69-CA69 -> 713.57569 | CC69: =BA69 -> 0 | CD69: =AC69-BA69 -> 713.57569 | CE69: =(0.3)*(CD69/AK69)+(0.7)*(CD69/AL69) -> 24.578718 | CF69: =IF(AA69="","0",$CF$1-AA69) -> 197 | CH69: =(0.3)*(($CF$1-W69)/AK69)+(0.7)*(($CF$1-W69)/AL69) -> 31.364274 | CI69: =CH69-CG69 -> 31.364274 | CJ69: =CF69/AP69 -> 3.2833333 | CK69: =IF(AA69>0,"",$CK$1-W69) | CL69: =IF(R69="NEW","REV","NON-REV") -> NON-REV | CM69: =IF(CK69="","",IF(CK69<91,"0-3 MONTHS",(IF(CK69<181,"4-6 MONTHS",(IF(CK69<271,"7-9 MONTHS",IF(CK69>270,"10 MONTHS AND ABOVE",))))))) | CP69: =IF(CQ69,"NTC ISSUED","FOR ISSUANCE") -> FOR ISSUANCE | CS69: =IF(AND(CQ69=0,CR69=0), "0",IF(CR69,(CR69-CQ69),TODAY()-CQ69)) -> 0 | CW69: 'P2301143554', | CX69: =VLOOKUP(E69,'[1]List of Work Orders'!$A:$I,9,FALSE) -> ME168443 | DC69: =VLOOKUP(E69,'[2]List of Work Orders'!$A:$F,6,FALSE) -> FCOMP | DS69: RONILO GANGE JR.
A70: 45000 | B70: OK | C70: Y | D70: CBG | E70: R21631694 | F70: CAVITEX INFRASTRUCTURE CORP., | G70: KAINGIN, STO. NIÑO, PARAÑAQUE | H70: PARAÑAQUE CITY | I70: PARAÑAQUE | J70: ongoing (03-16-23); c/o MPTS | K70: W/ ISSUE | L70: ECOM | M70: INPRG | N70: Ronilo Gange Jr. | O70: 1059.1652 | P70: 1865.53 | Q70: 0 | R70: RELOC | S70: 3525946.4 | T70: 1241706 | V70: =U70/T70 -> 0 | W70: 44992 | X70: 44993 | Y70: 44999 | AC70: =AA70-W70 -> -44992 | AD70: =AA70-X70 -> -44993 | AE70: =AB70-AA70 -> 0 | AF70: =W70+AO70 -> 45018.476 | AG70: =W70+AN70 -> 45029.336 | AH70: =W70+50 -> 45042 | AI70: =(0.3)*(AC70/AK70)+(0.7)*(AC70/AL70) -> -1144.7964 | AJ70: =AE70/AP70 -> 0 | AK70: =IF(P70<51,20,(IF(P70<101,23,(IF(P70<201,26,IF(P70<301,28,IF(P70<401,30,(IF(P70<501,32,(IF(P70<1001,40,50))))))))))) -> 50 | AL70: =IF(Q70<51,36,(IF(Q70<101,34,(IF(Q70<201,32,IF(Q70<301,30,IF(Q70<401,28,(IF(Q70<501,26,(IF(Q70<1001,23,20))))))))))) -> 36 | AM70: =(0.75)/((0.3/AK70)+(0.7/AL70)) -> 29.475983 | AN70: =(0.95)/((0.3/AK70)+(0.7/AL70)) -> 37.336245 | AO70: =AM70-3 -> 26.475983 | AP70: 60 | AQ70: =0.95*AP70 -> 57 | AR70: =AQ70-5 -> 52 | AS70: =AA70+AP70 -> 60 | AT70: =IFERROR(TODAY()-AA70,"") -> 45895 | BE70: =AA70+15 -> 15 | BF70: =IF(ISBLANK(AA70),0,IF(ISBLANK(BH70),(BE70-$L$1),(BH70-BE70))) -> 0 | BX70: PDZC | CA70: =IF(AY70="Y",BA70,"0") -> 0 | CB70: =AC70-CA70 -> -44992 | CC70: =BA70 -> 0 | CD70: =AC70-BA70 -> -44992 | CE70: =(0.3)*(CD70/AK70)+(0.7)*(CD70/AL70) -> -1144.7964 | CF70: =IF(AA70="","0",$CF$1-AA70) -> 0 | CH70: =(0.3)*(($CF$1-W70)/AK70)+(0.7)*(($CF$1-W70)/AL70) -> 22.314778 | CI70: =CH70-CG70 -> 22.314778 | CJ70: =CF70/AP70 -> 0 | CK70: =IF(AA70>0,"",$CK$1-W70) -> 864 | CL70: =IF(R70="NEW","REV","NON-REV") -> NON-REV | CM70: =IF(CK70="","",IF(CK70<91,"0-3 MONTHS",(IF(CK70<181,"4-6 MONTHS",(IF(CK70<271,"7-9 MONTHS",IF(CK70>270,"10 MONTHS AND ABOVE",))))))) -> 10 MONTHS AND ABOVE | CP70: =IF(CQ70,"NTC ISSUED","FOR ISSUANCE") -> FOR ISSUANCE | CS70: =IF(AND(CQ70=0,CR70=0), "0",IF(CR70,(CR70-CQ70),TODAY()-CQ70)) -> 0 | CW70: 'R21631694', | CX70: =VLOOKUP(E70,'[1]List of Work Orders'!$A:$I,9,FALSE) -> ME155242 | DC70: =VLOOKUP(E70,'[2]List of Work Orders'!$A:$F,6,FALSE) -> INPRG | DS70: RONILO GANGE JR.
A71: 45027 | B71: 45020 | D71: CBG | E71: R22344695 | F71: ALVEO LAND CORPORATION | G71: MADRIGAL BUSINESS PARK, ALABANG, MUNTINLUPA | H71: MUNTINLUPA CITY | I71: PARAÑAQUE | J71: for PAI and for schedule after Dapulang Project | K71: W/O ISSUE | L71: ECOM | M71: FCOMP | N71: Ronilo Gange Jr. | O71: 205.7057 | P71: 656.97 | Q71: 0 | R71: RELOC | S71: 4408402.5 | T71: 328357.79 | V71: =U71/T71 -> 0 | W71: 45012 | X71: 45020.594 | Y71: 45028 | AA71: 45685 | AC71: =AA71-W71 -> 673 | AD71: =AA71-X71 -> 664.40556 | AE71: =AB71-AA71 -> -45685 | AF71: =W71+AO71 -> 45036.835 | AG71: =W71+AN71 -> 45047.258 | AH71: =W71+50 -> 45062 | AI71: =(0.3)*(AC71/AK71)+(0.7)*(AC71/AL71) -> 18.133611 | AJ71: =AE71/AP71 -> -761.41667 | AK71: =IF(P71<51,20,(IF(P71<101,23,(IF(P71<201,26,IF(P71<301,28,IF(P71<401,30,(IF(P71<501,32,(IF(P71<1001,40,50))))))))))) -> 40 | AL71: =IF(Q71<51,36,(IF(Q71<101,34,(IF(Q71<201,32,IF(Q71<301,30,IF(Q71<401,28,(IF(Q71<501,26,(IF(Q71<1001,23,20))))))))))) -> 36 | AM71: =(0.75)/((0.3/AK71)+(0.7/AL71)) -> 27.835052 | AN71: =(0.95)/((0.3/AK71)+(0.7/AL71)) -> 35.257732 | AO71: =AM71-3 -> 24.835052 | AP71: 60 | AQ71: =0.95*AP71 -> 57 | AR71: =AQ71-5 -> 52 | AS71: =AA71+AP71 -> 45745 | AT71: =IFERROR(TODAY()-AA71,"") -> 210 | BC71: FOR AUDIT | BE71: =AA71+15 -> 45700 | BF71: =IF(ISBLANK(AA71),0,IF(ISBLANK(BH71),(BE71-$L$1),(BH71-BE71))) -> #VALUE! | BG71: 45743 | BQ71: N | BY71: 45027 | BZ71: CU9-5930, CU9-5931, CU9-5932, CU9-8002, CU9-8003, CU9-1748 | CA71: =IF(AY71="Y",BA71,"0") -> 0 | CB71: =AC71-CA71 -> 673 | CC71: =BA71 -> 0 | CD71: =AC71-BA71 -> 673 | CE71: =(0.3)*(CD71/AK71)+(0.7)*(CD71/AL71) -> 18.133611 | CF71: =IF(AA71="","0",$CF$1-AA71) -> 184 | CH71: =(0.3)*(($CF$1-W71)/AK71)+(0.7)*(($CF$1-W71)/AL71) -> 23.091389 | CI71: =CH71-CG71 -> 23.091389 | CJ71: =CF71/AP71 -> 3.0666667 | CK71: =IF(AA71>0,"",$CK$1-W71) | CL71: =IF(R71="NEW","REV","NON-REV") -> NON-REV | CM71: =IF(CK71="","",IF(CK71<91,"0-3 MONTHS",(IF(CK71<181,"4-6 MONTHS",(IF(CK71<271,"7-9 MONTHS",IF(CK71>270,"10 MONTHS AND ABOVE",))))))) | CP71: =IF(CQ71,"NTC ISSUED","FOR ISSUANCE") -> FOR ISSUANCE | CS71: =IF(AND(CQ71=0,CR71=0), "0",IF(CR71,(CR71-CQ71),TODAY()-CQ71)) -> 0 | CW71: 'R22344695', | CX71: =VLOOKUP(E71,'[1]List of Work Orders'!$A:$I,9,FALSE) -> ME155242 | DC71: =VLOOKUP(E71,'[2]List of Work Orders'!$A:$F,6,FALSE) -> FCOMP | DS71: Erika Mae Orlina
D72: HMB | E72: X22104175107 | F72: MARK KENNETH VITUG FLORES | G72: MAPLE DRIVE, MENLO PARK, PARANAQUE | H72: PARAÑAQUE CITY | I72: PARAÑAQUE | L72: AVECO | M72: PCAN3 | N72: Ronilo Gange Jr. | O72: 260.1375 | P72: #N/A | Q72: 48 | R72: NEW | S72: 262732.62 | T72: 1235620.5 | V72: =U72/T72 -> 0 | W72: 45019.727 | X72: 45021.62 | AC72: =AA72-W72 -> -45019.727 | AD72: 0 | AE72: 0 | AF72: 45767.971 | AG72: 45777.197 | AH72: 45797.626 | AI72: =(0.3)*(AC72/AK72)+(0.7)*(AC72/AL72) -> #N/A | AJ72: 0 | AK72: =IF(P72<51,20,(IF(P72<101,23,(IF(P72<201,26,IF(P72<301,28,IF(P72<401,30,(IF(P72<501,32,(IF(P72<1001,40,50))))))))))) -> #N/A | AL72: =IF(Q72<51,36,(IF(Q72<101,34,(IF(Q72<201,32,IF(Q72<301,30,IF(Q72<401,28,(IF(Q72<501,26,(IF(Q72<1001,23,20))))))))))) -> 36 | AM72: =(0.75)/((0.3/AK72)+(0.7/AL72)) -> #N/A | AN72: =(0.95)/((0.3/AK72)+(0.7/AL72)) -> #N/A | AO72: =AM72-3 -> #N/A | AP72: 60 | AQ72: =0.95*AP72 -> 57 | AR72: =AQ72-5 -> 52 | AS72: =AA72+AP72 -> 60 | AT72: =IFERROR(TODAY()-AA72,"") -> 45895 | BE72: =AA72+15 -> 15 | BF72: =IF(ISBLANK(AA72),0,IF(ISBLANK(BH72),(BE72-$L$1),(BH72-BE72))) -> 0 | CA72: =IF(AY72="Y",BA72,"0") -> 0 | CB72: =AC72-CA72 -> -45019.727 | CC72: =BA72 -> 0 | CD72: =AC72-BA72 -> -45019.727 | CE72: =(0.3)*(CD72/AK72)+(0.7)*(CD72/AL72) -> #N/A | CF72: =IF(AA72="","0",$CF$1-AA72) -> 0 | CH72: =(0.3)*(($CF$1-W72)/AK72)+(0.7)*(($CF$1-W72)/AL72) -> #N/A | CI72: =CH72-CG72 -> #N/A | CJ72: =CF72/AP72 -> 0 | CK72: =IF(AA72>0,"",$CK$1-W72) -> 836.27292 | CL72: =IF(R72="NEW","REV","NON-REV") -> REV | CM72: =IF(CK72="","",IF(CK72<91,"0-3 MONTHS",(IF(CK72<181,"4-6 MONTHS",(IF(CK72<271,"7-9 MONTHS",IF(CK72>270,"10 MONTHS AND ABOVE",))))))) -> 10 MONTHS AND ABOVE | CP72: =IF(CQ72,"NTC ISSUED","FOR ISSUANCE") -> FOR ISSUANCE | CS72: =IF(AND(CQ72=0,CR72=0), "0",IF(CR72,(CR72-CQ72),TODAY()-CQ72)) -> 0 | DC72: =VLOOKUP(E72,'[2]List of Work Orders'!$A:$F,6,FALSE) -> #N/A | DS72: Jenneth Madrid
A73: 45050 | B73: 45050 | D73: HMB | E73: X22104473949 | F73: CELEDONIA C. UTANES | G73: KYOTO COR JERUSALEM ST., BF HOMES, PARAÑAQUE | H73: PARAÑAQUE CITY | I73: PARAÑAQUE | J73: Digging Prob. | K73: W/ ISSUE | L73: POWERHOUSE | M73: SCHED | N73: Isan Carlo Lazaro | O73: 64.7485 | P73: 243.45 | Q73: 80 | R73: MODIFICATION | S73: 495372.18 | T73: 67653.48 | V73: =U73/T73 -> 0 | W73: 45043 | X73: 45049 | Y73: 45049 | AC73: =AA73-W73 -> -45043 | AD73: =AA73-X73 -> -45049 | AE73: =AB73-AA73 -> 0 | AF73: =W73+AO73 -> 45063.96 | AG73: =W73+AN73 -> 45073.349 | AH73: =W73+50 -> 45093 | AI73: =(0.3)*(AC73/AK73)+(0.7)*(AC73/AL73) -> -1409.9595 | AJ73: =AE73/AP73 -> 0 | AK73: =IF(P73<51,20,(IF(P73<101,23,(IF(P73<201,26,IF(P73<301,28,IF(P73<401,30,(IF(P73<501,32,(IF(P73<1001,40,50))))))))))) -> 28 | AL73: =IF(Q73<51,36,(IF(Q73<101,34,(IF(Q73<201,32,IF(Q73<301,30,IF(Q73<401,28,(IF(Q73<501,26,(IF(Q73<1001,23,20))))))))))) -> 34 | AM73: =(0.75)/((0.3/AK73)+(0.7/AL73)) -> 23.959732 | AN73: =(0.95)/((0.3/AK73)+(0.7/AL73)) -> 30.348993 | AO73: =AM73-3 -> 20.959732 | AP73: 60 | AQ73: =0.95*AP73 -> 57 | AR73: =AQ73-5 -> 52 | AS73: =AA73+AP73 -> 60 | AT73: =IFERROR(TODAY()-AA73,"") -> 45895 | BE73: =AA73+15 -> 15 | BF73: =IF(ISBLANK(AA73),0,IF(ISBLANK(BH73),(BE73-$L$1),(BH73-BE73))) -> 0 | BQ73: Y | BY73: 45052 | BZ73: CX8-0460, CX8-8074, CX8-0459, 514959, CX8-0547, CX8-8075 | CA73: =IF(AY73="Y",BA73,"0") -> 0 | CB73: =AC73-CA73 -> -45043 | CC73: =BA73 -> 0 | CD73: =AC73-BA73 -> -45043 | CE73: =(0.3)*(CD73/AK73)+(0.7)*(CD73/AL73) -> -1409.9595 | CF73: =IF(AA73="","0",$CF$1-AA73) -> 0 | CH73: =(0.3)*(($CF$1-W73)/AK73)+(0.7)*(($CF$1-W73)/AL73) -> 25.855882 | CI73: =CH73-CG73 -> 25.855882 | CJ73: =CF73/AP73 -> 0 | CK73: =IF(AA73>0,"",$CK$1-W73) -> 813 | CL73: =IF(R73="NEW","REV","NON-REV") -> NON-REV | CM73: =IF(CK73="","",IF(CK73<91,"0-3 MONTHS",(IF(CK73<181,"4-6 MONTHS",(IF(CK73<271,"7-9 MONTHS",IF(CK73>270,"10 MONTHS AND ABOVE",))))))) -> 10 MONTHS AND ABOVE | CP73: =IF(CQ73,"NTC ISSUED","FOR ISSUANCE") -> FOR ISSUANCE | CS73: =IF(AND(CQ73=0,CR73=0), "0",IF(CR73,(CR73-CQ73),TODAY()-CQ73)) -> 0 | CW73: 'X22104473949', | CX73: =VLOOKUP(E73,'[1]List of Work Orders'!$A:$I,9,FALSE) -> ME185284 | DC73: =VLOOKUP(E73,'[2]List of Work Orders'!$A:$F,6,FALSE) -> SCHED | DS73: RONILO GANGE JR.
A74: 45154 | B74: 45152 | D74: CBG | E74: X23072866920 | F74: GLOBE TELECOM, INC. | G74: STA. INES, SAN ANTONIO VALLEY 6, PARANAQUE | H74: PARAÑAQUE CITY | I74: PARAÑAQUE | J74: As per contractor, nakausap nila yung HOA, may i-sesettle pa daw si Globe sakanila. Bukod po dito, nakausap din ng contractor yung tapat ng pagtatayuan ng poste, ayaw rin nito pumayag. 3/16/24 - Already installed pole on 3/13/24, installed DT on 3/15/24; Pending energization of Globe due to issue with HOA | K74: W/ ISSUE | L74: ECOM | M74: PCAN | N74: Ronilo Gange Jr. | O74: 59.1616 | P74: #N/A | Q74: 23 | R74: MODIFICATION | S74: 363942.06 | T74: 71262.06 | V74: =U74/T74 -> 0 | W74: 45148.444 | X74: 45153 | Y74: 45150 | AC74: =AA74-W74 -> -45148.444 | AD74: =AA74-X74 -> -45153 | AE74: =AB74-AA74 -> 0 | AF74: =W74+AO74 -> #N/A | AG74: =W74+AN74 -> #N/A | AH74: =W74+50 -> 45198.444 | AI74: =(0.3)*(AC74/AK74)+(0.7)*(AC74/AL74) -> #N/A | AJ74: =AE74/AP74 -> 0 | AK74: =IF(P74<51,20,(IF(P74<101,23,(IF(P74<201,26,IF(P74<301,28,IF(P74<401,30,(IF(P74<501,32,(IF(P74<1001,40,50))))))))))) -> #N/A | AL74: =IF(Q74<51,36,(IF(Q74<101,34,(IF(Q74<201,32,IF(Q74<301,30,IF(Q74<401,28,(IF(Q74<501,26,(IF(Q74<1001,23,20))))))))))) -> 36 | AM74: =(0.75)/((0.3/AK74)+(0.7/AL74)) -> #N/A | AN74: =(0.95)/((0.3/AK74)+(0.7/AL74)) -> #N/A | AO74: =AM74-3 -> #N/A | AP74: 60 | AQ74: =0.95*AP74 -> 57 | AR74: =AQ74-5 -> 52 | AS74: =AA74+AP74 -> 60 | AT74: =IFERROR(TODAY()-AA74,"") -> 45895 | BC74: CANCELLED | BD74: Awaiting reply kay Monica, for confirmation ng issue | BE74: =AA74+15 -> 15 | BF74: =IF(ISBLANK(AA74),0,IF(ISBLANK(BH74),(BE74-$L$1),(BH74-BE74))) -> 0 | BQ74: Y | BY74: 45155 | BZ74: CX8-0211, CX8-8131, 518095, CY9-0203 | CA74: =IF(AY74="Y",BA74,"0") -> 0 | CB74: =AC74-CA74 -> -45148.444 | CC74: =BA74 -> 0 | CD74: =AC74-BA74 -> -45148.444 | CE74: =(0.3)*(CD74/AK74)+(0.7)*(CD74/AL74) -> #N/A | CF74: =IF(AA74="","0",$CF$1-AA74) -> 0 | CH74: =(0.3)*(($CF$1-W74)/AK74)+(0.7)*(($CF$1-W74)/AL74) -> #N/A | CI74: =CH74-CG74 -> #N/A | CJ74: =CF74/AP74 -> 0 | CK74: =IF(AA74>0,"",$CK$1-W74) -> 707.55556 | CL74: =IF(R74="NEW","REV","NON-REV") -> NON-REV | CM74: =IF(CK74="","",IF(CK74<91,"0-3 MONTHS",(IF(CK74<181,"4-6 MONTHS",(IF(CK74<271,"7-9 MONTHS",IF(CK74>270,"10 MONTHS AND ABOVE",))))))) -> 10 MONTHS AND ABOVE | CP74: =IF(CQ74,"NTC ISSUED","FOR ISSUANCE") -> FOR ISSUANCE | CS74: =IF(AND(CQ74=0,CR74=0), "0",IF(CR74,(CR74-CQ74),TODAY()-CQ74)) -> 0 | CW74: 'X23072866920', | CX74: =VLOOKUP(E74,'[1]List of Work Orders'!$A:$I,9,FALSE) -> ME155242 | DC74: =VLOOKUP(E74,'[2]List of Work Orders'!$A:$F,6,FALSE) -> PCAN | DS74: RONILO GANGE JR.
A75: 45181 | B75: 45169 | C75: Y | D75: HMB | E75: R22633190 | F75: CANDIE CHUA CO. | G75: BLK 8, PALM COAST MARINA, PARANAQUE | H75: PARAÑAQUE CITY | I75: PARAÑAQUE | J75: For Sched September 26, 2023 survey/digging; pole location issue Update as of October 28. Issue on HOA and Customer not yet conduct meeting to resolve the issue | K75: W/ ISSUE | L75: ECOM | M75: INPRG | N75: Ronilo Gange Jr. | O75: 85.5844 | P75: 185.89 | Q75: 0 | R75: RELOC | S75: 258760.27 | T75: 91241.75 | V75: =U75/T75 -> 0 | W75: 45169.519 | X75: 45174 | Y75: 45174 | AC75: =AA75-W75 -> -45169.519 | AD75: =AA75-X75 -> -45174 | AE75: =AB75-AA75 -> 0 | AF75: =W75+AO75 -> 45190.726 | AG75: =W75+AN75 -> 45200.181 | AH75: =W75+50 -> 45219.519 | AI75: =(0.3)*(AC75/AK75)+(0.7)*(AC75/AL75) -> -1399.483 | AJ75: =AE75/AP75 -> 0 | AK75: =IF(P75<51,20,(IF(P75<101,23,(IF(P75<201,26,IF(P75<301,28,IF(P75<401,30,(IF(P75<501,32,(IF(P75<1001,40,50))))))))))) -> 26 | AL75: =IF(Q75<51,36,(IF(Q75<101,34,(IF(Q75<201,32,IF(Q75<301,30,IF(Q75<401,28,(IF(Q75<501,26,(IF(Q75<1001,23,20))))))))))) -> 36 | AM75: =(0.75)/((0.3/AK75)+(0.7/AL75)) -> 24.206897 | AN75: =(0.95)/((0.3/AK75)+(0.7/AL75)) -> 30.662069 | AO75: =AM75-3 -> 21.206897 | AP75: 60 | AQ75: =0.95*AP75 -> 57 | AR75: =AQ75-5 -> 52 | AS75: =AA75+AP75 -> 60 | AT75: =IFERROR(TODAY()-AA75,"") -> 45895 | BE75: =AA75+15 -> 15 | BF75: =IF(ISBLANK(AA75),0,IF(ISBLANK(BH75),(BE75-$L$1),(BH75-BE75))) -> 0 | BQ75: Y | BY75: 45181 | BZ75: B4-2049, 113551, B4-8013, B4-5058, B4-2048 | CA75: =IF(AY75="Y",BA75,"0") -> 0 | CB75: =AC75-CA75 -> -45169.519 | CC75: =BA75 -> 0 | CD75: =AC75-BA75 -> -45169.519 | CE75: =(0.3)*(CD75/AK75)+(0.7)*(CD75/AL75) -> -1399.483 | CF75: =IF(AA75="","0",$CF$1-AA75) -> 0 | CH75: =(0.3)*(($CF$1-W75)/AK75)+(0.7)*(($CF$1-W75)/AL75) -> 21.671962 | CI75: =CH75-CG75 -> 21.671962 | CJ75: =CF75/AP75 -> 0 | CK75: =IF(AA75>0,"",$CK$1-W75) -> 686.48125 | CL75: =IF(R75="NEW","REV","NON-REV") -> NON-REV | CM75: =IF(CK75="","",IF(CK75<91,"0-3 MONTHS",(IF(CK75<181,"4-6 MONTHS",(IF(CK75<271,"7-9 MONTHS",IF(CK75>270,"10 MONTHS AND ABOVE",))))))) -> 10 MONTHS AND ABOVE | CP75: =IF(CQ75,"NTC ISSUED","FOR ISSUANCE") -> FOR ISSUANCE | CS75: =IF(AND(CQ75=0,CR75=0), "0",IF(CR75,(CR75-CQ75),TODAY()-CQ75)) -> 0 | CW75: 'R22633190', | CX75: =VLOOKUP(E75,'[1]List of Work Orders'!$A:$I,9,FALSE) -> ME155242 | DC75: =VLOOKUP(E75,'[2]List of Work Orders'!$A:$F,6,FALSE) -> INPRG | DS75: Jenneth Madrid
A76: 45197 | B76: N/A | D76: CBG | E76: P2210140139 | F76: ECP-SR:, ASEANA ,DEVT OF 115KV-34.5KV GIS SS Station Service | G76: BELLE, ASEANA BUSINESS PARK, PARANAQUE | H76: PARAÑAQUE CITY | I76: PARAÑAQUE | J76: pole staking 10/13/2023, 02/07/2024 -With revision and for approval of ASEANA 3/26/24: Approved design by ABPEA -to request for another joint survey and pole staking -VJCto secure and pay for permit after the approval of revised plan 6/6/24 - for payment of permit c/o VJC 7/11/24 - VJCpaid permit 7/15/24 - ABPEA released working permit & gate pass permit FOR ENERGIZATION WITH CONJ. WO FROM C2 | K76: W/O ISSUE | L76: VJC | M76: FCOMP | N76: Jenneth Madrid | O76: 334.68 | P76: 445.08 | Q76: 68 | R76: ECP | S76: 1162251.7 | T76: 245180.25 | V76: =U76/T76 -> 0 | W76: 45181.484 | X76: 45195 | Y76: 45194 | AA76: 45675 | AC76: =AA76-W76 -> 493.51597 | AD76: =AA76-X76 -> 480 | AE76: =AB76-AA76 -> -45675 | AF76: =W76+AO76 -> 45203.515 | AG76: =W76+AN76 -> 45213.19 | AH76: =W76+50 -> 45231.484 | AI76: =(0.3)*(AC76/AK76)+(0.7)*(AC76/AL76) -> 14.787335 | AJ76: =AE76/AP76 -> -761.25 | AK76: =IF(P76<51,20,(IF(P76<101,23,(IF(P76<201,26,IF(P76<301,28,IF(P76<401,30,(IF(P76<501,32,(IF(P76<1001,40,50))))))))))) -> 32 | AL76: =IF(Q76<51,36,(IF(Q76<101,34,(IF(Q76<201,32,IF(Q76<301,30,IF(Q76<401,28,(IF(Q76<501,26,(IF(Q76<1001,23,20))))))))))) -> 34 | AM76: =(0.75)/((0.3/AK76)+(0.7/AL76)) -> 25.030675 | AN76: =(0.95)/((0.3/AK76)+(0.7/AL76)) -> 31.705521 | AO76: =AM76-3 -> 22.030675 | AP76: 60 | AQ76: =0.95*AP76 -> 57 | AR76: =AQ76-5 -> 52 | AS76: =AA76+AP76 -> 45735 | AT76: =IFERROR(TODAY()-AA76,"") -> 220 | BC76: NO COC | BE76: =AA76+15 -> 45690 | BF76: =IF(ISBLANK(AA76),0,IF(ISBLANK(BH76),(BE76-$L$1),(BH76-BE76))) -> #VALUE! | BQ76: Y | BY76: 45198 | BZ76: C5-5609, C5-8032, C5-8033, C5-8034, C5-8035, C5-8001, 514027 | CA76: =IF(AY76="Y",BA76,"0") -> 0 | CB76: =AC76-CA76 -> 493.51597 | CC76: =BA76 -> 0 | CD76: =AC76-BA76 -> 493.51597 | CE76: =(0.3)*(CD76/AK76)+(0.7)*(CD76/AL76) -> 14.787335 | CF76: =IF(AA76="","0",$CF$1-AA76) -> 194 | CH76: =(0.3)*(($CF$1-W76)/AK76)+(0.7)*(($CF$1-W76)/AL76) -> 20.600203 | CI76: =CH76-CG76 -> 20.600203 | CJ76: =CF76/AP76 -> 3.2333333 | CK76: =IF(AA76>0,"",$CK$1-W76) | CL76: =IF(R76="NEW","REV","NON-REV") -> NON-REV | CM76: =IF(CK76="","",IF(CK76<91,"0-3 MONTHS",(IF(CK76<181,"4-6 MONTHS",(IF(CK76<271,"7-9 MONTHS",IF(CK76>270,"10 MONTHS AND ABOVE",))))))) | CP76: =IF(CQ76,"NTC ISSUED","FOR ISSUANCE") -> FOR ISSUANCE | CS76: =IF(AND(CQ76=0,CR76=0), "0",IF(CR76,(CR76-CQ76),TODAY()-CQ76)) -> 0 | CW76: 'P2210140139', | CX76: =VLOOKUP(E76,'[1]List of Work Orders'!$A:$I,9,FALSE) -> ME185284 | DC76: =VLOOKUP(E76,'[2]List of Work Orders'!$A:$F,6,FALSE) -> FCOMP | DS76: RONILO GANGE JR.
A77: 45198 | B77: 45196 | D77: HMB | E77: X23072873118 | F77: JOSEPH T. CHUA | G77: NARRA, LAKEVIEW HOMES I, MUNTINLUPA | H77: MUNTINLUPA CITY | I77: PARAÑAQUE | J77: HOA claiming that they owned the property not by LGU (on-going return of surplus materials) FOR CANCELLATION | K77: FOR CANCELLATION | L77: ECOM | M77: PCAN3 | N77: Ronilo Gange Jr. | O77: 262.9633 | P77: #N/A | Q77: 86 | R77: NEW | S77: 1509543.7 | T77: 257509.03 | V77: =U77/T77 -> 0 | W77: 45195.382 | X77: 45198 | Y77: 45196 | AC77: =AA77-W77 -> -45195.382 | AD77: =AA77-X77 -> -45198 | AE77: =AB77-AA77 -> 0 | AF77: =W77+AO77 -> #N/A | AG77: =W77+AN77 -> #N/A | AH77: =W77+50 -> 45245.382 | AI77: =(0.3)*(AC77/AK77)+(0.7)*(AC77/AL77) -> #N/A | AJ77: =AE77/AP77 -> 0 | AK77: =IF(P77<51,20,(IF(P77<101,23,(IF(P77<201,26,IF(P77<301,28,IF(P77<401,30,(IF(P77<501,32,(IF(P77<1001,40,50))))))))))) -> #N/A | AL77: =IF(Q77<51,36,(IF(Q77<101,34,(IF(Q77<201,32,IF(Q77<301,30,IF(Q77<401,28,(IF(Q77<501,26,(IF(Q77<1001,23,20))))))))))) -> 34 | AM77: =(0.75)/((0.3/AK77)+(0.7/AL77)) -> #N/A | AN77: =(0.95)/((0.3/AK77)+(0.7/AL77)) -> #N/A | AO77: =AM77-3 -> #N/A | AP77: 60 | AQ77: =0.95*AP77 -> 57 | AR77: =AQ77-5 -> 52 | AS77: =AA77+AP77 -> 60 | AT77: =IFERROR(TODAY()-AA77,"") -> 45895 | BC77: ON GOING MAT RETURN | BE77: =AA77+15 -> 15 | BF77: =IF(ISBLANK(AA77),0,IF(ISBLANK(BH77),(BE77-$L$1),(BH77-BE77))) -> 0 | BQ77: Y | BY77: 45201 | BZ77: DR1-1524, ALB1-1297, ALB1-1939, DS1-8036, DS1-8037, DS1-8038, 518136, DS1-8039, DR1-1109, DS1-8040 | CA77: =IF(AY77="Y",BA77,"0") -> 0 | CB77: =AC77-CA77 -> -45195.382 | CC77: =BA77 -> 0 | CD77: =AC77-BA77 -> -45195.382 | CE77: =(0.3)*(CD77/AK77)+(0.7)*(CD77/AL77) -> #N/A | CF77: =IF(AA77="","0",$CF$1-AA77) -> 0 | CH77: =(0.3)*(($CF$1-W77)/AK77)+(0.7)*(($CF$1-W77)/AL77) -> #N/A | CI77: =CH77-CG77 -> #N/A | CJ77: =CF77/AP77 -> 0 | CK77: =IF(AA77>0,"",$CK$1-W77) -> 660.61806 | CL77: =IF(R77="NEW","REV","NON-REV") -> REV | CM77: =IF(CK77="","",IF(CK77<91,"0-3 MONTHS",(IF(CK77<181,"4-6 MONTHS",(IF(CK77<271,"7-9 MONTHS",IF(CK77>270,"10 MONTHS AND ABOVE",))))))) -> 10 MONTHS AND ABOVE | CN77: 45839 | CO77: 92555.66 | CP77: =IF(CQ77,"NTC ISSUED","FOR ISSUANCE") -> NTC ISSUED | CQ77: 45841 | CS77: =IF(AND(CQ77=0,CR77=0), "0",IF(CR77,(CR77-CQ77),TODAY()-CQ77)) -> 54 | CW77: 'X23072873118', | CX77: =VLOOKUP(E77,'[1]List of Work Orders'!$A:$I,9,FALSE) -> ME155242 | DC77: =VLOOKUP(E77,'[2]List of Work Orders'!$A:$F,6,FALSE) -> PCAN3 | DS77: RONILO GANGE JR.
